Workbook

Sheet ReadMe
A1: Do NOT edit any formulas in the highligted columns, it will mess up the mapping. Only drag them down. Orange highlight means manually added (don't drag down).
A2: Final Tab | B2: The final tab is what is read into the dashboard as the CalSim to WEAP map. It uses a combination of all variables from the dashboard (historical and planning FV files) - unfilter it to see all of them. Common name mapping is also planned to be added. This tab shouldn't be edited. Orange highlighted rows are duplicate CalSim variables (either in both SacWAM and SJWAM or duplicated in the mapping tab) - rows are copied from the Duplicated tab (hidden).
A6: Mapping Tab | B6: The non-highlighted columns come from Sac and SJWAM post-processors which mapped CalSim to WEAP variables. Add more mapping/rows as needed and drag down the highlighted column's formulas. Evaporation, applied water demand, and groundwater pumping variables were manually mapped (highlighted in orange). AW and GP variables were mapped by DU using the DU Map tab (hidden).
A10: WEAP Tab | B10: The non-highlighted columns are what are exported from the WEAP model favorites (Sac and SJWAM). If new favorites are added, you will need to export the data and add it, then drag down the highlighted column's formulas. Use the scripts in the input_files/WEAP_CalSim folder. Export the units in the equivalent CalSim variable's units. Calculated variables or data without an ObjID are given a synthetic ObjID of -999 and may need to be updated in the code.
A14: WEAP Favorites Tab | B14: This tab instructs what favorites to set in WEAP and what to call them (don't add the favorites to a folder). I exported everything in TAF. Update these as needed (and add the variables to the WEAP tab). Only the CSVs listed in the CSV File column are what are used to create the final CalSim-formatted CSV which goes into the data folder and onto the dashboard. Red text means the favorite name is different than the default. Green highlighted ones are added, while red should be in the future (unfilter the CSV File column).
A20: A note on how the mapping works:
A21: "Match Key" ignores the number before the \ (unless it is a reach)
A22: "Match Var" only looks at the number before the \ and anything following after (unless it is a headflow or reach)
A23: First, it tries to match the "Match Key" in the WEAP and Mapping tabs, then if there is still no match, it looks at the "Match Var"
A24: Reasoning and dashboard logic:
A25: The numbers before the \ change between models when anything is added or changed. It is assumed the ObjID does not change, but can be duplicated for different favorites.
A26: For data without a -999 ObjID, the dashboard merges on the ObjID and WEAP Favorite to convert to CalSim format.
A27: Data with a -999 ObjID merge on the WEAP Variable and WEAP Favorite.

Sheet Final
A1: CalSim Variable | B1: CalSim Kind | C1: ObjID | D1: WEAP Variable | E1: WEAP Model | F1: WEAP Favorite
A2: SWP_PERCENT_ACT | B2: ALIAS | C2: =_xlfn.XLOOKUP($A2,Mapping!$A:$A,Mapping!$D:$D) -> #N/A | D2: =_xlfn.XLOOKUP($A2,Mapping!$A:$A,Mapping!$E:$E) -> #N/A | E2: =_xlfn.XLOOKUP($A2,Mapping!$A:$A,Mapping!$C:$C) -> #N/A | F2: =_xlfn.XLOOKUP($A2,Mapping!$A:$A,Mapping!$G:$G) -> #N/A
A3: AW_02_NA | B3: APPLIED-WATER | C3: =_xlfn.XLOOKUP($A3,Mapping!$A:$A,Mapping!$D:$D) -> -999 | D3: =_xlfn.XLOOKUP($A3,Mapping!$A:$A,Mapping!$E:$E) -> A_02_NA | E3: =_xlfn.XLOOKUP($A3,Mapping!$A:$A,Mapping!$C:$C) -> SacWAM | F3: =_xlfn.XLOOKUP($A3,Mapping!$A:$A,Mapping!$G:$G) -> Theoretical Catchment Irrigation Demand
A4: AW_02_PA | B4: APPLIED-WATER | C4: =_xlfn.XLOOKUP($A4,Mapping!$A:$A,Mapping!$D:$D) -> -999 | D4: =_xlfn.XLOOKUP($A4,Mapping!$A:$A,Mapping!$E:$E) -> A_02_PA | E4: =_xlfn.XLOOKUP($A4,Mapping!$A:$A,Mapping!$C:$C) -> SacWAM | F4: =_xlfn.XLOOKUP($A4,Mapping!$A:$A,Mapping!$G:$G) -> Theoretical Catchment Irrigation Demand
A5: AW_02_SA | B5: APPLIED-WATER | C5: =_xlfn.XLOOKUP($A5,Mapping!$A:$A,Mapping!$D:$D) -> -999 | D5: =_xlfn.XLOOKUP($A5,Mapping!$A:$A,Mapping!$E:$E) -> A_02_SA | E5: =_xlfn.XLOOKUP($A5,Mapping!$A:$A,Mapping!$C:$C) -> SacWAM | F5: =_xlfn.XLOOKUP($A5,Mapping!$A:$A,Mapping!$G:$G) -> Theoretical Catchment Irrigation Demand
A6: AW_03_NA | B6: APPLIED-WATER | C6: =_xlfn.XLOOKUP($A6,Mapping!$A:$A,Mapping!$D:$D) -> -999 | D6: =_xlfn.XLOOKUP($A6,Mapping!$A:$A,Mapping!$E:$E) -> A_03_NA | E6: =_xlfn.XLOOKUP($A6,Mapping!$A:$A,Mapping!$C:$C) -> SacWAM | F6: =_xlfn.XLOOKUP($A6,Mapping!$A:$A,Mapping!$G:$G) -> Theoretical Catchment Irrigation Demand
A7: AW_03_PA | B7: APPLIED-WATER | C7: =_xlfn.XLOOKUP($A7,Mapping!$A:$A,Mapping!$D:$D) -> -999 | D7: =_xlfn.XLOOKUP($A7,Mapping!$A:$A,Mapping!$E:$E) -> A_03_PA | E7: =_xlfn.XLOOKUP($A7,Mapping!$A:$A,Mapping!$C:$C) -> SacWAM | F7: =_xlfn.XLOOKUP($A7,Mapping!$A:$A,Mapping!$G:$G) -> Theoretical Catchment Irrigation Demand
A8: AW_03_SA | B8: APPLIED-WATER | C8: =_xlfn.XLOOKUP($A8,Mapping!$A:$A,Mapping!$D:$D) -> -999 | D8: =_xlfn.XLOOKUP($A8,Mapping!$A:$A,Mapping!$E:$E) -> A_03_SA | E8: =_xlfn.XLOOKUP($A8,Mapping!$A:$A,Mapping!$C:$C) -> SacWAM | F8: =_xlfn.XLOOKUP($A8,Mapping!$A:$A,Mapping!$G:$G) -> Theoretical Catchment Irrigation Demand
A9: AW_04_NA | B9: APPLIED-WATER | C9: =_xlfn.XLOOKUP($A9,Mapping!$A:$A,Mapping!$D:$D) -> -999 | D9: =_xlfn.XLOOKUP($A9,Mapping!$A:$A,Mapping!$E:$E) -> A_04_06_NA2 | E9: =_xlfn.XLOOKUP($A9,Mapping!$A:$A,Mapping!$C:$C) -> SacWAM | F9: =_xlfn.XLOOKUP($A9,Mapping!$A:$A,Mapping!$G:$G) -> Theoretical Catchment Irrigation Demand
A10: AW_04_PA1 | B10: APPLIED-WATER | C10: =_xlfn.XLOOKUP($A10,Mapping!$A:$A,Mapping!$D:$D) -> -999 | D10: =_xlfn.XLOOKUP($A10,Mapping!$A:$A,Mapping!$E:$E) -> A_04_06_PA1 | E10: =_xlfn.XLOOKUP($A10,Mapping!$A:$A,Mapping!$C:$C) -> SacWAM | F10: =_xlfn.XLOOKUP($A10,Mapping!$A:$A,Mapping!$G:$G) -> Theoretical Catchment Irrigation Demand
A11: AW_04_PA2 | B11: APPLIED-WATER | C11: =_xlfn.XLOOKUP($A11,Mapping!$A:$A,Mapping!$D:$D) -> -999 | D11: =_xlfn.XLOOKUP($A11,Mapping!$A:$A,Mapping!$E:$E) -> A_04_06_PA2 | E11: =_xlfn.XLOOKUP($A11,Mapping!$A:$A,Mapping!$C:$C) -> SacWAM | F11: =_xlfn.XLOOKUP($A11,Mapping!$A:$A,Mapping!$G:$G) -> Theoretical Catchment Irrigation Demand
A12: AW_05_NA | B12: APPLIED-WATER | C12: =_xlfn.XLOOKUP($A12,Mapping!$A:$A,Mapping!$D:$D) -> -999 | D12: =_xlfn.XLOOKUP($A12,Mapping!$A:$A,Mapping!$E:$E) -> A_05_NA | E12: =_xlfn.XLOOKUP($A12,Mapping!$A:$A,Mapping!$C:$C) -> SacWAM | F12: =_xlfn.XLOOKUP($A12,Mapping!$A:$A,Mapping!$G:$G) -> Theoretical Catchment Irrigation Demand
A13: AW_06_NA | B13: APPLIED-WATER | C13: =_xlfn.XLOOKUP($A13,Mapping!$A:$A,Mapping!$D:$D) -> #N/A | D13: =_xlfn.XLOOKUP($A13,Mapping!$A:$A,Mapping!$E:$E) -> #N/A | E13: =_xlfn.XLOOKUP($A13,Mapping!$A:$A,Mapping!$C:$C) -> #N/A | F13: =_xlfn.XLOOKUP($A13,Mapping!$A:$A,Mapping!$G:$G) -> #N/A
... A618: C_CFS001 | B618: CHANNEL | C618: =_xlfn.XLOOKUP($A618,Mapping!$A:$A,Mapping!$D:$D) | D618: =_xlfn.XLOOKUP($A618,Mapping!$A:$A,Mapping!$E:$E) | E618: =_xlfn.XLOOKUP($A618,Mapping!$A:$A,Mapping!$C:$C) -> SJWAM | F618: =_xlfn.XLOOKUP($A618,Mapping!$A:$A,Mapping!$G:$G)
A619: C_MFT011 | B619: CHANNEL | C619: 14306 | D619: Hell Hole Tunnel 0 \ Headflow | E619: SacWAM | F619: Streamflow (below node or reach listed) | G619: Duplicate
A620: C_CMN006 | B620: CHANNEL | C620: 13975 | D620: Camino Conduit 0 \ Headflow | E620: SacWAM | F620: Streamflow (below node or reach listed) | G620: Duplicate
A621: C_CAA003 | B621: CHANNEL | C621: 6638 | D621: California Aqueduct 0 \ Headflow | E621: SacWAM | F621: Streamflow (below node or reach listed) | G621: Duplicate
A622: C_NFA022 | B622: CHANNEL | C622: 6643 | D622: North Fork American River 15 \ I_NFA022 Inflow | E622: SacWAM | F622: Streamflow (below node or reach listed) | G622: Duplicate
A623: C_SFA030 | B623: CHANNEL | C623: 6170 | D623: South Fork American River 47 \ SF American nr Placerville | E623: SacWAM | F623: Streamflow (below node or reach listed) | G623: Duplicate
A624: C_BRR066 | B624: CHANNEL | C624: 10942 | D624: Bear River 5 \ Drum Afterbay | E624: SacWAM | F624: Streamflow (below node or reach listed) | G624: Duplicate
A625: C_TTC002 | B625: CHANNEL | C625: 5019 | D625: Toadtown Canal 0 \ Headflow | E625: SacWAM | F625: Streamflow (below node or reach listed) | G625: Duplicate
A626: C_TAB000 | B626: CHANNEL | C626: 4427 | D626: Power Canal 7 \ Thermalito Afterbay | E626: SacWAM | F626: Streamflow (below node or reach listed) | G626: Duplicate
A627: C_BTL006 | B627: CHANNEL | C627: 12490 | D627: Battle Creek 11 \ SWRCB Battle Creek | E627: SacWAM | F627: Streamflow (below node or reach listed) | G627: Duplicate
A628: C_PYN001 | B628: CHANNEL | C628: 5821 | D628: Paynes Creek 5 \ I_PYN001 Inflow | E628: SacWAM | F628: Streamflow (below node or reach listed) | G628: Duplicate
A629: C_SJR070 | B629: CHANNEL | C629: 9267 | D629: San Joaquin River 1 \ Inflow at Vernalis Inflow | E629: SacWAM | F629: Streamflow (below node or reach listed) | G629: Duplicate
A630: C_MOK034 | B630: CHANNEL | C630: 12533 | D630: Mokelumne River 43 \ SWRCB Mokelumne River | E630: SacWAM | F630: Streamflow (below node or reach listed) | G630: Duplicate
... A648: C_EBP042 | B648: CHANNEL | C648: 15237 | D648: Eastside Bypass 41 \ Deadman Creek Inflow | E648: SJWAM | F648: Streamflow (below node or reach listed) | G648: Duplicate
A649: C_FCS006 | B649: CHANNEL | E649: SJWAM | G649: Duplicate
A650: C_EBP033 | B650: CHANNEL | E650: SJWAM | G650: Duplicate
A651: C_CAA003 | B651: CHANNEL | C651: 21633 | D651: California Aqueduct 3 \ Withdrawal Node 44 | E651: SJWAM | F651: Streamflow (below node or reach listed) | G651: Duplicate
A652: C_EBP050 | B652: CHANNEL | E652: SJWAM | G652: Duplicate
A653: C_DMC003 | B653: CHANNEL | C653: 16811 | D653: Delta Mendota Canal 1 \ CVP Boundary Condition | E653: SJWAM | F653: Streamflow (below node or reach listed) | G653: Duplicate
A654: C_SLUIS_CVP | B654: CHANNEL | E654: SJWAM | G654: Duplicate
A655: C_CVT009 | B655: CHANNEL | C655: 19423 | D655: Collierville Tunnel 3 \ OPS Collierville Tunnel | E655: SJWAM | F655: Streamflow (below node or reach listed) | G655: Duplicate
A656: SG128_ORT014_19 | B656: CHANNEL-SEEPAGE | C656: =_xlfn.XLOOKUP($A656,Mapping!$A:$A,Mapping!$D:$D) -> #N/A | D656: =_xlfn.XLOOKUP($A656,Mapping!$A:$A,Mapping!$E:$E) -> #N/A | E656: =_xlfn.XLOOKUP($A656,Mapping!$A:$A,Mapping!$C:$C) -> #N/A | F656: =_xlfn.XLOOKUP($A656,Mapping!$A:$A,Mapping!$G:$G) -> #N/A
A657: SG129_ORT009_19 | B657: CHANNEL-SEEPAGE | C657: =_xlfn.XLOOKUP($A657,Mapping!$A:$A,Mapping!$D:$D) -> #N/A | D657: =_xlfn.XLOOKUP($A657,Mapping!$A:$A,Mapping!$E:$E) -> #N/A | E657: =_xlfn.XLOOKUP($A657,Mapping!$A:$A,Mapping!$C:$C) -> #N/A | F657: =_xlfn.XLOOKUP($A657,Mapping!$A:$A,Mapping!$G:$G) -> #N/A
A658: SG130_ORT001_19 | B658: CHANNEL-SEEPAGE | C658: =_xlfn.XLOOKUP($A658,Mapping!$A:$A,Mapping!$D:$D) -> #N/A | D658: =_xlfn.XLOOKUP($A658,Mapping!$A:$A,Mapping!$E:$E) -> #N/A | E658: =_xlfn.XLOOKUP($A658,Mapping!$A:$A,Mapping!$C:$C) -> #N/A | F658: =_xlfn.XLOOKUP($A658,Mapping!$A:$A,Mapping!$G:$G) -> #N/A
A659: SG51_FSL012_4 | B659: CHANNEL-SEEPAGE | C659: =_xlfn.XLOOKUP($A659,Mapping!$A:$A,Mapping!$D:$D) -> #N/A | D659: =_xlfn.XLOOKUP($A659,Mapping!$A:$A,Mapping!$E:$E) -> #N/A | E659: =_xlfn.XLOOKUP($A659,Mapping!$A:$A,Mapping!$C:$C) -> #N/A | F659: =_xlfn.XLOOKUP($A659,Mapping!$A:$A,Mapping!$G:$G) -> #N/A
A660: SG52_FSL005_4 | B660: CHANNEL-SEEPAGE | C660: =_xlfn.XLOOKUP($A660,Mapping!$A:$A,Mapping!$D:$D) -> #N/A | D660: =_xlfn.XLOOKUP($A660,Mapping!$A:$A,Mapping!$E:$E) -> #N/A | E660: =_xlfn.XLOOKUP($A660,Mapping!$A:$A,Mapping!$C:$C) -> #N/A | F660: =_xlfn.XLOOKUP($A660,Mapping!$A:$A,Mapping!$G:$G) -> #N/A
A661: SG53_FSL005_4 | B661: CHANNEL-SEEPAGE | C661: =_xlfn.XLOOKUP($A661,Mapping!$A:$A,Mapping!$D:$D) -> #N/A | D661: =_xlfn.XLOOKUP($A661,Mapping!$A:$A,Mapping!$E:$E) -> #N/A | E661: =_xlfn.XLOOKUP($A661,Mapping!$A:$A,Mapping!$C:$C) -> #N/A | F661: =_xlfn.XLOOKUP($A661,Mapping!$A:$A,Mapping!$G:$G) -> #N/A
A662: CT_BENDBRIDGE_SV | B662: CLOSURE-TERM | C662: =_xlfn.XLOOKUP($A662,Mapping!$A:$A,Mapping!$D:$D) -> #N/A | D662: =_xlfn.XLOOKUP($A662,Mapping!$A:$A,Mapping!$E:$E) -> #N/A | E662: =_xlfn.XLOOKUP($A662,Mapping!$A:$A,Mapping!$C:$C) -> #N/A | F662: =_xlfn.XLOOKUP($A662,Mapping!$A:$A,Mapping!$G:$G) -> #N/A
A663: CT_BUTTECITY_SV | B663: CLOSURE-TERM | C663: =_xlfn.XLOOKUP($A663,Mapping!$A:$A,Mapping!$D:$D) -> #N/A | D663: =_xlfn.XLOOKUP($A663,Mapping!$A:$A,Mapping!$E:$E) -> #N/A | E663: =_xlfn.XLOOKUP($A663,Mapping!$A:$A,Mapping!$C:$C) -> #N/A | F663: =_xlfn.XLOOKUP($A663,Mapping!$A:$A,Mapping!$G:$G) -> #N/A
A664: CT_COLUSA_SV | B664: CLOSURE-TERM | C664: =_xlfn.XLOOKUP($A664,Mapping!$A:$A,Mapping!$D:$D) -> #N/A | D664: =_xlfn.XLOOKUP($A664,Mapping!$A:$A,Mapping!$E:$E) -> #N/A | E664: =_xlfn.XLOOKUP($A664,Mapping!$A:$A,Mapping!$C:$C) -> #N/A | F664: =_xlfn.XLOOKUP($A664,Mapping!$A:$A,Mapping!$G:$G) -> #N/A
A665: CT_DAVIS_SV | B665: CLOSURE-TERM | C665: =_xlfn.XLOOKUP($A665,Mapping!$A:$A,Mapping!$D:$D) -> #N/A | D665: =_xlfn.XLOOKUP($A665,Mapping!$A:$A,Mapping!$E:$E) -> #N/A | E665: =_xlfn.XLOOKUP($A665,Mapping!$A:$A,Mapping!$C:$C) -> #N/A | F665: =_xlfn.XLOOKUP($A665,Mapping!$A:$A,Mapping!$G:$G) -> #N/A
A666: CT_FAIROAKS_SV | B666: CLOSURE-TERM | C666: =_xlfn.XLOOKUP($A666,Mapping!$A:$A,Mapping!$D:$D) -> #N/A | D666: =_xlfn.XLOOKUP($A666,Mapping!$A:$A,Mapping!$E:$E) -> #N/A | E666: =_xlfn.XLOOKUP($A666,Mapping!$A:$A,Mapping!$C:$C) -> #N/A | F666: =_xlfn.XLOOKUP($A666,Mapping!$A:$A,Mapping!$G:$G) -> #N/A
A667: CT_FREEPORT_SV | B667: CLOSURE-TERM | C667: =_xlfn.XLOOKUP($A667,Mapping!$A:$A,Mapping!$D:$D) -> #N/A | D667: =_xlfn.XLOOKUP($A667,Mapping!$A:$A,Mapping!$E:$E) -> #N/A | E667: =_xlfn.XLOOKUP($A667,Mapping!$A:$A,Mapping!$C:$C) -> #N/A | F667: =_xlfn.XLOOKUP($A667,Mapping!$A:$A,Mapping!$G:$G) -> #N/A
... A692: CT_FREEPORT | B692: CLOSURE-TERM | C692: =_xlfn.XLOOKUP($A692,Mapping!$A:$A,Mapping!$D:$D) -> #N/A | D692: =_xlfn.XLOOKUP($A692,Mapping!$A:$A,Mapping!$E:$E) -> #N/A | E692: =_xlfn.XLOOKUP($A692,Mapping!$A:$A,Mapping!$C:$C) -> #N/A | F692: =_xlfn.XLOOKUP($A692,Mapping!$A:$A,Mapping!$G:$G) -> #N/A
A693: CT_MERCED_SV | B693: CLOSURE-TERM | E693: SJWAM | G693: Duplicate
A694: UF_CULOS | B694: CONSUMPTIVE-USE | C694: =_xlfn.XLOOKUP($A694,Mapping!$A:$A,Mapping!$D:$D) -> #N/A | D694: =_xlfn.XLOOKUP($A694,Mapping!$A:$A,Mapping!$E:$E) -> #N/A | E694: =_xlfn.XLOOKUP($A694,Mapping!$A:$A,Mapping!$C:$C) -> #N/A | F694: =_xlfn.XLOOKUP($A694,Mapping!$A:$A,Mapping!$G:$G) -> #N/A
A695: BEGDAY_CHSDV | B695: DEBUG | C695: =_xlfn.XLOOKUP($A695,Mapping!$A:$A,Mapping!$D:$D) -> #N/A | D695: =_xlfn.XLOOKUP($A695,Mapping!$A:$A,Mapping!$E:$E) -> #N/A | E695: =_xlfn.XLOOKUP($A695,Mapping!$A:$A,Mapping!$C:$C) -> #N/A | F695: =_xlfn.XLOOKUP($A695,Mapping!$A:$A,Mapping!$G:$G) -> #N/A
A696: BEGDAY_CNFDV | B696: DEBUG | C696: =_xlfn.XLOOKUP($A696,Mapping!$A:$A,Mapping!$D:$D) -> #N/A | D696: =_xlfn.XLOOKUP($A696,Mapping!$A:$A,Mapping!$E:$E) -> #N/A | E696: =_xlfn.XLOOKUP($A696,Mapping!$A:$A,Mapping!$C:$C) -> #N/A | F696: =_xlfn.XLOOKUP($A696,Mapping!$A:$A,Mapping!$G:$G) -> #N/A
A697: BEGDAY_ROEDV | B697: DEBUG | C697: =_xlfn.XLOOKUP($A697,Mapping!$A:$A,Mapping!$D:$D) -> #N/A | D697: =_xlfn.XLOOKUP($A697,Mapping!$A:$A,Mapping!$E:$E) -> #N/A | E697: =_xlfn.XLOOKUP($A697,Mapping!$A:$A,Mapping!$C:$C) -> #N/A | F697: =_xlfn.XLOOKUP($A697,Mapping!$A:$A,Mapping!$G:$G) -> #N/A
A698: ENDDAY_CHSDV | B698: DEBUG | C698: =_xlfn.XLOOKUP($A698,Mapping!$A:$A,Mapping!$D:$D) -> #N/A | D698: =_xlfn.XLOOKUP($A698,Mapping!$A:$A,Mapping!$E:$E) -> #N/A | E698: =_xlfn.XLOOKUP($A698,Mapping!$A:$A,Mapping!$C:$C) -> #N/A | F698: =_xlfn.XLOOKUP($A698,Mapping!$A:$A,Mapping!$G:$G) -> #N/A
A699: ENDDAY_CNFDV | B699: DEBUG | C699: =_xlfn.XLOOKUP($A699,Mapping!$A:$A,Mapping!$D:$D) -> #N/A | D699: =_xlfn.XLOOKUP($A699,Mapping!$A:$A,Mapping!$E:$E) -> #N/A | E699: =_xlfn.XLOOKUP($A699,Mapping!$A:$A,Mapping!$C:$C) -> #N/A | F699: =_xlfn.XLOOKUP($A699,Mapping!$A:$A,Mapping!$G:$G) -> #N/A
A700: ENDDAY_ROEDV | B700: DEBUG | C700: =_xlfn.XLOOKUP($A700,Mapping!$A:$A,Mapping!$D:$D) -> #N/A | D700: =_xlfn.XLOOKUP($A700,Mapping!$A:$A,Mapping!$E:$E) -> #N/A | E700: =_xlfn.XLOOKUP($A700,Mapping!$A:$A,Mapping!$C:$C) -> #N/A | F700: =_xlfn.XLOOKUP($A700,Mapping!$A:$A,Mapping!$G:$G) -> #N/A
A701: MODROEDAY | B701: DEBUG | C701: =_xlfn.XLOOKUP($A701,Mapping!$A:$A,Mapping!$D:$D) -> #N/A | D701: =_xlfn.XLOOKUP($A701,Mapping!$A:$A,Mapping!$E:$E) -> #N/A | E701: =_xlfn.XLOOKUP($A701,Mapping!$A:$A,Mapping!$C:$C) -> #N/A | F701: =_xlfn.XLOOKUP($A701,Mapping!$A:$A,Mapping!$G:$G) -> #N/A
A702: DP_WBATOTAL_10 | B702: DEEP-PERCOLATION | C702: =_xlfn.XLOOKUP($A702,Mapping!$A:$A,Mapping!$D:$D) -> #N/A | D702: =_xlfn.XLOOKUP($A702,Mapping!$A:$A,Mapping!$E:$E) -> #N/A | E702: =_xlfn.XLOOKUP($A702,Mapping!$A:$A,Mapping!$C:$C) -> #N/A | F702: =_xlfn.XLOOKUP($A702,Mapping!$A:$A,Mapping!$G:$G) -> #N/A
A703: DP_WBATOTAL_11 | B703: DEEP-PERCOLATION | C703: =_xlfn.XLOOKUP($A703,Mapping!$A:$A,Mapping!$D:$D) -> #N/A | D703: =_xlfn.XLOOKUP($A703,Mapping!$A:$A,Mapping!$E:$E) -> #N/A | E703: =_xlfn.XLOOKUP($A703,Mapping!$A:$A,Mapping!$C:$C) -> #N/A | F703: =_xlfn.XLOOKUP($A703,Mapping!$A:$A,Mapping!$G:$G) -> #N/A
A704: DP_WBATOTAL_12 | B704: DEEP-PERCOLATION | C704: =_xlfn.XLOOKUP($A704,Mapping!$A:$A,Mapping!$D:$D) -> #N/A | D704: =_xlfn.XLOOKUP($A704,Mapping!$A:$A,Mapping!$E:$E) -> #N/A | E704: =_xlfn.XLOOKUP($A704,Mapping!$A:$A,Mapping!$C:$C) -> #N/A | F704: =_xlfn.XLOOKUP($A704,Mapping!$A:$A,Mapping!$G:$G) -> #N/A
A705: DP_WBATOTAL_13 | B705: DEEP-PERCOLATION | C705: =_xlfn.XLOOKUP($A705,Mapping!$A:$A,Mapping!$D:$D) -> #N/A | D705: =_xlfn.XLOOKUP($A705,Mapping!$A:$A,Mapping!$E:$E) -> #N/A | E705: =_xlfn.XLOOKUP($A705,Mapping!$A:$A,Mapping!$C:$C) -> #N/A | F705: =_xlfn.XLOOKUP($A705,Mapping!$A:$A,Mapping!$G:$G) -> #N/A
... A1390: D_LYONS_TCN000 | B1390: DIVERSION | C1390: =_xlfn.XLOOKUP($A1390,Mapping!$A:$A,Mapping!$D:$D) -> 20515 | D1390: =_xlfn.XLOOKUP($A1390,Mapping!$A:$A,Mapping!$E:$E) -> Tuolomne Canal 0 \ Headflow | E1390: =_xlfn.XLOOKUP($A1390,Mapping!$A:$A,Mapping!$C:$C) -> SJWAM | F1390: =_xlfn.XLOOKUP($A1390,Mapping!$A:$A,Mapping!$G:$G) -> Streamflow (below node or reach listed)
A1391: D_EDC021_EDP003 | B1391: DIVERSION | C1391: 12628 | D1391: El Dorado Akin Powerhouse 0 \ Headflow | E1391: SacWAM | F1391: Streamflow (below node or reach listed) | G1391: Duplicate
A1392: D_BSH003_CMN005 | B1392: DIVERSION | C1392: 13984 | D1392: Brush Creek Tunnel 0 \ Headflow | E1392: SacWAM | F1392: Streamflow (below node or reach listed) | G1392: Duplicate
A1393: D_GERLE_SFR006 | B1393: DIVERSION | C1393: 14042 | D1393: Gerle Canal 0 \ Headflow | E1393: SacWAM | F1393: Streamflow (below node or reach listed) | G1393: Duplicate
A1394: D_UNVLY_SLV017 | B1394: DIVERSION | C1394: 14300 | D1394: Union Valley Powerhouse 0 \ Headflow | E1394: SacWAM | F1394: Streamflow (below node or reach listed) | G1394: Duplicate
A1395: D_SFA040_WRT000 | B1395: DIVERSION | C1395: 13889 | D1395: White Rock Tunnel 0 \ Headflow | E1395: SacWAM | F1395: Streamflow (below node or reach listed) | G1395: Duplicate
A1396: D_NFA016_ABT002 | B1396: DIVERSION | C1396: 8471 | D1396: Auburn Tunnel 0 \ Headflow | E1396: SacWAM | F1396: Streamflow (below node or reach listed) | G1396: Duplicate
A1397: D_NTOMA_FSC003 | B1397: DIVERSION | C1397: 14623 | D1397: Folsom South Canal 0 \ Headflow | E1397: SacWAM | F1397: Streamflow (below node or reach listed) | G1397: Duplicate
A1398: D_LBR002_LBC001 | B1398: DIVERSION | C1398: 14635 | D1398: Lower Boardman Canal 0 \ Headflow | E1398: SacWAM | F1398: Streamflow (below node or reach listed) | G1398: Duplicate
A1399: D_BRR050_BEC000 | B1399: DIVERSION | C1399: 6539 | D1399: Bear River Canal 0 \ Headflow | E1399: SacWAM | F1399: Streamflow (below node or reach listed) | G1399: Duplicate
A1400: D_LBR002_LBC001 | B1400: DIVERSION | C1400: 14635 | D1400: Lower Boardman Canal 0 \ Headflow | E1400: SacWAM | F1400: Streamflow (below node or reach listed) | G1400: Duplicate
A1401: D_SFF011_MNRRH | B1401: DIVERSION | C1401: 6898 | D1401: Miners Ranch Canal 0 \ Headflow | E1401: SacWAM | F1401: Streamflow (below node or reach listed) | G1401: Duplicate
A1402: D_OROVL_13_NU1 | B1402: DIVERSION | C1402: 8480 | D1402: Palermo Canal 0 \ Headflow | E1402: SacWAM | F1402: Streamflow (below node or reach listed) | G1402: Duplicate
... A1418: D_LWSTN_CCT011 | B1418: DIVERSION | C1418: 11833 | D1418: Clear Creek Tunnel 0 \ Headflow | E1418: SacWAM | F1418: Streamflow (below node or reach listed) | G1418: Duplicate
A1419: D_BKR004_NBA009 | B1419: DIVERSION | E1419: SacWAM | G1419: Duplicate
A1420: D_SHSTA_WTPJMS | B1420: DIVERSION | C1420: 7476 | D1420: Transmission Link from Shasta Lake to U_03_PU | E1420: SacWAM | F1420: Transmission Link Flow | G1420: Duplicate
A1421: D_SAC296_WTPFTH | B1421: DIVERSION | C1421: 8459 | D1421: Foothill WTP 0 \ Headflow | E1421: SacWAM | F1421: Streamflow (below node or reach listed) | G1421: Duplicate
A1422: D_SAC065_WTPBTB | B1422: DIVERSION | C1422: 7647 | D1422: Transmission Link from Sacramento River RM 065 to U_21_PU | E1422: SacWAM | F1422: Transmission Link Flow | G1422: Duplicate
A1423: D_SAC050_FPT013 | B1423: DIVERSION | C1423: 13077 | D1423: Freeport Pumping Plant 0 \ Headflow | E1423: SacWAM | F1423: Streamflow (below node or reach listed) | G1423: Duplicate
A1424: D_THRMF_11_NU1 | B1424: DIVERSION | C1424: 7538 | D1424: Transmission Link from Power Canal SWP water to U_11_NU1 | E1424: SacWAM | F1424: Transmission Link Flow | G1424: Duplicate
A1425: D_THRMF_12_NU1 | B1425: DIVERSION | C1425: 7550 | D1425: Transmission Link from Power Canal SWP water to U_12_13_NU1 | E1425: SacWAM | F1425: Transmission Link Flow | G1425: Duplicate
A1426: D_FTR031_WTPCYC | B1426: DIVERSION | C1426: 7595 | D1426: Transmission Link from Feather River RM 031 to U_16_PU | E1426: SacWAM | F1426: Transmission Link Flow | G1426: Duplicate
A1427: D_AMR007_WTPFBN | B1427: DIVERSION | C1427: 7717 | D1427: Fairbairn WTP 0 \ Headflow | E1427: SacWAM | F1427: Streamflow (below node or reach listed) | G1427: Duplicate
A1428: D_AMR017_WTPBJM | B1428: DIVERSION | C1428: 7737 | D1428: Bajamont WTP 0 \ Headflow | E1428: SacWAM | F1428: Streamflow (below node or reach listed) | G1428: Duplicate
A1429: D_FOLSM_WTPEDH | B1429: DIVERSION | C1429: 14621 | D1429: El Dorado Hills WTP 0 \ Headflow | E1429: SacWAM | F1429: Streamflow (below node or reach listed) | G1429: Duplicate
A1430: D_FOLSM_WTPFOL | B1430: DIVERSION | C1430: 7817 | D1430: Folsom WTP 0 \ Headflow | E1430: SacWAM | F1430: Streamflow (below node or reach listed) | G1430: Duplicate
A1431: D_FOLSM_WTPRSV | B1431: DIVERSION | C1431: 7795 | D1431: Roseville WTP 0 \ Headflow | E1431: SacWAM | F1431: Streamflow (below node or reach listed) | G1431: Duplicate
... A1447: D_SJR214_EBP001 | B1447: DIVERSION | C1447: 25273 | D1447: Chowchilla Bypass 0 \ Headflow | E1447: SJWAM | F1447: Streamflow (below node or reach listed) | G1447: Duplicate
A1448: D_SJR214_EBP001 | B1448: DIVERSION | E1448: SJWAM | G1448: Duplicate
A1449: D_SJR166_EBP032 | B1449: DIVERSION | E1449: SJWAM | G1449: Duplicate
A1450: D_DMC007_CAA009 | B1450: DIVERSION | E1450: SJWAM | G1450: Duplicate
A1451: D_CAA069_DMC070 | B1451: DIVERSION | E1451: SJWAM | G1451: Duplicate
A1452: D_DMC070_CAA069 | B1452: DIVERSION | E1452: SJWAM | G1452: Duplicate
A1453: D_NFS033_SDT000 | B1453: DIVERSION | C1453: 15434 | D1453: North Fork Stanislaus Diversion Tunnel 0 \ Headflow | E1453: SJWAM | F1453: Streamflow (below node or reach listed) | G1453: Duplicate
A1454: D_BVC007_BVT000 | B1454: DIVERSION | C1454: 15455 | D1454: Beaver Creek Diversion 0 \ Headflow | E1454: SJWAM | F1454: Streamflow (below node or reach listed) | G1454: Duplicate
A1455: D_DMC070_VLW008 | B1455: DIVERSION | E1455: SJWAM | G1455: Duplicate
A1456: D_CLV037_CACWD | B1456: DIVERSION | E1456: SJWAM | G1456: Duplicate
A1457: D_CLV026_60S_PA1 | B1457: DIVERSION | E1457: SJWAM | G1457: Duplicate
A1458: D_MCD055_62_NA6 | B1458: DIVERSION | E1458: SJWAM | G1458: Duplicate
A1459: D_MCD052_MID021 | B1459: DIVERSION | E1459: SJWAM | G1459: Duplicate
...

Sheet Mapping
A1: CalSim Variable | B1: WEAP Variable | C1: WEAP Model | D1: ObjID | E1: WEAP Variable | F1: WEAP Units | G1: WEAP Favorite | H1: Match Key | I1: Match Var
A2: Trinity River at Lewiston | B2: Trinity River at Lewiston | C2: SacWAM | D2: =IFERROR( _xlfn.XLOOKUP($H2,WEAP!$F:$F,WEAP!$A:$A), IF($I2="","",_xlfn.XLOOKUP($I2,WEAP!$G:$G,WEAP!$A:$A,"")) ) | E2: =IFERROR( _xlfn.XLOOKUP($H2,WEAP!$F:$F,WEAP!$B:$B), IF($I2="","",_xlfn.XLOOKUP($I2,WEAP!$G:$G,WEAP!$B:$B,"")) ) | F2: =IFERROR( _xlfn.XLOOKUP($H2,WEAP!$F:$F,WEAP!$C:$C), IF($I2="","",_xlfn.XLOOKUP($I2,WEAP!$G:$G,WEAP!$C:$C,"")) ) | G2: =IFERROR( _xlfn.XLOOKUP($H2,WEAP!$F:$F,WEAP!$E:$E), IF($I2="","",_xlfn.XLOOKUP($I2,WEAP!$G:$G,WEAP!$E:$E,"")) ) | H2: =IFERROR( _xlfn.LET( _xlpm.txt,TRIM(B2), _xlpm.before,TRIM(_xlfn.TEXTBEFORE(_xlpm.txt,"\",-1)), _xlpm.after,_xlfn.TEXTAFTER(_xlpm.txt,"\"), _xlpm.lastToken,TRIM(_xlfn.TEXTAFTER(_xlpm.before," ",-1)), _xlpm.isReach,LOWER(TRIM(_xlpm.after))="reach", _xlpm.cleaned, IF( ISNUMBER(--_xlpm.lastToken), _xlfn.TEXTBEFORE(_xlpm.before," ",-1) & " \ " & _xlpm.after, _xlpm.txt ), IF(_xlpm.isReach,_xlpm.txt,TRIM(_xlpm.cleaned)) ), B2 ) -> Trinity River at Lewiston | I2: =IFERROR( _xlfn.LET( _xlpm.txt,B2, _xlpm.before,TRIM(_xlfn.TEXTBEFORE(_xlpm.txt,"\")), _xlpm.after,TRIM(_xlfn.TEXTAFTER(_xlpm.txt,"\")), _xlpm.lastToken,TRIM(_xlfn.TEXTAFTER(_xlpm.before," ",-1)), _xlpm.isNum,IFERROR(ISNUMBER(--_xlpm.lastToken),FALSE), IF( OR( LOWER(_xlpm.after)="headflow", LOWER(_xlpm.after)="reach" ), "", IF( _xlpm.isNum, _xlpm.lastToken & " \ " & _xlpm.after, "" ) ) ), "" )
A3: Sacramento River at Shasta | B3: Sacramento River at Shasta | C3: SacWAM | D3: =IFERROR( _xlfn.XLOOKUP($H3,WEAP!$F:$F,WEAP!$A:$A), IF($I3="","",_xlfn.XLOOKUP($I3,WEAP!$G:$G,WEAP!$A:$A,"")) ) | E3: =IFERROR( _xlfn.XLOOKUP($H3,WEAP!$F:$F,WEAP!$B:$B), IF($I3="","",_xlfn.XLOOKUP($I3,WEAP!$G:$G,WEAP!$B:$B,"")) ) | F3: =IFERROR( _xlfn.XLOOKUP($H3,WEAP!$F:$F,WEAP!$C:$C), IF($I3="","",_xlfn.XLOOKUP($I3,WEAP!$G:$G,WEAP!$C:$C,"")) ) | G3: =IFERROR( _xlfn.XLOOKUP($H3,WEAP!$F:$F,WEAP!$E:$E), IF($I3="","",_xlfn.XLOOKUP($I3,WEAP!$G:$G,WEAP!$E:$E,"")) ) | H3: =IFERROR( _xlfn.LET( _xlpm.txt,TRIM(B3), _xlpm.before,TRIM(_xlfn.TEXTBEFORE(_xlpm.txt,"\",-1)), _xlpm.after,_xlfn.TEXTAFTER(_xlpm.txt,"\"), _xlpm.lastToken,TRIM(_xlfn.TEXTAFTER(_xlpm.before," ",-1)), _xlpm.isReach,LOWER(TRIM(_xlpm.after))="reach", _xlpm.cleaned, IF( ISNUMBER(--_xlpm.lastToken), _xlfn.TEXTBEFORE(_xlpm.before," ",-1) & " \ " & _xlpm.after, _xlpm.txt ), IF(_xlpm.isReach,_xlpm.txt,TRIM(_xlpm.cleaned)) ), B3 ) -> Sacramento River at Shasta | I3: =IFERROR( _xlfn.LET( _xlpm.txt,B3, _xlpm.before,TRIM(_xlfn.TEXTBEFORE(_xlpm.txt,"\")), _xlpm.after,TRIM(_xlfn.TEXTAFTER(_xlpm.txt,"\")), _xlpm.lastToken,TRIM(_xlfn.TEXTAFTER(_xlpm.before," ",-1)), _xlpm.isNum,IFERROR(ISNUMBER(--_xlpm.lastToken),FALSE), IF( OR( LOWER(_xlpm.after)="headflow", LOWER(_xlpm.after)="reach" ), "", IF( _xlpm.isNum, _xlpm.lastToken & " \ " & _xlpm.after, "" ) ) ), "" )
A4: Feather River at Oroville | B4: Feather River at Oroville | C4: SacWAM | D4: =IFERROR( _xlfn.XLOOKUP($H4,WEAP!$F:$F,WEAP!$A:$A), IF($I4="","",_xlfn.XLOOKUP($I4,WEAP!$G:$G,WEAP!$A:$A,"")) ) | E4: =IFERROR( _xlfn.XLOOKUP($H4,WEAP!$F:$F,WEAP!$B:$B), IF($I4="","",_xlfn.XLOOKUP($I4,WEAP!$G:$G,WEAP!$B:$B,"")) ) | F4: =IFERROR( _xlfn.XLOOKUP($H4,WEAP!$F:$F,WEAP!$C:$C), IF($I4="","",_xlfn.XLOOKUP($I4,WEAP!$G:$G,WEAP!$C:$C,"")) ) | G4: =IFERROR( _xlfn.XLOOKUP($H4,WEAP!$F:$F,WEAP!$E:$E), IF($I4="","",_xlfn.XLOOKUP($I4,WEAP!$G:$G,WEAP!$E:$E,"")) ) | H4: =IFERROR( _xlfn.LET( _xlpm.txt,TRIM(B4), _xlpm.before,TRIM(_xlfn.TEXTBEFORE(_xlpm.txt,"\",-1)), _xlpm.after,_xlfn.TEXTAFTER(_xlpm.txt,"\"), _xlpm.lastToken,TRIM(_xlfn.TEXTAFTER(_xlpm.before," ",-1)), _xlpm.isReach,LOWER(TRIM(_xlpm.after))="reach", _xlpm.cleaned, IF( ISNUMBER(--_xlpm.lastToken), _xlfn.TEXTBEFORE(_xlpm.before," ",-1) & " \ " & _xlpm.after, _xlpm.txt ), IF(_xlpm.isReach,_xlpm.txt,TRIM(_xlpm.cleaned)) ), B4 ) -> Feather River at Oroville | I4: =IFERROR( _xlfn.LET( _xlpm.txt,B4, _xlpm.before,TRIM(_xlfn.TEXTBEFORE(_xlpm.txt,"\")), _xlpm.after,TRIM(_xlfn.TEXTAFTER(_xlpm.txt,"\")), _xlpm.lastToken,TRIM(_xlfn.TEXTAFTER(_xlpm.before," ",-1)), _xlpm.isNum,IFERROR(ISNUMBER(--_xlpm.lastToken),FALSE), IF( OR( LOWER(_xlpm.after)="headflow", LOWER(_xlpm.after)="reach" ), "", IF( _xlpm.isNum, _xlpm.lastToken & " \ " & _xlpm.after, "" ) ) ), "" )
A5: Yuba River above Daguerre | B5: Yuba River above Daguerre | C5: SacWAM | D5: =IFERROR( _xlfn.XLOOKUP($H5,WEAP!$F:$F,WEAP!$A:$A), IF($I5="","",_xlfn.XLOOKUP($I5,WEAP!$G:$G,WEAP!$A:$A,"")) ) | E5: =IFERROR( _xlfn.XLOOKUP($H5,WEAP!$F:$F,WEAP!$B:$B), IF($I5="","",_xlfn.XLOOKUP($I5,WEAP!$G:$G,WEAP!$B:$B,"")) ) | F5: =IFERROR( _xlfn.XLOOKUP($H5,WEAP!$F:$F,WEAP!$C:$C), IF($I5="","",_xlfn.XLOOKUP($I5,WEAP!$G:$G,WEAP!$C:$C,"")) ) | G5: =IFERROR( _xlfn.XLOOKUP($H5,WEAP!$F:$F,WEAP!$E:$E), IF($I5="","",_xlfn.XLOOKUP($I5,WEAP!$G:$G,WEAP!$E:$E,"")) ) | H5: =IFERROR( _xlfn.LET( _xlpm.txt,TRIM(B5), _xlpm.before,TRIM(_xlfn.TEXTBEFORE(_xlpm.txt,"\",-1)), _xlpm.after,_xlfn.TEXTAFTER(_xlpm.txt,"\"), _xlpm.lastToken,TRIM(_xlfn.TEXTAFTER(_xlpm.before," ",-1)), _xlpm.isReach,LOWER(TRIM(_xlpm.after))="reach", _xlpm.cleaned, IF( ISNUMBER(--_xlpm.lastToken), _xlfn.TEXTBEFORE(_xlpm.before," ",-1) & " \ " & _xlpm.after, _xlpm.txt ), IF(_xlpm.isReach,_xlpm.txt,TRIM(_xlpm.cleaned)) ), B5 ) -> Yuba River above Daguerre | I5: =IFERROR( _xlfn.LET( _xlpm.txt,B5, _xlpm.before,TRIM(_xlfn.TEXTBEFORE(_xlpm.txt,"\")), _xlpm.after,TRIM(_xlfn.TEXTAFTER(_xlpm.txt,"\")), _xlpm.lastToken,TRIM(_xlfn.TEXTAFTER(_xlpm.before," ",-1)), _xlpm.isNum,IFERROR(ISNUMBER(--_xlpm.lastToken),FALSE), IF( OR( LOWER(_xlpm.after)="headflow", LOWER(_xlpm.after)="reach" ), "", IF( _xlpm.isNum, _xlpm.lastToken & " \ " & _xlpm.after, "" ) ) ), "" )
A6: Bear River at Camp Far West | B6: Bear River at Camp Far West | C6: SacWAM | D6: =IFERROR( _xlfn.XLOOKUP($H6,WEAP!$F:$F,WEAP!$A:$A), IF($I6="","",_xlfn.XLOOKUP($I6,WEAP!$G:$G,WEAP!$A:$A,"")) ) | E6: =IFERROR( _xlfn.XLOOKUP($H6,WEAP!$F:$F,WEAP!$B:$B), IF($I6="","",_xlfn.XLOOKUP($I6,WEAP!$G:$G,WEAP!$B:$B,"")) ) | F6: =IFERROR( _xlfn.XLOOKUP($H6,WEAP!$F:$F,WEAP!$C:$C), IF($I6="","",_xlfn.XLOOKUP($I6,WEAP!$G:$G,WEAP!$C:$C,"")) ) | G6: =IFERROR( _xlfn.XLOOKUP($H6,WEAP!$F:$F,WEAP!$E:$E), IF($I6="","",_xlfn.XLOOKUP($I6,WEAP!$G:$G,WEAP!$E:$E,"")) ) | H6: =IFERROR( _xlfn.LET( _xlpm.txt,TRIM(B6), _xlpm.before,TRIM(_xlfn.TEXTBEFORE(_xlpm.txt,"\",-1)), _xlpm.after,_xlfn.TEXTAFTER(_xlpm.txt,"\"), _xlpm.lastToken,TRIM(_xlfn.TEXTAFTER(_xlpm.before," ",-1)), _xlpm.isReach,LOWER(TRIM(_xlpm.after))="reach", _xlpm.cleaned, IF( ISNUMBER(--_xlpm.lastToken), _xlfn.TEXTBEFORE(_xlpm.before," ",-1) & " \ " & _xlpm.after, _xlpm.txt ), IF(_xlpm.isReach,_xlpm.txt,TRIM(_xlpm.cleaned)) ), B6 ) -> Bear River at Camp Far West | I6: =IFERROR( _xlfn.LET( _xlpm.txt,B6, _xlpm.before,TRIM(_xlfn.TEXTBEFORE(_xlpm.txt,"\")), _xlpm.after,TRIM(_xlfn.TEXTAFTER(_xlpm.txt,"\")), _xlpm.lastToken,TRIM(_xlfn.TEXTAFTER(_xlpm.before," ",-1)), _xlpm.isNum,IFERROR(ISNUMBER(--_xlpm.lastToken),FALSE), IF( OR( LOWER(_xlpm.after)="headflow", LOWER(_xlpm.after)="reach" ), "", IF( _xlpm.isNum, _xlpm.lastToken & " \ " & _xlpm.after, "" ) ) ), "" )
A7: American River at Folsom | B7: American River at Folsom | C7: SacWAM | D7: =IFERROR( _xlfn.XLOOKUP($H7,WEAP!$F:$F,WEAP!$A:$A), IF($I7="","",_xlfn.XLOOKUP($I7,WEAP!$G:$G,WEAP!$A:$A,"")) ) | E7: =IFERROR( _xlfn.XLOOKUP($H7,WEAP!$F:$F,WEAP!$B:$B), IF($I7="","",_xlfn.XLOOKUP($I7,WEAP!$G:$G,WEAP!$B:$B,"")) ) | F7: =IFERROR( _xlfn.XLOOKUP($H7,WEAP!$F:$F,WEAP!$C:$C), IF($I7="","",_xlfn.XLOOKUP($I7,WEAP!$G:$G,WEAP!$C:$C,"")) ) | G7: =IFERROR( _xlfn.XLOOKUP($H7,WEAP!$F:$F,WEAP!$E:$E), IF($I7="","",_xlfn.XLOOKUP($I7,WEAP!$G:$G,WEAP!$E:$E,"")) ) | H7: =IFERROR( _xlfn.LET( _xlpm.txt,TRIM(B7), _xlpm.before,TRIM(_xlfn.TEXTBEFORE(_xlpm.txt,"\",-1)), _xlpm.after,_xlfn.TEXTAFTER(_xlpm.txt,"\"), _xlpm.lastToken,TRIM(_xlfn.TEXTAFTER(_xlpm.before," ",-1)), _xlpm.isReach,LOWER(TRIM(_xlpm.after))="reach", _xlpm.cleaned, IF( ISNUMBER(--_xlpm.lastToken), _xlfn.TEXTBEFORE(_xlpm.before," ",-1) & " \ " & _xlpm.after, _xlpm.txt ), IF(_xlpm.isReach,_xlpm.txt,TRIM(_xlpm.cleaned)) ), B7 ) -> American River at Folsom | I7: =IFERROR( _xlfn.LET( _xlpm.txt,B7, _xlpm.before,TRIM(_xlfn.TEXTBEFORE(_xlpm.txt,"\")), _xlpm.after,TRIM(_xlfn.TEXTAFTER(_xlpm.txt,"\")), _xlpm.lastToken,TRIM(_xlfn.TEXTAFTER(_xlpm.before," ",-1)), _xlpm.isNum,IFERROR(ISNUMBER(--_xlpm.lastToken),FALSE), IF( OR( LOWER(_xlpm.after)="headflow", LOWER(_xlpm.after)="reach" ), "", IF( _xlpm.isNum, _xlpm.lastToken & " \ " & _xlpm.after, "" ) ) ), "" )
A8: Stony Creek at Black Butte | B8: Stony Creek at Black Butte | C8: SacWAM | D8: =IFERROR( _xlfn.XLOOKUP($H8,WEAP!$F:$F,WEAP!$A:$A), IF($I8="","",_xlfn.XLOOKUP($I8,WEAP!$G:$G,WEAP!$A:$A,"")) ) | E8: =IFERROR( _xlfn.XLOOKUP($H8,WEAP!$F:$F,WEAP!$B:$B), IF($I8="","",_xlfn.XLOOKUP($I8,WEAP!$G:$G,WEAP!$B:$B,"")) ) | F8: =IFERROR( _xlfn.XLOOKUP($H8,WEAP!$F:$F,WEAP!$C:$C), IF($I8="","",_xlfn.XLOOKUP($I8,WEAP!$G:$G,WEAP!$C:$C,"")) ) | G8: =IFERROR( _xlfn.XLOOKUP($H8,WEAP!$F:$F,WEAP!$E:$E), IF($I8="","",_xlfn.XLOOKUP($I8,WEAP!$G:$G,WEAP!$E:$E,"")) ) | H8: =IFERROR( _xlfn.LET( _xlpm.txt,TRIM(B8), _xlpm.before,TRIM(_xlfn.TEXTBEFORE(_xlpm.txt,"\",-1)), _xlpm.after,_xlfn.TEXTAFTER(_xlpm.txt,"\"), _xlpm.lastToken,TRIM(_xlfn.TEXTAFTER(_xlpm.before," ",-1)), _xlpm.isReach,LOWER(TRIM(_xlpm.after))="reach", _xlpm.cleaned, IF( ISNUMBER(--_xlpm.lastToken), _xlfn.TEXTBEFORE(_xlpm.before," ",-1) & " \ " & _xlpm.after, _xlpm.txt ), IF(_xlpm.isReach,_xlpm.txt,TRIM(_xlpm.cleaned)) ), B8 ) -> Stony Creek at Black Butte | I8: =IFERROR( _xlfn.LET( _xlpm.txt,B8, _xlpm.before,TRIM(_xlfn.TEXTBEFORE(_xlpm.txt,"\")), _xlpm.after,TRIM(_xlfn.TEXTAFTER(_xlpm.txt,"\")), _xlpm.lastToken,TRIM(_xlfn.TEXTAFTER(_xlpm.before," ",-1)), _xlpm.isNum,IFERROR(ISNUMBER(--_xlpm.lastToken),FALSE), IF( OR( LOWER(_xlpm.after)="headflow", LOWER(_xlpm.after)="reach" ), "", IF( _xlpm.isNum, _xlpm.lastToken & " \ " & _xlpm.after, "" ) ) ), "" )
A9: Cache Creek at Rumsey | B9: Cache Creek at Rumsey | C9: SacWAM | D9: =IFERROR( _xlfn.XLOOKUP($H9,WEAP!$F:$F,WEAP!$A:$A), IF($I9="","",_xlfn.XLOOKUP($I9,WEAP!$G:$G,WEAP!$A:$A,"")) ) | E9: =IFERROR( _xlfn.XLOOKUP($H9,WEAP!$F:$F,WEAP!$B:$B), IF($I9="","",_xlfn.XLOOKUP($I9,WEAP!$G:$G,WEAP!$B:$B,"")) ) | F9: =IFERROR( _xlfn.XLOOKUP($H9,WEAP!$F:$F,WEAP!$C:$C), IF($I9="","",_xlfn.XLOOKUP($I9,WEAP!$G:$G,WEAP!$C:$C,"")) ) | G9: =IFERROR( _xlfn.XLOOKUP($H9,WEAP!$F:$F,WEAP!$E:$E), IF($I9="","",_xlfn.XLOOKUP($I9,WEAP!$G:$G,WEAP!$E:$E,"")) ) | H9: =IFERROR( _xlfn.LET( _xlpm.txt,TRIM(B9), _xlpm.before,TRIM(_xlfn.TEXTBEFORE(_xlpm.txt,"\",-1)), _xlpm.after,_xlfn.TEXTAFTER(_xlpm.txt,"\"), _xlpm.lastToken,TRIM(_xlfn.TEXTAFTER(_xlpm.before," ",-1)), _xlpm.isReach,LOWER(TRIM(_xlpm.after))="reach", _xlpm.cleaned, IF( ISNUMBER(--_xlpm.lastToken), _xlfn.TEXTBEFORE(_xlpm.before," ",-1) & " \ " & _xlpm.after, _xlpm.txt ), IF(_xlpm.isReach,_xlpm.txt,TRIM(_xlpm.cleaned)) ), B9 ) -> Cache Creek at Rumsey | I9: =IFERROR( _xlfn.LET( _xlpm.txt,B9, _xlpm.before,TRIM(_xlfn.TEXTBEFORE(_xlpm.txt,"\")), _xlpm.after,TRIM(_xlfn.TEXTAFTER(_xlpm.txt,"\")), _xlpm.lastToken,TRIM(_xlfn.TEXTAFTER(_xlpm.before," ",-1)), _xlpm.isNum,IFERROR(ISNUMBER(--_xlpm.lastToken),FALSE), IF( OR( LOWER(_xlpm.after)="headflow", LOWER(_xlpm.after)="reach" ), "", IF( _xlpm.isNum, _xlpm.lastToken & " \ " & _xlpm.after, "" ) ) ), "" )
A10: Putah Creek at Monticello | B10: Putah Creek at Monticello | C10: SacWAM | D10: =IFERROR( _xlfn.XLOOKUP($H10,WEAP!$F:$F,WEAP!$A:$A), IF($I10="","",_xlfn.XLOOKUP($I10,WEAP!$G:$G,WEAP!$A:$A,"")) ) | E10: =IFERROR( _xlfn.XLOOKUP($H10,WEAP!$F:$F,WEAP!$B:$B), IF($I10="","",_xlfn.XLOOKUP($I10,WEAP!$G:$G,WEAP!$B:$B,"")) ) | F10: =IFERROR( _xlfn.XLOOKUP($H10,WEAP!$F:$F,WEAP!$C:$C), IF($I10="","",_xlfn.XLOOKUP($I10,WEAP!$G:$G,WEAP!$C:$C,"")) ) | G10: =IFERROR( _xlfn.XLOOKUP($H10,WEAP!$F:$F,WEAP!$E:$E), IF($I10="","",_xlfn.XLOOKUP($I10,WEAP!$G:$G,WEAP!$E:$E,"")) ) | H10: =IFERROR( _xlfn.LET( _xlpm.txt,TRIM(B10), _xlpm.before,TRIM(_xlfn.TEXTBEFORE(_xlpm.txt,"\",-1)), _xlpm.after,_xlfn.TEXTAFTER(_xlpm.txt,"\"), _xlpm.lastToken,TRIM(_xlfn.TEXTAFTER(_xlpm.before," ",-1)), _xlpm.isReach,LOWER(TRIM(_xlpm.after))="reach", _xlpm.cleaned, IF( ISNUMBER(--_xlpm.lastToken), _xlfn.TEXTBEFORE(_xlpm.before," ",-1) & " \ " & _xlpm.after, _xlpm.txt ), IF(_xlpm.isReach,_xlpm.txt,TRIM(_xlpm.cleaned)) ), B10 ) -> Putah Creek at Monticello | I10: =IFERROR( _xlfn.LET( _xlpm.txt,B10, _xlpm.before,TRIM(_xlfn.TEXTBEFORE(_xlpm.txt,"\")), _xlpm.after,TRIM(_xlfn.TEXTAFTER(_xlpm.txt,"\")), _xlpm.lastToken,TRIM(_xlfn.TEXTAFTER(_xlpm.before," ",-1)), _xlpm.isNum,IFERROR(ISNUMBER(--_xlpm.lastToken),FALSE), IF( OR( LOWER(_xlpm.after)="headflow", LOWER(_xlpm.after)="reach" ), "", IF( _xlpm.isNum, _xlpm.lastToken & " \ " & _xlpm.after, "" ) ) ), "" )
A11: Cosumnes River at Michigan Bar | B11: Cosumnes River at Michigan Bar | C11: SacWAM | D11: =IFERROR( _xlfn.XLOOKUP($H11,WEAP!$F:$F,WEAP!$A:$A), IF($I11="","",_xlfn.XLOOKUP($I11,WEAP!$G:$G,WEAP!$A:$A,"")) ) | E11: =IFERROR( _xlfn.XLOOKUP($H11,WEAP!$F:$F,WEAP!$B:$B), IF($I11="","",_xlfn.XLOOKUP($I11,WEAP!$G:$G,WEAP!$B:$B,"")) ) | F11: =IFERROR( _xlfn.XLOOKUP($H11,WEAP!$F:$F,WEAP!$C:$C), IF($I11="","",_xlfn.XLOOKUP($I11,WEAP!$G:$G,WEAP!$C:$C,"")) ) | G11: =IFERROR( _xlfn.XLOOKUP($H11,WEAP!$F:$F,WEAP!$E:$E), IF($I11="","",_xlfn.XLOOKUP($I11,WEAP!$G:$G,WEAP!$E:$E,"")) ) | H11: =IFERROR( _xlfn.LET( _xlpm.txt,TRIM(B11), _xlpm.before,TRIM(_xlfn.TEXTBEFORE(_xlpm.txt,"\",-1)), _xlpm.after,_xlfn.TEXTAFTER(_xlpm.txt,"\"), _xlpm.lastToken,TRIM(_xlfn.TEXTAFTER(_xlpm.before," ",-1)), _xlpm.isReach,LOWER(TRIM(_xlpm.after))="reach", _xlpm.cleaned, IF( ISNUMBER(--_xlpm.lastToken), _xlfn.TEXTBEFORE(_xlpm.before," ",-1) & " \ " & _xlpm.after, _xlpm.txt ), IF(_xlpm.isReach,_xlpm.txt,TRIM(_xlpm.cleaned)) ), B11 ) -> Cosumnes River at Michigan Bar | I11: =IFERROR( _xlfn.LET( _xlpm.txt,B11, _xlpm.before,TRIM(_xlfn.TEXTBEFORE(_xlpm.txt,"\")), _xlpm.after,TRIM(_xlfn.TEXTAFTER(_xlpm.txt,"\")), _xlpm.lastToken,TRIM(_xlfn.TEXTAFTER(_xlpm.before," ",-1)), _xlpm.isNum,IFERROR(ISNUMBER(--_xlpm.lastToken),FALSE), IF( OR( LOWER(_xlpm.after)="headflow", LOWER(_xlpm.after)="reach" ), "", IF( _xlpm.isNum, _xlpm.lastToken & " \ " & _xlpm.after, "" ) ) ), "" )
A12: Mokelumne River at Mokelumne Hill | B12: Mokelumne River at Mokelumne Hill | C12: SacWAM | D12: =IFERROR( _xlfn.XLOOKUP($H12,WEAP!$F:$F,WEAP!$A:$A), IF($I12="","",_xlfn.XLOOKUP($I12,WEAP!$G:$G,WEAP!$A:$A,"")) ) | E12: =IFERROR( _xlfn.XLOOKUP($H12,WEAP!$F:$F,WEAP!$B:$B), IF($I12="","",_xlfn.XLOOKUP($I12,WEAP!$G:$G,WEAP!$B:$B,"")) ) | F12: =IFERROR( _xlfn.XLOOKUP($H12,WEAP!$F:$F,WEAP!$C:$C), IF($I12="","",_xlfn.XLOOKUP($I12,WEAP!$G:$G,WEAP!$C:$C,"")) ) | G12: =IFERROR( _xlfn.XLOOKUP($H12,WEAP!$F:$F,WEAP!$E:$E), IF($I12="","",_xlfn.XLOOKUP($I12,WEAP!$G:$G,WEAP!$E:$E,"")) ) | H12: =IFERROR( _xlfn.LET( _xlpm.txt,TRIM(B12), _xlpm.before,TRIM(_xlfn.TEXTBEFORE(_xlpm.txt,"\",-1)), _xlpm.after,_xlfn.TEXTAFTER(_xlpm.txt,"\"), _xlpm.lastToken,TRIM(_xlfn.TEXTAFTER(_xlpm.before," ",-1)), _xlpm.isReach,LOWER(TRIM(_xlpm.after))="reach", _xlpm.cleaned, IF( ISNUMBER(--_xlpm.lastToken), _xlfn.TEXTBEFORE(_xlpm.before," ",-1) & " \ " & _xlpm.after, _xlpm.txt ), IF(_xlpm.isReach,_xlpm.txt,TRIM(_xlpm.cleaned)) ), B12 ) -> Mokelumne River at Mokelumne Hill | I12: =IFERROR( _xlfn.LET( _xlpm.txt,B12, _xlpm.before,TRIM(_xlfn.TEXTBEFORE(_xlpm.txt,"\")), _xlpm.after,TRIM(_xlfn.TEXTAFTER(_xlpm.txt,"\")), _xlpm.lastToken,TRIM(_xlfn.TEXTAFTER(_xlpm.before," ",-1)), _xlpm.isNum,IFERROR(ISNUMBER(--_xlpm.lastToken),FALSE), IF( OR( LOWER(_xlpm.after)="headflow", LOWER(_xlpm.after)="reach" ), "", IF( _xlpm.isNum, _xlpm.lastToken & " \ " & _xlpm.after, "" ) ) ), "" )
A13: Mokelumne River at Camanche | B13: Mokelumne River at Camanche | C13: SacWAM | D13: =IFERROR( _xlfn.XLOOKUP($H13,WEAP!$F:$F,WEAP!$A:$A), IF($I13="","",_xlfn.XLOOKUP($I13,WEAP!$G:$G,WEAP!$A:$A,"")) ) | E13: =IFERROR( _xlfn.XLOOKUP($H13,WEAP!$F:$F,WEAP!$B:$B), IF($I13="","",_xlfn.XLOOKUP($I13,WEAP!$G:$G,WEAP!$B:$B,"")) ) | F13: =IFERROR( _xlfn.XLOOKUP($H13,WEAP!$F:$F,WEAP!$C:$C), IF($I13="","",_xlfn.XLOOKUP($I13,WEAP!$G:$G,WEAP!$C:$C,"")) ) | G13: =IFERROR( _xlfn.XLOOKUP($H13,WEAP!$F:$F,WEAP!$E:$E), IF($I13="","",_xlfn.XLOOKUP($I13,WEAP!$G:$G,WEAP!$E:$E,"")) ) | H13: =IFERROR( _xlfn.LET( _xlpm.txt,TRIM(B13), _xlpm.before,TRIM(_xlfn.TEXTBEFORE(_xlpm.txt,"\",-1)), _xlpm.after,_xlfn.TEXTAFTER(_xlpm.txt,"\"), _xlpm.lastToken,TRIM(_xlfn.TEXTAFTER(_xlpm.before," ",-1)), _xlpm.isReach,LOWER(TRIM(_xlpm.after))="reach", _xlpm.cleaned, IF( ISNUMBER(--_xlpm.lastToken), _xlfn.TEXTBEFORE(_xlpm.before," ",-1) & " \ " & _xlpm.after, _xlpm.txt ), IF(_xlpm.isReach,_xlpm.txt,TRIM(_xlpm.cleaned)) ), B13 ) -> Mokelumne River at Camanche | I13: =IFERROR( _xlfn.LET( _xlpm.txt,B13, _xlpm.before,TRIM(_xlfn.TEXTBEFORE(_xlpm.txt,"\")), _xlpm.after,TRIM(_xlfn.TEXTAFTER(_xlpm.txt,"\")), _xlpm.lastToken,TRIM(_xlfn.TEXTAFTER(_xlpm.before," ",-1)), _xlpm.isNum,IFERROR(ISNUMBER(--_xlpm.lastToken),FALSE), IF( OR( LOWER(_xlpm.after)="headflow", LOWER(_xlpm.after)="reach" ), "", IF( _xlpm.isNum, _xlpm.lastToken & " \ " & _xlpm.after, "" ) ) ), "" )
... A16: Misc Sac Valley Creeks | B16: Misc Sac Valley Creeks | C16: SacWAM | D16: =IFERROR( _xlfn.XLOOKUP($H16,WEAP!$F:$F,WEAP!$A:$A), IF($I16="","",_xlfn.XLOOKUP($I16,WEAP!$G:$G,WEAP!$A:$A,"")) ) | E16: =IFERROR( _xlfn.XLOOKUP($H16,WEAP!$F:$F,WEAP!$B:$B), IF($I16="","",_xlfn.XLOOKUP($I16,WEAP!$G:$G,WEAP!$B:$B,"")) ) | F16: =IFERROR( _xlfn.XLOOKUP($H16,WEAP!$F:$F,WEAP!$C:$C), IF($I16="","",_xlfn.XLOOKUP($I16,WEAP!$G:$G,WEAP!$C:$C,"")) ) | G16: =IFERROR( _xlfn.XLOOKUP($H16,WEAP!$F:$F,WEAP!$E:$E), IF($I16="","",_xlfn.XLOOKUP($I16,WEAP!$G:$G,WEAP!$E:$E,"")) ) | H16: =IFERROR( _xlfn.LET( _xlpm.txt,TRIM(B16), _xlpm.before,TRIM(_xlfn.TEXTBEFORE(_xlpm.txt,"\",-1)), _xlpm.after,_xlfn.TEXTAFTER(_xlpm.txt,"\"), _xlpm.lastToken,TRIM(_xlfn.TEXTAFTER(_xlpm.before," ",-1)), _xlpm.isReach,LOWER(TRIM(_xlpm.after))="reach", _xlpm.cleaned, IF( ISNUMBER(--_xlpm.lastToken), _xlfn.TEXTBEFORE(_xlpm.before," ",-1) & " \ " & _xlpm.after, _xlpm.txt ), IF(_xlpm.isReach,_xlpm.txt,TRIM(_xlpm.cleaned)) ), B16 ) -> Misc Sac Valley Creeks | I16: =IFERROR( _xlfn.LET( _xlpm.txt,B16, _xlpm.before,TRIM(_xlfn.TEXTBEFORE(_xlpm.txt,"\")), _xlpm.after,TRIM(_xlfn.TEXTAFTER(_xlpm.txt,"\")), _xlpm.lastToken,TRIM(_xlfn.TEXTAFTER(_xlpm.before," ",-1)), _xlpm.isNum,IFERROR(ISNUMBER(--_xlpm.lastToken),FALSE), IF( OR( LOWER(_xlpm.after)="headflow", LOWER(_xlpm.after)="reach" ), "", IF( _xlpm.isNum, _xlpm.lastToken & " \ " & _xlpm.after, "" ) ) ), "" )
B17: SWP Allocations\Final_Allocation\SWP_percent_delivery | C17: SacWAM | D17: =IFERROR( _xlfn.XLOOKUP($H17,WEAP!$F:$F,WEAP!$A:$A), IF($I17="","",_xlfn.XLOOKUP($I17,WEAP!$G:$G,WEAP!$A:$A,"")) ) | E17: =IFERROR( _xlfn.XLOOKUP($H17,WEAP!$F:$F,WEAP!$B:$B), IF($I17="","",_xlfn.XLOOKUP($I17,WEAP!$G:$G,WEAP!$B:$B,"")) ) | F17: =IFERROR( _xlfn.XLOOKUP($H17,WEAP!$F:$F,WEAP!$C:$C), IF($I17="","",_xlfn.XLOOKUP($I17,WEAP!$G:$G,WEAP!$C:$C,"")) ) | G17: =IFERROR( _xlfn.XLOOKUP($H17,WEAP!$F:$F,WEAP!$E:$E), IF($I17="","",_xlfn.XLOOKUP($I17,WEAP!$G:$G,WEAP!$E:$E,"")) ) | H17: =IFERROR( _xlfn.LET( _xlpm.txt,TRIM(B17), _xlpm.before,TRIM(_xlfn.TEXTBEFORE(_xlpm.txt,"\",-1)), _xlpm.after,_xlfn.TEXTAFTER(_xlpm.txt,"\"), _xlpm.lastToken,TRIM(_xlfn.TEXTAFTER(_xlpm.before," ",-1)), _xlpm.isReach,LOWER(TRIM(_xlpm.after))="reach", _xlpm.cleaned, IF( ISNUMBER(--_xlpm.lastToken), _xlfn.TEXTBEFORE(_xlpm.before," ",-1) & " \ " & _xlpm.after, _xlpm.txt ), IF(_xlpm.isReach,_xlpm.txt,TRIM(_xlpm.cleaned)) ), B17 ) -> SWP Allocations\Final_Allocation\SWP_percent_delivery | I17: =IFERROR( _xlfn.LET( _xlpm.txt,B17, _xlpm.before,TRIM(_xlfn.TEXTBEFORE(_xlpm.txt,"\")), _xlpm.after,TRIM(_xlfn.TEXTAFTER(_xlpm.txt,"\")), _xlpm.lastToken,TRIM(_xlfn.TEXTAFTER(_xlpm.before," ",-1)), _xlpm.isNum,IFERROR(ISNUMBER(--_xlpm.lastToken),FALSE), IF( OR( LOWER(_xlpm.after)="headflow", LOWER(_xlpm.after)="reach" ), "", IF( _xlpm.isNum, _xlpm.lastToken & " \ " & _xlpm.after, "" ) ) ), "" )
B18: CVP Allocations\System\Percent_Alloc_AG | C18: SacWAM | D18: =IFERROR( _xlfn.XLOOKUP($H18,WEAP!$F:$F,WEAP!$A:$A), IF($I18="","",_xlfn.XLOOKUP($I18,WEAP!$G:$G,WEAP!$A:$A,"")) ) | E18: =IFERROR( _xlfn.XLOOKUP($H18,WEAP!$F:$F,WEAP!$B:$B), IF($I18="","",_xlfn.XLOOKUP($I18,WEAP!$G:$G,WEAP!$B:$B,"")) ) | F18: =IFERROR( _xlfn.XLOOKUP($H18,WEAP!$F:$F,WEAP!$C:$C), IF($I18="","",_xlfn.XLOOKUP($I18,WEAP!$G:$G,WEAP!$C:$C,"")) ) | G18: =IFERROR( _xlfn.XLOOKUP($H18,WEAP!$F:$F,WEAP!$E:$E), IF($I18="","",_xlfn.XLOOKUP($I18,WEAP!$G:$G,WEAP!$E:$E,"")) ) | H18: =IFERROR( _xlfn.LET( _xlpm.txt,TRIM(B18), _xlpm.before,TRIM(_xlfn.TEXTBEFORE(_xlpm.txt,"\",-1)), _xlpm.after,_xlfn.TEXTAFTER(_xlpm.txt,"\"), _xlpm.lastToken,TRIM(_xlfn.TEXTAFTER(_xlpm.before," ",-1)), _xlpm.isReach,LOWER(TRIM(_xlpm.after))="reach", _xlpm.cleaned, IF( ISNUMBER(--_xlpm.lastToken), _xlfn.TEXTBEFORE(_xlpm.before," ",-1) & " \ " & _xlpm.after, _xlpm.txt ), IF(_xlpm.isReach,_xlpm.txt,TRIM(_xlpm.cleaned)) ), B18 ) -> CVP Allocations\System\Percent_Alloc_AG | I18: =IFERROR( _xlfn.LET( _xlpm.txt,B18, _xlpm.before,TRIM(_xlfn.TEXTBEFORE(_xlpm.txt,"\")), _xlpm.after,TRIM(_xlfn.TEXTAFTER(_xlpm.txt,"\")), _xlpm.lastToken,TRIM(_xlfn.TEXTAFTER(_xlpm.before," ",-1)), _xlpm.isNum,IFERROR(ISNUMBER(--_xlpm.lastToken),FALSE), IF( OR( LOWER(_xlpm.after)="headflow", LOWER(_xlpm.after)="reach" ), "", IF( _xlpm.isNum, _xlpm.lastToken & " \ " & _xlpm.after, "" ) ) ), "" )
B19: CVP Allocations\South\Percent_Alloc_AG | C19: SacWAM | D19: =IFERROR( _xlfn.XLOOKUP($H19,WEAP!$F:$F,WEAP!$A:$A), IF($I19="","",_xlfn.XLOOKUP($I19,WEAP!$G:$G,WEAP!$A:$A,"")) ) | E19: =IFERROR( _xlfn.XLOOKUP($H19,WEAP!$F:$F,WEAP!$B:$B), IF($I19="","",_xlfn.XLOOKUP($I19,WEAP!$G:$G,WEAP!$B:$B,"")) ) | F19: =IFERROR( _xlfn.XLOOKUP($H19,WEAP!$F:$F,WEAP!$C:$C), IF($I19="","",_xlfn.XLOOKUP($I19,WEAP!$G:$G,WEAP!$C:$C,"")) ) | G19: =IFERROR( _xlfn.XLOOKUP($H19,WEAP!$F:$F,WEAP!$E:$E), IF($I19="","",_xlfn.XLOOKUP($I19,WEAP!$G:$G,WEAP!$E:$E,"")) ) | H19: =IFERROR( _xlfn.LET( _xlpm.txt,TRIM(B19), _xlpm.before,TRIM(_xlfn.TEXTBEFORE(_xlpm.txt,"\",-1)), _xlpm.after,_xlfn.TEXTAFTER(_xlpm.txt,"\"), _xlpm.lastToken,TRIM(_xlfn.TEXTAFTER(_xlpm.before," ",-1)), _xlpm.isReach,LOWER(TRIM(_xlpm.after))="reach", _xlpm.cleaned, IF( ISNUMBER(--_xlpm.lastToken), _xlfn.TEXTBEFORE(_xlpm.before," ",-1) & " \ " & _xlpm.after, _xlpm.txt ), IF(_xlpm.isReach,_xlpm.txt,TRIM(_xlpm.cleaned)) ), B19 ) -> CVP Allocations\South\Percent_Alloc_AG | I19: =IFERROR( _xlfn.LET( _xlpm.txt,B19, _xlpm.before,TRIM(_xlfn.TEXTBEFORE(_xlpm.txt,"\")), _xlpm.after,TRIM(_xlfn.TEXTAFTER(_xlpm.txt,"\")), _xlpm.lastToken,TRIM(_xlfn.TEXTAFTER(_xlpm.before," ",-1)), _xlpm.isNum,IFERROR(ISNUMBER(--_xlpm.lastToken),FALSE), IF( OR( LOWER(_xlpm.after)="headflow", LOWER(_xlpm.after)="reach" ), "", IF( _xlpm.isNum, _xlpm.lastToken & " \ " & _xlpm.after, "" ) ) ), "" )
B20: CVP Allocations\System\Percent_Alloc_MI | C20: SacWAM | D20: =IFERROR( _xlfn.XLOOKUP($H20,WEAP!$F:$F,WEAP!$A:$A), IF($I20="","",_xlfn.XLOOKUP($I20,WEAP!$G:$G,WEAP!$A:$A,"")) ) | E20: =IFERROR( _xlfn.XLOOKUP($H20,WEAP!$F:$F,WEAP!$B:$B), IF($I20="","",_xlfn.XLOOKUP($I20,WEAP!$G:$G,WEAP!$B:$B,"")) ) | F20: =IFERROR( _xlfn.XLOOKUP($H20,WEAP!$F:$F,WEAP!$C:$C), IF($I20="","",_xlfn.XLOOKUP($I20,WEAP!$G:$G,WEAP!$C:$C,"")) ) | G20: =IFERROR( _xlfn.XLOOKUP($H20,WEAP!$F:$F,WEAP!$E:$E), IF($I20="","",_xlfn.XLOOKUP($I20,WEAP!$G:$G,WEAP!$E:$E,"")) ) | H20: =IFERROR( _xlfn.LET( _xlpm.txt,TRIM(B20), _xlpm.before,TRIM(_xlfn.TEXTBEFORE(_xlpm.txt,"\",-1)), _xlpm.after,_xlfn.TEXTAFTER(_xlpm.txt,"\"), _xlpm.lastToken,TRIM(_xlfn.TEXTAFTER(_xlpm.before," ",-1)), _xlpm.isReach,LOWER(TRIM(_xlpm.after))="reach", _xlpm.cleaned, IF( ISNUMBER(--_xlpm.lastToken), _xlfn.TEXTBEFORE(_xlpm.before," ",-1) & " \ " & _xlpm.after, _xlpm.txt ), IF(_xlpm.isReach,_xlpm.txt,TRIM(_xlpm.cleaned)) ), B20 ) -> CVP Allocations\System\Percent_Alloc_MI | I20: =IFERROR( _xlfn.LET( _xlpm.txt,B20, _xlpm.before,TRIM(_xlfn.TEXTBEFORE(_xlpm.txt,"\")), _xlpm.after,TRIM(_xlfn.TEXTAFTER(_xlpm.txt,"\")), _xlpm.lastToken,TRIM(_xlfn.TEXTAFTER(_xlpm.before," ",-1)), _xlpm.isNum,IFERROR(ISNUMBER(--_xlpm.lastToken),FALSE), IF( OR( LOWER(_xlpm.after)="headflow", LOWER(_xlpm.after)="reach" ), "", IF( _xlpm.isNum, _xlpm.lastToken & " \ " & _xlpm.after, "" ) ) ), "" )
B21: CVP Allocations\South\Percent_Alloc_MI | C21: SacWAM | D21: =IFERROR( _xlfn.XLOOKUP($H21,WEAP!$F:$F,WEAP!$A:$A), IF($I21="","",_xlfn.XLOOKUP($I21,WEAP!$G:$G,WEAP!$A:$A,"")) ) | E21: =IFERROR( _xlfn.XLOOKUP($H21,WEAP!$F:$F,WEAP!$B:$B), IF($I21="","",_xlfn.XLOOKUP($I21,WEAP!$G:$G,WEAP!$B:$B,"")) ) | F21: =IFERROR( _xlfn.XLOOKUP($H21,WEAP!$F:$F,WEAP!$C:$C), IF($I21="","",_xlfn.XLOOKUP($I21,WEAP!$G:$G,WEAP!$C:$C,"")) ) | G21: =IFERROR( _xlfn.XLOOKUP($H21,WEAP!$F:$F,WEAP!$E:$E), IF($I21="","",_xlfn.XLOOKUP($I21,WEAP!$G:$G,WEAP!$E:$E,"")) ) | H21: =IFERROR( _xlfn.LET( _xlpm.txt,TRIM(B21), _xlpm.before,TRIM(_xlfn.TEXTBEFORE(_xlpm.txt,"\",-1)), _xlpm.after,_xlfn.TEXTAFTER(_xlpm.txt,"\"), _xlpm.lastToken,TRIM(_xlfn.TEXTAFTER(_xlpm.before," ",-1)), _xlpm.isReach,LOWER(TRIM(_xlpm.after))="reach", _xlpm.cleaned, IF( ISNUMBER(--_xlpm.lastToken), _xlfn.TEXTBEFORE(_xlpm.before," ",-1) & " \ " & _xlpm.after, _xlpm.txt ), IF(_xlpm.isReach,_xlpm.txt,TRIM(_xlpm.cleaned)) ), B21 ) -> CVP Allocations\South\Percent_Alloc_MI | I21: =IFERROR( _xlfn.LET( _xlpm.txt,B21, _xlpm.before,TRIM(_xlfn.TEXTBEFORE(_xlpm.txt,"\")), _xlpm.after,TRIM(_xlfn.TEXTAFTER(_xlpm.txt,"\")), _xlpm.lastToken,TRIM(_xlfn.TEXTAFTER(_xlpm.before," ",-1)), _xlpm.isNum,IFERROR(ISNUMBER(--_xlpm.lastToken),FALSE), IF( OR( LOWER(_xlpm.after)="headflow", LOWER(_xlpm.after)="reach" ), "", IF( _xlpm.isNum, _xlpm.lastToken & " \ " & _xlpm.after, "" ) ) ), "" )
B22: CVP Allocations\System\Percent_Alloc_SC | C22: SacWAM | D22: =IFERROR( _xlfn.XLOOKUP($H22,WEAP!$F:$F,WEAP!$A:$A), IF($I22="","",_xlfn.XLOOKUP($I22,WEAP!$G:$G,WEAP!$A:$A,"")) ) | E22: =IFERROR( _xlfn.XLOOKUP($H22,WEAP!$F:$F,WEAP!$B:$B), IF($I22="","",_xlfn.XLOOKUP($I22,WEAP!$G:$G,WEAP!$B:$B,"")) ) | F22: =IFERROR( _xlfn.XLOOKUP($H22,WEAP!$F:$F,WEAP!$C:$C), IF($I22="","",_xlfn.XLOOKUP($I22,WEAP!$G:$G,WEAP!$C:$C,"")) ) | G22: =IFERROR( _xlfn.XLOOKUP($H22,WEAP!$F:$F,WEAP!$E:$E), IF($I22="","",_xlfn.XLOOKUP($I22,WEAP!$G:$G,WEAP!$E:$E,"")) ) | H22: =IFERROR( _xlfn.LET( _xlpm.txt,TRIM(B22), _xlpm.before,TRIM(_xlfn.TEXTBEFORE(_xlpm.txt,"\",-1)), _xlpm.after,_xlfn.TEXTAFTER(_xlpm.txt,"\"), _xlpm.lastToken,TRIM(_xlfn.TEXTAFTER(_xlpm.before," ",-1)), _xlpm.isReach,LOWER(TRIM(_xlpm.after))="reach", _xlpm.cleaned, IF( ISNUMBER(--_xlpm.lastToken), _xlfn.TEXTBEFORE(_xlpm.before," ",-1) & " \ " & _xlpm.after, _xlpm.txt ), IF(_xlpm.isReach,_xlpm.txt,TRIM(_xlpm.cleaned)) ), B22 ) -> CVP Allocations\System\Percent_Alloc_SC | I22: =IFERROR( _xlfn.LET( _xlpm.txt,B22, _xlpm.before,TRIM(_xlfn.TEXTBEFORE(_xlpm.txt,"\")), _xlpm.after,TRIM(_xlfn.TEXTAFTER(_xlpm.txt,"\")), _xlpm.lastToken,TRIM(_xlfn.TEXTAFTER(_xlpm.before," ",-1)), _xlpm.isNum,IFERROR(ISNUMBER(--_xlpm.lastToken),FALSE), IF( OR( LOWER(_xlpm.after)="headflow", LOWER(_xlpm.after)="reach" ), "", IF( _xlpm.isNum, _xlpm.lastToken & " \ " & _xlpm.after, "" ) ) ), "" )
B23: CVP Allocations\South\Percent_Alloc_EX | C23: SacWAM | D23: =IFERROR( _xlfn.XLOOKUP($H23,WEAP!$F:$F,WEAP!$A:$A), IF($I23="","",_xlfn.XLOOKUP($I23,WEAP!$G:$G,WEAP!$A:$A,"")) ) | E23: =IFERROR( _xlfn.XLOOKUP($H23,WEAP!$F:$F,WEAP!$B:$B), IF($I23="","",_xlfn.XLOOKUP($I23,WEAP!$G:$G,WEAP!$B:$B,"")) ) | F23: =IFERROR( _xlfn.XLOOKUP($H23,WEAP!$F:$F,WEAP!$C:$C), IF($I23="","",_xlfn.XLOOKUP($I23,WEAP!$G:$G,WEAP!$C:$C,"")) ) | G23: =IFERROR( _xlfn.XLOOKUP($H23,WEAP!$F:$F,WEAP!$E:$E), IF($I23="","",_xlfn.XLOOKUP($I23,WEAP!$G:$G,WEAP!$E:$E,"")) ) | H23: =IFERROR( _xlfn.LET( _xlpm.txt,TRIM(B23), _xlpm.before,TRIM(_xlfn.TEXTBEFORE(_xlpm.txt,"\",-1)), _xlpm.after,_xlfn.TEXTAFTER(_xlpm.txt,"\"), _xlpm.lastToken,TRIM(_xlfn.TEXTAFTER(_xlpm.before," ",-1)), _xlpm.isReach,LOWER(TRIM(_xlpm.after))="reach", _xlpm.cleaned, IF( ISNUMBER(--_xlpm.lastToken), _xlfn.TEXTBEFORE(_xlpm.before," ",-1) & " \ " & _xlpm.after, _xlpm.txt ), IF(_xlpm.isReach,_xlpm.txt,TRIM(_xlpm.cleaned)) ), B23 ) -> CVP Allocations\South\Percent_Alloc_EX | I23: =IFERROR( _xlfn.LET( _xlpm.txt,B23, _xlpm.before,TRIM(_xlfn.TEXTBEFORE(_xlpm.txt,"\")), _xlpm.after,TRIM(_xlfn.TEXTAFTER(_xlpm.txt,"\")), _xlpm.lastToken,TRIM(_xlfn.TEXTAFTER(_xlpm.before," ",-1)), _xlpm.isNum,IFERROR(ISNUMBER(--_xlpm.lastToken),FALSE), IF( OR( LOWER(_xlpm.after)="headflow", LOWER(_xlpm.after)="reach" ), "", IF( _xlpm.isNum, _xlpm.lastToken & " \ " & _xlpm.after, "" ) ) ), "" )
B24: CVP Allocations\System\Percent_Alloc_RFN | C24: SacWAM | D24: =IFERROR( _xlfn.XLOOKUP($H24,WEAP!$F:$F,WEAP!$A:$A), IF($I24="","",_xlfn.XLOOKUP($I24,WEAP!$G:$G,WEAP!$A:$A,"")) ) | E24: =IFERROR( _xlfn.XLOOKUP($H24,WEAP!$F:$F,WEAP!$B:$B), IF($I24="","",_xlfn.XLOOKUP($I24,WEAP!$G:$G,WEAP!$B:$B,"")) ) | F24: =IFERROR( _xlfn.XLOOKUP($H24,WEAP!$F:$F,WEAP!$C:$C), IF($I24="","",_xlfn.XLOOKUP($I24,WEAP!$G:$G,WEAP!$C:$C,"")) ) | G24: =IFERROR( _xlfn.XLOOKUP($H24,WEAP!$F:$F,WEAP!$E:$E), IF($I24="","",_xlfn.XLOOKUP($I24,WEAP!$G:$G,WEAP!$E:$E,"")) ) | H24: =IFERROR( _xlfn.LET( _xlpm.txt,TRIM(B24), _xlpm.before,TRIM(_xlfn.TEXTBEFORE(_xlpm.txt,"\",-1)), _xlpm.after,_xlfn.TEXTAFTER(_xlpm.txt,"\"), _xlpm.lastToken,TRIM(_xlfn.TEXTAFTER(_xlpm.before," ",-1)), _xlpm.isReach,LOWER(TRIM(_xlpm.after))="reach", _xlpm.cleaned, IF( ISNUMBER(--_xlpm.lastToken), _xlfn.TEXTBEFORE(_xlpm.before," ",-1) & " \ " & _xlpm.after, _xlpm.txt ), IF(_xlpm.isReach,_xlpm.txt,TRIM(_xlpm.cleaned)) ), B24 ) -> CVP Allocations\System\Percent_Alloc_RFN | I24: =IFERROR( _xlfn.LET( _xlpm.txt,B24, _xlpm.before,TRIM(_xlfn.TEXTBEFORE(_xlpm.txt,"\")), _xlpm.after,TRIM(_xlfn.TEXTAFTER(_xlpm.txt,"\")), _xlpm.lastToken,TRIM(_xlfn.TEXTAFTER(_xlpm.before," ",-1)), _xlpm.isNum,IFERROR(ISNUMBER(--_xlpm.lastToken),FALSE), IF( OR( LOWER(_xlpm.after)="headflow", LOWER(_xlpm.after)="reach" ), "", IF( _xlpm.isNum, _xlpm.lastToken & " \ " & _xlpm.after, "" ) ) ), "" )
B25: CVP Allocations\South\Percent_Alloc_RFS | C25: SacWAM | D25: =IFERROR( _xlfn.XLOOKUP($H25,WEAP!$F:$F,WEAP!$A:$A), IF($I25="","",_xlfn.XLOOKUP($I25,WEAP!$G:$G,WEAP!$A:$A,"")) ) | E25: =IFERROR( _xlfn.XLOOKUP($H25,WEAP!$F:$F,WEAP!$B:$B), IF($I25="","",_xlfn.XLOOKUP($I25,WEAP!$G:$G,WEAP!$B:$B,"")) ) | F25: =IFERROR( _xlfn.XLOOKUP($H25,WEAP!$F:$F,WEAP!$C:$C), IF($I25="","",_xlfn.XLOOKUP($I25,WEAP!$G:$G,WEAP!$C:$C,"")) ) | G25: =IFERROR( _xlfn.XLOOKUP($H25,WEAP!$F:$F,WEAP!$E:$E), IF($I25="","",_xlfn.XLOOKUP($I25,WEAP!$G:$G,WEAP!$E:$E,"")) ) | H25: =IFERROR( _xlfn.LET( _xlpm.txt,TRIM(B25), _xlpm.before,TRIM(_xlfn.TEXTBEFORE(_xlpm.txt,"\",-1)), _xlpm.after,_xlfn.TEXTAFTER(_xlpm.txt,"\"), _xlpm.lastToken,TRIM(_xlfn.TEXTAFTER(_xlpm.before," ",-1)), _xlpm.isReach,LOWER(TRIM(_xlpm.after))="reach", _xlpm.cleaned, IF( ISNUMBER(--_xlpm.lastToken), _xlfn.TEXTBEFORE(_xlpm.before," ",-1) & " \ " & _xlpm.after, _xlpm.txt ), IF(_xlpm.isReach,_xlpm.txt,TRIM(_xlpm.cleaned)) ), B25 ) -> CVP Allocations\South\Percent_Alloc_RFS | I25: =IFERROR( _xlfn.LET( _xlpm.txt,B25, _xlpm.before,TRIM(_xlfn.TEXTBEFORE(_xlpm.txt,"\")), _xlpm.after,TRIM(_xlfn.TEXTAFTER(_xlpm.txt,"\")), _xlpm.lastToken,TRIM(_xlfn.TEXTAFTER(_xlpm.before," ",-1)), _xlpm.isNum,IFERROR(ISNUMBER(--_xlpm.lastToken),FALSE), IF( OR( LOWER(_xlpm.after)="headflow", LOWER(_xlpm.after)="reach" ), "", IF( _xlpm.isNum, _xlpm.lastToken & " \ " & _xlpm.after, "" ) ) ), "" )
B26: San Luis\SWP\RuleCurve (Thousand AF) | C26: SacWAM | D26: =IFERROR( _xlfn.XLOOKUP($H26,WEAP!$F:$F,WEAP!$A:$A), IF($I26="","",_xlfn.XLOOKUP($I26,WEAP!$G:$G,WEAP!$A:$A,"")) ) | E26: =IFERROR( _xlfn.XLOOKUP($H26,WEAP!$F:$F,WEAP!$B:$B), IF($I26="","",_xlfn.XLOOKUP($I26,WEAP!$G:$G,WEAP!$B:$B,"")) ) | F26: =IFERROR( _xlfn.XLOOKUP($H26,WEAP!$F:$F,WEAP!$C:$C), IF($I26="","",_xlfn.XLOOKUP($I26,WEAP!$G:$G,WEAP!$C:$C,"")) ) | G26: =IFERROR( _xlfn.XLOOKUP($H26,WEAP!$F:$F,WEAP!$E:$E), IF($I26="","",_xlfn.XLOOKUP($I26,WEAP!$G:$G,WEAP!$E:$E,"")) ) | H26: =IFERROR( _xlfn.LET( _xlpm.txt,TRIM(B26), _xlpm.before,TRIM(_xlfn.TEXTBEFORE(_xlpm.txt,"\",-1)), _xlpm.after,_xlfn.TEXTAFTER(_xlpm.txt,"\"), _xlpm.lastToken,TRIM(_xlfn.TEXTAFTER(_xlpm.before," ",-1)), _xlpm.isReach,LOWER(TRIM(_xlpm.after))="reach", _xlpm.cleaned, IF( ISNUMBER(--_xlpm.lastToken), _xlfn.TEXTBEFORE(_xlpm.before," ",-1) & " \ " & _xlpm.after, _xlpm.txt ), IF(_xlpm.isReach,_xlpm.txt,TRIM(_xlpm.cleaned)) ), B26 ) -> San Luis\SWP\RuleCurve (Thousand AF) | I26: =IFERROR( _xlfn.LET( _xlpm.txt,B26, _xlpm.before,TRIM(_xlfn.TEXTBEFORE(_xlpm.txt,"\")), _xlpm.after,TRIM(_xlfn.TEXTAFTER(_xlpm.txt,"\")), _xlpm.lastToken,TRIM(_xlfn.TEXTAFTER(_xlpm.before," ",-1)), _xlpm.isNum,IFERROR(ISNUMBER(--_xlpm.lastToken),FALSE), IF( OR( LOWER(_xlpm.after)="headflow", LOWER(_xlpm.after)="reach" ), "", IF( _xlpm.isNum, _xlpm.lastToken & " \ " & _xlpm.after, "" ) ) ), "" )
B27: San Luis\SWP\RuleCurveCalc (Thousand AF) | C27: SacWAM | D27: =IFERROR( _xlfn.XLOOKUP($H27,WEAP!$F:$F,WEAP!$A:$A), IF($I27="","",_xlfn.XLOOKUP($I27,WEAP!$G:$G,WEAP!$A:$A,"")) ) | E27: =IFERROR( _xlfn.XLOOKUP($H27,WEAP!$F:$F,WEAP!$B:$B), IF($I27="","",_xlfn.XLOOKUP($I27,WEAP!$G:$G,WEAP!$B:$B,"")) ) | F27: =IFERROR( _xlfn.XLOOKUP($H27,WEAP!$F:$F,WEAP!$C:$C), IF($I27="","",_xlfn.XLOOKUP($I27,WEAP!$G:$G,WEAP!$C:$C,"")) ) | G27: =IFERROR( _xlfn.XLOOKUP($H27,WEAP!$F:$F,WEAP!$E:$E), IF($I27="","",_xlfn.XLOOKUP($I27,WEAP!$G:$G,WEAP!$E:$E,"")) ) | H27: =IFERROR( _xlfn.LET( _xlpm.txt,TRIM(B27), _xlpm.before,TRIM(_xlfn.TEXTBEFORE(_xlpm.txt,"\",-1)), _xlpm.after,_xlfn.TEXTAFTER(_xlpm.txt,"\"), _xlpm.lastToken,TRIM(_xlfn.TEXTAFTER(_xlpm.before," ",-1)), _xlpm.isReach,LOWER(TRIM(_xlpm.after))="reach", _xlpm.cleaned, IF( ISNUMBER(--_xlpm.lastToken), _xlfn.TEXTBEFORE(_xlpm.before," ",-1) & " \ " & _xlpm.after, _xlpm.txt ), IF(_xlpm.isReach,_xlpm.txt,TRIM(_xlpm.cleaned)) ), B27 ) -> San Luis\SWP\RuleCurveCalc (Thousand AF) | I27: =IFERROR( _xlfn.LET( _xlpm.txt,B27, _xlpm.before,TRIM(_xlfn.TEXTBEFORE(_xlpm.txt,"\")), _xlpm.after,TRIM(_xlfn.TEXTAFTER(_xlpm.txt,"\")), _xlpm.lastToken,TRIM(_xlfn.TEXTAFTER(_xlpm.before," ",-1)), _xlpm.isNum,IFERROR(ISNUMBER(--_xlpm.lastToken),FALSE), IF( OR( LOWER(_xlpm.after)="headflow", LOWER(_xlpm.after)="reach" ), "", IF( _xlpm.isNum, _xlpm.lastToken & " \ " & _xlpm.after, "" ) ) ), "" )
B28: San Luis\SWP\SWPdemfinal\SWP_demprofile (/AF) | C28: SacWAM | D28: =IFERROR( _xlfn.XLOOKUP($H28,WEAP!$F:$F,WEAP!$A:$A), IF($I28="","",_xlfn.XLOOKUP($I28,WEAP!$G:$G,WEAP!$A:$A,"")) ) | E28: =IFERROR( _xlfn.XLOOKUP($H28,WEAP!$F:$F,WEAP!$B:$B), IF($I28="","",_xlfn.XLOOKUP($I28,WEAP!$G:$G,WEAP!$B:$B,"")) ) | F28: =IFERROR( _xlfn.XLOOKUP($H28,WEAP!$F:$F,WEAP!$C:$C), IF($I28="","",_xlfn.XLOOKUP($I28,WEAP!$G:$G,WEAP!$C:$C,"")) ) | G28: =IFERROR( _xlfn.XLOOKUP($H28,WEAP!$F:$F,WEAP!$E:$E), IF($I28="","",_xlfn.XLOOKUP($I28,WEAP!$G:$G,WEAP!$E:$E,"")) ) | H28: =IFERROR( _xlfn.LET( _xlpm.txt,TRIM(B28), _xlpm.before,TRIM(_xlfn.TEXTBEFORE(_xlpm.txt,"\",-1)), _xlpm.after,_xlfn.TEXTAFTER(_xlpm.txt,"\"), _xlpm.lastToken,TRIM(_xlfn.TEXTAFTER(_xlpm.before," ",-1)), _xlpm.isReach,LOWER(TRIM(_xlpm.after))="reach", _xlpm.cleaned, IF( ISNUMBER(--_xlpm.lastToken), _xlfn.TEXTBEFORE(_xlpm.before," ",-1) & " \ " & _xlpm.after, _xlpm.txt ), IF(_xlpm.isReach,_xlpm.txt,TRIM(_xlpm.cleaned)) ), B28 ) -> San Luis\SWP\SWPdemfinal\SWP_demprofile (/AF) | I28: =IFERROR( _xlfn.LET( _xlpm.txt,B28, _xlpm.before,TRIM(_xlfn.TEXTBEFORE(_xlpm.txt,"\")), _xlpm.after,TRIM(_xlfn.TEXTAFTER(_xlpm.txt,"\")), _xlpm.lastToken,TRIM(_xlfn.TEXTAFTER(_xlpm.before," ",-1)), _xlpm.isNum,IFERROR(ISNUMBER(--_xlpm.lastToken),FALSE), IF( OR( LOWER(_xlpm.after)="headflow", LOWER(_xlpm.after)="reach" ), "", IF( _xlpm.isNum, _xlpm.lastToken & " \ " & _xlpm.after, "" ) ) ), "" )
... B36: Folsom Rule Curve | C36: SacWAM | D36: =IFERROR( _xlfn.XLOOKUP($H36,WEAP!$F:$F,WEAP!$A:$A), IF($I36="","",_xlfn.XLOOKUP($I36,WEAP!$G:$G,WEAP!$A:$A,"")) ) | E36: =IFERROR( _xlfn.XLOOKUP($H36,WEAP!$F:$F,WEAP!$B:$B), IF($I36="","",_xlfn.XLOOKUP($I36,WEAP!$G:$G,WEAP!$B:$B,"")) ) | F36: =IFERROR( _xlfn.XLOOKUP($H36,WEAP!$F:$F,WEAP!$C:$C), IF($I36="","",_xlfn.XLOOKUP($I36,WEAP!$G:$G,WEAP!$C:$C,"")) ) | G36: =IFERROR( _xlfn.XLOOKUP($H36,WEAP!$F:$F,WEAP!$E:$E), IF($I36="","",_xlfn.XLOOKUP($I36,WEAP!$G:$G,WEAP!$E:$E,"")) ) | H36: =IFERROR( _xlfn.LET( _xlpm.txt,TRIM(B36), _xlpm.before,TRIM(_xlfn.TEXTBEFORE(_xlpm.txt,"\",-1)), _xlpm.after,_xlfn.TEXTAFTER(_xlpm.txt,"\"), _xlpm.lastToken,TRIM(_xlfn.TEXTAFTER(_xlpm.before," ",-1)), _xlpm.isReach,LOWER(TRIM(_xlpm.after))="reach", _xlpm.cleaned, IF( ISNUMBER(--_xlpm.lastToken), _xlfn.TEXTBEFORE(_xlpm.before," ",-1) & " \ " & _xlpm.after, _xlpm.txt ), IF(_xlpm.isReach,_xlpm.txt,TRIM(_xlpm.cleaned)) ), B36 ) -> Folsom Rule Curve | I36: =IFERROR( _xlfn.LET( _xlpm.txt,B36, _xlpm.before,TRIM(_xlfn.TEXTBEFORE(_xlpm.txt,"\")), _xlpm.after,TRIM(_xlfn.TEXTAFTER(_xlpm.txt,"\")), _xlpm.lastToken,TRIM(_xlfn.TEXTAFTER(_xlpm.before," ",-1)), _xlpm.isNum,IFERROR(ISNUMBER(--_xlpm.lastToken),FALSE), IF( OR( LOWER(_xlpm.after)="headflow", LOWER(_xlpm.after)="reach" ), "", IF( _xlpm.isNum, _xlpm.lastToken & " \ " & _xlpm.after, "" ) ) ), "" )
A37: D_NFA016_ABT002 | B37: Auburn Tunnel 0 \ Headflow | C37: SacWAM | D37: =IFERROR( _xlfn.XLOOKUP($H37,WEAP!$F:$F,WEAP!$A:$A), IF($I37="","",_xlfn.XLOOKUP($I37,WEAP!$G:$G,WEAP!$A:$A,"")) ) -> 8471 | E37: =IFERROR( _xlfn.XLOOKUP($H37,WEAP!$F:$F,WEAP!$B:$B), IF($I37="","",_xlfn.XLOOKUP($I37,WEAP!$G:$G,WEAP!$B:$B,"")) ) -> Auburn Tunnel 0 \ Headflow | F37: =IFERROR( _xlfn.XLOOKUP($H37,WEAP!$F:$F,WEAP!$C:$C), IF($I37="","",_xlfn.XLOOKUP($I37,WEAP!$G:$G,WEAP!$C:$C,"")) ) -> taf | G37: =IFERROR( _xlfn.XLOOKUP($H37,WEAP!$F:$F,WEAP!$E:$E), IF($I37="","",_xlfn.XLOOKUP($I37,WEAP!$G:$G,WEAP!$E:$E,"")) ) -> Streamflow (below node or reach listed) | H37: =IFERROR( _xlfn.LET( _xlpm.txt,TRIM(B37), _xlpm.before,TRIM(_xlfn.TEXTBEFORE(_xlpm.txt,"\",-1)), _xlpm.after,_xlfn.TEXTAFTER(_xlpm.txt,"\"), _xlpm.lastToken,TRIM(_xlfn.TEXTAFTER(_xlpm.before," ",-1)), _xlpm.isReach,LOWER(TRIM(_xlpm.after))="reach", _xlpm.cleaned, IF( ISNUMBER(--_xlpm.lastToken), _xlfn.TEXTBEFORE(_xlpm.before," ",-1) & " \ " & _xlpm.after, _xlpm.txt ), IF(_xlpm.isReach,_xlpm.txt,TRIM(_xlpm.cleaned)) ), B37 ) -> Auburn Tunnel \ Headflow | I37: =IFERROR( _xlfn.LET( _xlpm.txt,B37, _xlpm.before,TRIM(_xlfn.TEXTBEFORE(_xlpm.txt,"\")), _xlpm.after,TRIM(_xlfn.TEXTAFTER(_xlpm.txt,"\")), _xlpm.lastToken,TRIM(_xlfn.TEXTAFTER(_xlpm.before," ",-1)), _xlpm.isNum,IFERROR(ISNUMBER(--_xlpm.lastToken),FALSE), IF( OR( LOWER(_xlpm.after)="headflow", LOWER(_xlpm.after)="reach" ), "", IF( _xlpm.isNum, _xlpm.lastToken & " \ " & _xlpm.after, "" ) ) ), "" )
A38: D_BRR050_BEC000 | B38: Bear River Canal 0 \ Headflow | C38: SacWAM | D38: =IFERROR( _xlfn.XLOOKUP($H38,WEAP!$F:$F,WEAP!$A:$A), IF($I38="","",_xlfn.XLOOKUP($I38,WEAP!$G:$G,WEAP!$A:$A,"")) ) -> 6539 | E38: =IFERROR( _xlfn.XLOOKUP($H38,WEAP!$F:$F,WEAP!$B:$B), IF($I38="","",_xlfn.XLOOKUP($I38,WEAP!$G:$G,WEAP!$B:$B,"")) ) -> Bear River Canal 0 \ Headflow | F38: =IFERROR( _xlfn.XLOOKUP($H38,WEAP!$F:$F,WEAP!$C:$C), IF($I38="","",_xlfn.XLOOKUP($I38,WEAP!$G:$G,WEAP!$C:$C,"")) ) -> taf | G38: =IFERROR( _xlfn.XLOOKUP($H38,WEAP!$F:$F,WEAP!$E:$E), IF($I38="","",_xlfn.XLOOKUP($I38,WEAP!$G:$G,WEAP!$E:$E,"")) ) -> Streamflow (below node or reach listed) | H38: =IFERROR( _xlfn.LET( _xlpm.txt,TRIM(B38), _xlpm.before,TRIM(_xlfn.TEXTBEFORE(_xlpm.txt,"\",-1)), _xlpm.after,_xlfn.TEXTAFTER(_xlpm.txt,"\"), _xlpm.lastToken,TRIM(_xlfn.TEXTAFTER(_xlpm.before," ",-1)), _xlpm.isReach,LOWER(TRIM(_xlpm.after))="reach", _xlpm.cleaned, IF( ISNUMBER(--_xlpm.lastToken), _xlfn.TEXTBEFORE(_xlpm.before," ",-1) & " \ " & _xlpm.after, _xlpm.txt ), IF(_xlpm.isReach,_xlpm.txt,TRIM(_xlpm.cleaned)) ), B38 ) -> Bear River Canal \ Headflow | I38: =IFERROR( _xlfn.LET( _xlpm.txt,B38, _xlpm.before,TRIM(_xlfn.TEXTBEFORE(_xlpm.txt,"\")), _xlpm.after,TRIM(_xlfn.TEXTAFTER(_xlpm.txt,"\")), _xlpm.lastToken,TRIM(_xlfn.TEXTAFTER(_xlpm.before," ",-1)), _xlpm.isNum,IFERROR(ISNUMBER(--_xlpm.lastToken),FALSE), IF( OR( LOWER(_xlpm.after)="headflow", LOWER(_xlpm.after)="reach" ), "", IF( _xlpm.isNum, _xlpm.lastToken & " \ " & _xlpm.after, "" ) ) ), "" )
A39: D_CCS010_BSC000 | B39: Bowman Spaulding Conduit 0 \ Headflow | C39: SacWAM | D39: =IFERROR( _xlfn.XLOOKUP($H39,WEAP!$F:$F,WEAP!$A:$A), IF($I39="","",_xlfn.XLOOKUP($I39,WEAP!$G:$G,WEAP!$A:$A,"")) ) -> 10839 | E39: =IFERROR( _xlfn.XLOOKUP($H39,WEAP!$F:$F,WEAP!$B:$B), IF($I39="","",_xlfn.XLOOKUP($I39,WEAP!$G:$G,WEAP!$B:$B,"")) ) -> Bowman Spaulding Conduit 0 \ Headflow | F39: =IFERROR( _xlfn.XLOOKUP($H39,WEAP!$F:$F,WEAP!$C:$C), IF($I39="","",_xlfn.XLOOKUP($I39,WEAP!$G:$G,WEAP!$C:$C,"")) ) -> taf | G39: =IFERROR( _xlfn.XLOOKUP($H39,WEAP!$F:$F,WEAP!$E:$E), IF($I39="","",_xlfn.XLOOKUP($I39,WEAP!$G:$G,WEAP!$E:$E,"")) ) -> Streamflow (below node or reach listed) | H39: =IFERROR( _xlfn.LET( _xlpm.txt,TRIM(B39), _xlpm.before,TRIM(_xlfn.TEXTBEFORE(_xlpm.txt,"\",-1)), _xlpm.after,_xlfn.TEXTAFTER(_xlpm.txt,"\"), _xlpm.lastToken,TRIM(_xlfn.TEXTAFTER(_xlpm.before," ",-1)), _xlpm.isReach,LOWER(TRIM(_xlpm.after))="reach", _xlpm.cleaned, IF( ISNUMBER(--_xlpm.lastToken), _xlfn.TEXTBEFORE(_xlpm.before," ",-1) & " \ " & _xlpm.after, _xlpm.txt ), IF(_xlpm.isReach,_xlpm.txt,TRIM(_xlpm.cleaned)) ), B39 ) -> Bowman Spaulding Conduit \ Headflow | I39: =IFERROR( _xlfn.LET( _xlpm.txt,B39, _xlpm.before,TRIM(_xlfn.TEXTBEFORE(_xlpm.txt,"\")), _xlpm.after,TRIM(_xlfn.TEXTAFTER(_xlpm.txt,"\")), _xlpm.lastToken,TRIM(_xlfn.TEXTAFTER(_xlpm.before," ",-1)), _xlpm.isNum,IFERROR(ISNUMBER(--_xlpm.lastToken),FALSE), IF( OR( LOWER(_xlpm.after)="headflow", LOWER(_xlpm.after)="reach" ), "", IF( _xlpm.isNum, _xlpm.lastToken & " \ " & _xlpm.after, "" ) ) ), "" )
A40: D_BSH003_CMN005 | B40: Brush Creek Tunnel 0 \ Headflow | C40: SacWAM | D40: =IFERROR( _xlfn.XLOOKUP($H40,WEAP!$F:$F,WEAP!$A:$A), IF($I40="","",_xlfn.XLOOKUP($I40,WEAP!$G:$G,WEAP!$A:$A,"")) ) -> 13984 | E40: =IFERROR( _xlfn.XLOOKUP($H40,WEAP!$F:$F,WEAP!$B:$B), IF($I40="","",_xlfn.XLOOKUP($I40,WEAP!$G:$G,WEAP!$B:$B,"")) ) -> Brush Creek Tunnel 0 \ Headflow | F40: =IFERROR( _xlfn.XLOOKUP($H40,WEAP!$F:$F,WEAP!$C:$C), IF($I40="","",_xlfn.XLOOKUP($I40,WEAP!$G:$G,WEAP!$C:$C,"")) ) -> taf | G40: =IFERROR( _xlfn.XLOOKUP($H40,WEAP!$F:$F,WEAP!$E:$E), IF($I40="","",_xlfn.XLOOKUP($I40,WEAP!$G:$G,WEAP!$E:$E,"")) ) -> Streamflow (below node or reach listed) | H40: =IFERROR( _xlfn.LET( _xlpm.txt,TRIM(B40), _xlpm.before,TRIM(_xlfn.TEXTBEFORE(_xlpm.txt,"\",-1)), _xlpm.after,_xlfn.TEXTAFTER(_xlpm.txt,"\"), _xlpm.lastToken,TRIM(_xlfn.TEXTAFTER(_xlpm.before," ",-1)), _xlpm.isReach,LOWER(TRIM(_xlpm.after))="reach", _xlpm.cleaned, IF( ISNUMBER(--_xlpm.lastToken), _xlfn.TEXTBEFORE(_xlpm.before," ",-1) & " \ " & _xlpm.after, _xlpm.txt ), IF(_xlpm.isReach,_xlpm.txt,TRIM(_xlpm.cleaned)) ), B40 ) -> Brush Creek Tunnel \ Headflow | I40: =IFERROR( _xlfn.LET( _xlpm.txt,B40, _xlpm.before,TRIM(_xlfn.TEXTBEFORE(_xlpm.txt,"\")), _xlpm.after,TRIM(_xlfn.TEXTAFTER(_xlpm.txt,"\")), _xlpm.lastToken,TRIM(_xlfn.TEXTAFTER(_xlpm.before," ",-1)), _xlpm.isNum,IFERROR(ISNUMBER(--_xlpm.lastToken),FALSE), IF( OR( LOWER(_xlpm.after)="headflow", LOWER(_xlpm.after)="reach" ), "", IF( _xlpm.isNum, _xlpm.lastToken & " \ " & _xlpm.after, "" ) ) ), "" )
A41: D_LRR003_BLT000 | B41: Buck Loon Tunnel 0 \ Headflow | C41: SacWAM | D41: =IFERROR( _xlfn.XLOOKUP($H41,WEAP!$F:$F,WEAP!$A:$A), IF($I41="","",_xlfn.XLOOKUP($I41,WEAP!$G:$G,WEAP!$A:$A,"")) ) -> 11032 | E41: =IFERROR( _xlfn.XLOOKUP($H41,WEAP!$F:$F,WEAP!$B:$B), IF($I41="","",_xlfn.XLOOKUP($I41,WEAP!$G:$G,WEAP!$B:$B,"")) ) -> Buck Loon Tunnel 0 \ Headflow | F41: =IFERROR( _xlfn.XLOOKUP($H41,WEAP!$F:$F,WEAP!$C:$C), IF($I41="","",_xlfn.XLOOKUP($I41,WEAP!$G:$G,WEAP!$C:$C,"")) ) -> taf | G41: =IFERROR( _xlfn.XLOOKUP($H41,WEAP!$F:$F,WEAP!$E:$E), IF($I41="","",_xlfn.XLOOKUP($I41,WEAP!$G:$G,WEAP!$E:$E,"")) ) -> Streamflow (below node or reach listed) | H41: =IFERROR( _xlfn.LET( _xlpm.txt,TRIM(B41), _xlpm.before,TRIM(_xlfn.TEXTBEFORE(_xlpm.txt,"\",-1)), _xlpm.after,_xlfn.TEXTAFTER(_xlpm.txt,"\"), _xlpm.lastToken,TRIM(_xlfn.TEXTAFTER(_xlpm.before," ",-1)), _xlpm.isReach,LOWER(TRIM(_xlpm.after))="reach", _xlpm.cleaned, IF( ISNUMBER(--_xlpm.lastToken), _xlfn.TEXTBEFORE(_xlpm.before," ",-1) & " \ " & _xlpm.after, _xlpm.txt ), IF(_xlpm.isReach,_xlpm.txt,TRIM(_xlpm.cleaned)) ), B41 ) -> Buck Loon Tunnel \ Headflow | I41: =IFERROR( _xlfn.LET( _xlpm.txt,B41, _xlpm.before,TRIM(_xlfn.TEXTBEFORE(_xlpm.txt,"\")), _xlpm.after,TRIM(_xlfn.TEXTAFTER(_xlpm.txt,"\")), _xlpm.lastToken,TRIM(_xlfn.TEXTAFTER(_xlpm.before," ",-1)), _xlpm.isNum,IFERROR(ISNUMBER(--_xlpm.lastToken),FALSE), IF( OR( LOWER(_xlpm.after)="headflow", LOWER(_xlpm.after)="reach" ), "", IF( _xlpm.isNum, _xlpm.lastToken & " \ " & _xlpm.after, "" ) ) ), "" )
A42: C_CAA003 | B42: California Aqueduct 0 \ Headflow | C42: SacWAM | D42: =IFERROR( _xlfn.XLOOKUP($H42,WEAP!$F:$F,WEAP!$A:$A), IF($I42="","",_xlfn.XLOOKUP($I42,WEAP!$G:$G,WEAP!$A:$A,"")) ) -> 6638 | E42: =IFERROR( _xlfn.XLOOKUP($H42,WEAP!$F:$F,WEAP!$B:$B), IF($I42="","",_xlfn.XLOOKUP($I42,WEAP!$G:$G,WEAP!$B:$B,"")) ) -> California Aqueduct 0 \ Headflow | F42: =IFERROR( _xlfn.XLOOKUP($H42,WEAP!$F:$F,WEAP!$C:$C), IF($I42="","",_xlfn.XLOOKUP($I42,WEAP!$G:$G,WEAP!$C:$C,"")) ) -> taf | G42: =IFERROR( _xlfn.XLOOKUP($H42,WEAP!$F:$F,WEAP!$E:$E), IF($I42="","",_xlfn.XLOOKUP($I42,WEAP!$G:$G,WEAP!$E:$E,"")) ) -> Streamflow (below node or reach listed) | H42: =IFERROR( _xlfn.LET( _xlpm.txt,TRIM(B42), _xlpm.before,TRIM(_xlfn.TEXTBEFORE(_xlpm.txt,"\",-1)), _xlpm.after,_xlfn.TEXTAFTER(_xlpm.txt,"\"), _xlpm.lastToken,TRIM(_xlfn.TEXTAFTER(_xlpm.before," ",-1)), _xlpm.isReach,LOWER(TRIM(_xlpm.after))="reach", _xlpm.cleaned, IF( ISNUMBER(--_xlpm.lastToken), _xlfn.TEXTBEFORE(_xlpm.before," ",-1) & " \ " & _xlpm.after, _xlpm.txt ), IF(_xlpm.isReach,_xlpm.txt,TRIM(_xlpm.cleaned)) ), B42 ) -> California Aqueduct \ Headflow | I42: =IFERROR( _xlfn.LET( _xlpm.txt,B42, _xlpm.before,TRIM(_xlfn.TEXTBEFORE(_xlpm.txt,"\")), _xlpm.after,TRIM(_xlfn.TEXTAFTER(_xlpm.txt,"\")), _xlpm.lastToken,TRIM(_xlfn.TEXTAFTER(_xlpm.before," ",-1)), _xlpm.isNum,IFERROR(ISNUMBER(--_xlpm.lastToken),FALSE), IF( OR( LOWER(_xlpm.after)="headflow", LOWER(_xlpm.after)="reach" ), "", IF( _xlpm.isNum, _xlpm.lastToken & " \ " & _xlpm.after, "" ) ) ), "" )
A43: D_JNKSN_ELDID | B43: Jenkinson Lake Camino Conduit 0 \ Headflow | C43: SacWAM | D43: =IFERROR( _xlfn.XLOOKUP($H43,WEAP!$F:$F,WEAP!$A:$A), IF($I43="","",_xlfn.XLOOKUP($I43,WEAP!$G:$G,WEAP!$A:$A,"")) ) -> 14674 | E43: =IFERROR( _xlfn.XLOOKUP($H43,WEAP!$F:$F,WEAP!$B:$B), IF($I43="","",_xlfn.XLOOKUP($I43,WEAP!$G:$G,WEAP!$B:$B,"")) ) -> Jenkinson Lake Camino Conduit 0 \ Headflow | F43: =IFERROR( _xlfn.XLOOKUP($H43,WEAP!$F:$F,WEAP!$C:$C), IF($I43="","",_xlfn.XLOOKUP($I43,WEAP!$G:$G,WEAP!$C:$C,"")) ) -> taf | G43: =IFERROR( _xlfn.XLOOKUP($H43,WEAP!$F:$F,WEAP!$E:$E), IF($I43="","",_xlfn.XLOOKUP($I43,WEAP!$G:$G,WEAP!$E:$E,"")) ) -> Streamflow (below node or reach listed) | H43: =IFERROR( _xlfn.LET( _xlpm.txt,TRIM(B43), _xlpm.before,TRIM(_xlfn.TEXTBEFORE(_xlpm.txt,"\",-1)), _xlpm.after,_xlfn.TEXTAFTER(_xlpm.txt,"\"), _xlpm.lastToken,TRIM(_xlfn.TEXTAFTER(_xlpm.before," ",-1)), _xlpm.isReach,LOWER(TRIM(_xlpm.after))="reach", _xlpm.cleaned, IF( ISNUMBER(--_xlpm.lastToken), _xlfn.TEXTBEFORE(_xlpm.before," ",-1) & " \ " & _xlpm.after, _xlpm.txt ), IF(_xlpm.isReach,_xlpm.txt,TRIM(_xlpm.cleaned)) ), B43 ) -> Jenkinson Lake Camino Conduit \ Headflow | I43: =IFERROR( _xlfn.LET( _xlpm.txt,B43, _xlpm.before,TRIM(_xlfn.TEXTBEFORE(_xlpm.txt,"\")), _xlpm.after,TRIM(_xlfn.TEXTAFTER(_xlpm.txt,"\")), _xlpm.lastToken,TRIM(_xlfn.TEXTAFTER(_xlpm.before," ",-1)), _xlpm.isNum,IFERROR(ISNUMBER(--_xlpm.lastToken),FALSE), IF( OR( LOWER(_xlpm.after)="headflow", LOWER(_xlpm.after)="reach" ), "", IF( _xlpm.isNum, _xlpm.lastToken & " \ " & _xlpm.after, "" ) ) ), "" )
A44: C_CMN006 | B44: Camino Conduit 0 \ Headflow | C44: SacWAM | D44: =IFERROR( _xlfn.XLOOKUP($H44,WEAP!$F:$F,WEAP!$A:$A), IF($I44="","",_xlfn.XLOOKUP($I44,WEAP!$G:$G,WEAP!$A:$A,"")) ) -> 13975 | E44: =IFERROR( _xlfn.XLOOKUP($H44,WEAP!$F:$F,WEAP!$B:$B), IF($I44="","",_xlfn.XLOOKUP($I44,WEAP!$G:$G,WEAP!$B:$B,"")) ) -> Camino Conduit 0 \ Headflow | F44: =IFERROR( _xlfn.XLOOKUP($H44,WEAP!$F:$F,WEAP!$C:$C), IF($I44="","",_xlfn.XLOOKUP($I44,WEAP!$G:$G,WEAP!$C:$C,"")) ) -> taf | G44: =IFERROR( _xlfn.XLOOKUP($H44,WEAP!$F:$F,WEAP!$E:$E), IF($I44="","",_xlfn.XLOOKUP($I44,WEAP!$G:$G,WEAP!$E:$E,"")) ) -> Streamflow (below node or reach listed) | H44: =IFERROR( _xlfn.LET( _xlpm.txt,TRIM(B44), _xlpm.before,TRIM(_xlfn.TEXTBEFORE(_xlpm.txt,"\",-1)), _xlpm.after,_xlfn.TEXTAFTER(_xlpm.txt,"\"), _xlpm.lastToken,TRIM(_xlfn.TEXTAFTER(_xlpm.before," ",-1)), _xlpm.isReach,LOWER(TRIM(_xlpm.after))="reach", _xlpm.cleaned, IF( ISNUMBER(--_xlpm.lastToken), _xlfn.TEXTBEFORE(_xlpm.before," ",-1) & " \ " & _xlpm.after, _xlpm.txt ), IF(_xlpm.isReach,_xlpm.txt,TRIM(_xlpm.cleaned)) ), B44 ) -> Camino Conduit \ Headflow | I44: =IFERROR( _xlfn.LET( _xlpm.txt,B44, _xlpm.before,TRIM(_xlfn.TEXTBEFORE(_xlpm.txt,"\")), _xlpm.after,TRIM(_xlfn.TEXTAFTER(_xlpm.txt,"\")), _xlpm.lastToken,TRIM(_xlfn.TEXTAFTER(_xlpm.before," ",-1)), _xlpm.isNum,IFERROR(ISNUMBER(--_xlpm.lastToken),FALSE), IF( OR( LOWER(_xlpm.after)="headflow", LOWER(_xlpm.after)="reach" ), "", IF( _xlpm.isNum, _xlpm.lastToken & " \ " & _xlpm.after, "" ) ) ), "" )
A45: D_CMP012_JNKSN | B45: Camp Creek Diversion Tunnel 0 \ Headflow | C45: SacWAM | D45: =IFERROR( _xlfn.XLOOKUP($H45,WEAP!$F:$F,WEAP!$A:$A), IF($I45="","",_xlfn.XLOOKUP($I45,WEAP!$G:$G,WEAP!$A:$A,"")) ) -> 11947 | E45: =IFERROR( _xlfn.XLOOKUP($H45,WEAP!$F:$F,WEAP!$B:$B), IF($I45="","",_xlfn.XLOOKUP($I45,WEAP!$G:$G,WEAP!$B:$B,"")) ) -> Camp Creek Diversion Tunnel 0 \ Headflow | F45: =IFERROR( _xlfn.XLOOKUP($H45,WEAP!$F:$F,WEAP!$C:$C), IF($I45="","",_xlfn.XLOOKUP($I45,WEAP!$G:$G,WEAP!$C:$C,"")) ) -> taf | G45: =IFERROR( _xlfn.XLOOKUP($H45,WEAP!$F:$F,WEAP!$E:$E), IF($I45="","",_xlfn.XLOOKUP($I45,WEAP!$G:$G,WEAP!$E:$E,"")) ) -> Streamflow (below node or reach listed) | H45: =IFERROR( _xlfn.LET( _xlpm.txt,TRIM(B45), _xlpm.before,TRIM(_xlfn.TEXTBEFORE(_xlpm.txt,"\",-1)), _xlpm.after,_xlfn.TEXTAFTER(_xlpm.txt,"\"), _xlpm.lastToken,TRIM(_xlfn.TEXTAFTER(_xlpm.before," ",-1)), _xlpm.isReach,LOWER(TRIM(_xlpm.after))="reach", _xlpm.cleaned, IF( ISNUMBER(--_xlpm.lastToken), _xlfn.TEXTBEFORE(_xlpm.before," ",-1) & " \ " & _xlpm.after, _xlpm.txt ), IF(_xlpm.isReach,_xlpm.txt,TRIM(_xlpm.cleaned)) ), B45 ) -> Camp Creek Diversion Tunnel \ Headflow | I45: =IFERROR( _xlfn.LET( _xlpm.txt,B45, _xlpm.before,TRIM(_xlfn.TEXTBEFORE(_xlpm.txt,"\")), _xlpm.after,TRIM(_xlfn.TEXTAFTER(_xlpm.txt,"\")), _xlpm.lastToken,TRIM(_xlfn.TEXTAFTER(_xlpm.before," ",-1)), _xlpm.isNum,IFERROR(ISNUMBER(--_xlpm.lastToken),FALSE), IF( OR( LOWER(_xlpm.after)="headflow", LOWER(_xlpm.after)="reach" ), "", IF( _xlpm.isNum, _xlpm.lastToken & " \ " & _xlpm.after, "" ) ) ), "" )
A46: D_OGN005_CMT000 | B46: Camptonville Tunnel 0 \ Headflow | C46: SacWAM | D46: =IFERROR( _xlfn.XLOOKUP($H46,WEAP!$F:$F,WEAP!$A:$A), IF($I46="","",_xlfn.XLOOKUP($I46,WEAP!$G:$G,WEAP!$A:$A,"")) ) -> 6929 | E46: =IFERROR( _xlfn.XLOOKUP($H46,WEAP!$F:$F,WEAP!$B:$B), IF($I46="","",_xlfn.XLOOKUP($I46,WEAP!$G:$G,WEAP!$B:$B,"")) ) -> Camptonville Tunnel 0 \ Headflow | F46: =IFERROR( _xlfn.XLOOKUP($H46,WEAP!$F:$F,WEAP!$C:$C), IF($I46="","",_xlfn.XLOOKUP($I46,WEAP!$G:$G,WEAP!$C:$C,"")) ) -> taf | G46: =IFERROR( _xlfn.XLOOKUP($H46,WEAP!$F:$F,WEAP!$E:$E), IF($I46="","",_xlfn.XLOOKUP($I46,WEAP!$G:$G,WEAP!$E:$E,"")) ) -> Streamflow (below node or reach listed) | H46: =IFERROR( _xlfn.LET( _xlpm.txt,TRIM(B46), _xlpm.before,TRIM(_xlfn.TEXTBEFORE(_xlpm.txt,"\",-1)), _xlpm.after,_xlfn.TEXTAFTER(_xlpm.txt,"\"), _xlpm.lastToken,TRIM(_xlfn.TEXTAFTER(_xlpm.before," ",-1)), _xlpm.isReach,LOWER(TRIM(_xlpm.after))="reach", _xlpm.cleaned, IF( ISNUMBER(--_xlpm.lastToken), _xlfn.TEXTBEFORE(_xlpm.before," ",-1) & " \ " & _xlpm.after, _xlpm.txt ), IF(_xlpm.isReach,_xlpm.txt,TRIM(_xlpm.cleaned)) ), B46 ) -> Camptonville Tunnel \ Headflow | I46: =IFERROR( _xlfn.LET( _xlpm.txt,B46, _xlpm.before,TRIM(_xlfn.TEXTBEFORE(_xlpm.txt,"\")), _xlpm.after,TRIM(_xlfn.TEXTAFTER(_xlpm.txt,"\")), _xlpm.lastToken,TRIM(_xlfn.TEXTAFTER(_xlpm.before," ",-1)), _xlpm.isNum,IFERROR(ISNUMBER(--_xlpm.lastToken),FALSE), IF( OR( LOWER(_xlpm.after)="headflow", LOWER(_xlpm.after)="reach" ), "", IF( _xlpm.isNum, _xlpm.lastToken & " \ " & _xlpm.after, "" ) ) ), "" )
A47: D_LWSTN_CCT011 | B47: Clear Creek Tunnel 0 \ Headflow | C47: SacWAM | D47: =IFERROR( _xlfn.XLOOKUP($H47,WEAP!$F:$F,WEAP!$A:$A), IF($I47="","",_xlfn.XLOOKUP($I47,WEAP!$G:$G,WEAP!$A:$A,"")) ) -> 11833 | E47: =IFERROR( _xlfn.XLOOKUP($H47,WEAP!$F:$F,WEAP!$B:$B), IF($I47="","",_xlfn.XLOOKUP($I47,WEAP!$G:$G,WEAP!$B:$B,"")) ) -> Clear Creek Tunnel 0 \ Headflow | F47: =IFERROR( _xlfn.XLOOKUP($H47,WEAP!$F:$F,WEAP!$C:$C), IF($I47="","",_xlfn.XLOOKUP($I47,WEAP!$G:$G,WEAP!$C:$C,"")) ) -> taf | G47: =IFERROR( _xlfn.XLOOKUP($H47,WEAP!$F:$F,WEAP!$E:$E), IF($I47="","",_xlfn.XLOOKUP($I47,WEAP!$G:$G,WEAP!$E:$E,"")) ) -> Streamflow (below node or reach listed) | H47: =IFERROR( _xlfn.LET( _xlpm.txt,TRIM(B47), _xlpm.before,TRIM(_xlfn.TEXTBEFORE(_xlpm.txt,"\",-1)), _xlpm.after,_xlfn.TEXTAFTER(_xlpm.txt,"\"), _xlpm.lastToken,TRIM(_xlfn.TEXTAFTER(_xlpm.before," ",-1)), _xlpm.isReach,LOWER(TRIM(_xlpm.after))="reach", _xlpm.cleaned, IF( ISNUMBER(--_xlpm.lastToken), _xlfn.TEXTBEFORE(_xlpm.before," ",-1) & " \ " & _xlpm.after, _xlpm.txt ), IF(_xlpm.isReach,_xlpm.txt,TRIM(_xlpm.cleaned)) ), B47 ) -> Clear Creek Tunnel \ Headflow | I47: =IFERROR( _xlfn.LET( _xlpm.txt,B47, _xlpm.before,TRIM(_xlfn.TEXTBEFORE(_xlpm.txt,"\")), _xlpm.after,TRIM(_xlfn.TEXTAFTER(_xlpm.txt,"\")), _xlpm.lastToken,TRIM(_xlfn.TEXTAFTER(_xlpm.before," ",-1)), _xlpm.isNum,IFERROR(ISNUMBER(--_xlpm.lastToken),FALSE), IF( OR( LOWER(_xlpm.after)="headflow", LOWER(_xlpm.after)="reach" ), "", IF( _xlpm.isNum, _xlpm.lastToken & " \ " & _xlpm.after, "" ) ) ), "" )
A48: R_JBC008_FTR048 | B48: Cox Spill 0 \ Headflow | C48: SacWAM | D48: =IFERROR( _xlfn.XLOOKUP($H48,WEAP!$F:$F,WEAP!$A:$A), IF($I48="","",_xlfn.XLOOKUP($I48,WEAP!$G:$G,WEAP!$A:$A,"")) ) -> 8496 | E48: =IFERROR( _xlfn.XLOOKUP($H48,WEAP!$F:$F,WEAP!$B:$B), IF($I48="","",_xlfn.XLOOKUP($I48,WEAP!$G:$G,WEAP!$B:$B,"")) ) -> Cox Spill 0 \ Headflow | F48: =IFERROR( _xlfn.XLOOKUP($H48,WEAP!$F:$F,WEAP!$C:$C), IF($I48="","",_xlfn.XLOOKUP($I48,WEAP!$G:$G,WEAP!$C:$C,"")) ) -> taf | G48: =IFERROR( _xlfn.XLOOKUP($H48,WEAP!$F:$F,WEAP!$E:$E), IF($I48="","",_xlfn.XLOOKUP($I48,WEAP!$G:$G,WEAP!$E:$E,"")) ) -> Streamflow (below node or reach listed) | H48: =IFERROR( _xlfn.LET( _xlpm.txt,TRIM(B48), _xlpm.before,TRIM(_xlfn.TEXTBEFORE(_xlpm.txt,"\",-1)), _xlpm.after,_xlfn.TEXTAFTER(_xlpm.txt,"\"), _xlpm.lastToken,TRIM(_xlfn.TEXTAFTER(_xlpm.before," ",-1)), _xlpm.isReach,LOWER(TRIM(_xlpm.after))="reach", _xlpm.cleaned, IF( ISNUMBER(--_xlpm.lastToken), _xlfn.TEXTBEFORE(_xlpm.before," ",-1) & " \ " & _xlpm.after, _xlpm.txt ), IF(_xlpm.isReach,_xlpm.txt,TRIM(_xlpm.cleaned)) ), B48 ) -> Cox Spill \ Headflow | I48: =IFERROR( _xlfn.LET( _xlpm.txt,B48, _xlpm.before,TRIM(_xlfn.TEXTBEFORE(_xlpm.txt,"\")), _xlpm.after,TRIM(_xlfn.TEXTAFTER(_xlpm.txt,"\")), _xlpm.lastToken,TRIM(_xlfn.TEXTAFTER(_xlpm.before," ",-1)), _xlpm.isNum,IFERROR(ISNUMBER(--_xlpm.lastToken),FALSE), IF( OR( LOWER(_xlpm.after)="headflow", LOWER(_xlpm.after)="reach" ), "", IF( _xlpm.isNum, _xlpm.lastToken & " \ " & _xlpm.after, "" ) ) ), "" )
... A158: D_CLRLK_CLLPT | B158: Transmission Link from Clear Lake to U_CLLPT_NU | C158: SacWAM | D158: =IFERROR( _xlfn.XLOOKUP($H158,WEAP!$F:$F,WEAP!$A:$A), IF($I158="","",_xlfn.XLOOKUP($I158,WEAP!$G:$G,WEAP!$A:$A,"")) ) -> 7934 | E158: =IFERROR( _xlfn.XLOOKUP($H158,WEAP!$F:$F,WEAP!$B:$B), IF($I158="","",_xlfn.XLOOKUP($I158,WEAP!$G:$G,WEAP!$B:$B,"")) ) -> Transmission Link from Clear Lake to U_CLLPT_NU | F158: =IFERROR( _xlfn.XLOOKUP($H158,WEAP!$F:$F,WEAP!$C:$C), IF($I158="","",_xlfn.XLOOKUP($I158,WEAP!$G:$G,WEAP!$C:$C,"")) ) -> taf | G158: =IFERROR( _xlfn.XLOOKUP($H158,WEAP!$F:$F,WEAP!$E:$E), IF($I158="","",_xlfn.XLOOKUP($I158,WEAP!$G:$G,WEAP!$E:$E,"")) ) -> Transmission Link Flow | H158: =IFERROR( _xlfn.LET( _xlpm.txt,TRIM(B158), _xlpm.before,TRIM(_xlfn.TEXTBEFORE(_xlpm.txt,"\",-1)), _xlpm.after,_xlfn.TEXTAFTER(_xlpm.txt,"\"), _xlpm.lastToken,TRIM(_xlfn.TEXTAFTER(_xlpm.before," ",-1)), _xlpm.isReach,LOWER(TRIM(_xlpm.after))="reach", _xlpm.cleaned, IF( ISNUMBER(--_xlpm.lastToken), _xlfn.TEXTBEFORE(_xlpm.before," ",-1) & " \ " & _xlpm.after, _xlpm.txt ), IF(_xlpm.isReach,_xlpm.txt,TRIM(_xlpm.cleaned)) ), B158 ) -> Transmission Link from Clear Lake to U_CLLPT_NU | I158: =IFERROR( _xlfn.LET( _xlpm.txt,B158, _xlpm.before,TRIM(_xlfn.TEXTBEFORE(_xlpm.txt,"\")), _xlpm.after,TRIM(_xlfn.TEXTAFTER(_xlpm.txt,"\")), _xlpm.lastToken,TRIM(_xlfn.TEXTAFTER(_xlpm.before," ",-1)), _xlpm.isNum,IFERROR(ISNUMBER(--_xlpm.lastToken),FALSE), IF( OR( LOWER(_xlpm.after)="headflow", LOWER(_xlpm.after)="reach" ), "", IF( _xlpm.isNum, _xlpm.lastToken & " \ " & _xlpm.after, "" ) ) ), "" )
A159: D_CCH052_20_NA1 | C159: SacWAM | D159: =IFERROR( _xlfn.XLOOKUP($H159,WEAP!$F:$F,WEAP!$A:$A), IF($I159="","",_xlfn.XLOOKUP($I159,WEAP!$G:$G,WEAP!$A:$A,"")) ) | E159: =IFERROR( _xlfn.XLOOKUP($H159,WEAP!$F:$F,WEAP!$B:$B), IF($I159="","",_xlfn.XLOOKUP($I159,WEAP!$G:$G,WEAP!$B:$B,"")) ) | F159: =IFERROR( _xlfn.XLOOKUP($H159,WEAP!$F:$F,WEAP!$C:$C), IF($I159="","",_xlfn.XLOOKUP($I159,WEAP!$G:$G,WEAP!$C:$C,"")) ) | G159: =IFERROR( _xlfn.XLOOKUP($H159,WEAP!$F:$F,WEAP!$E:$E), IF($I159="","",_xlfn.XLOOKUP($I159,WEAP!$G:$G,WEAP!$E:$E,"")) ) | H159: =IFERROR( _xlfn.LET( _xlpm.txt,TRIM(B159), _xlpm.before,TRIM(_xlfn.TEXTBEFORE(_xlpm.txt,"\",-1)), _xlpm.after,_xlfn.TEXTAFTER(_xlpm.txt,"\"), _xlpm.lastToken,TRIM(_xlfn.TEXTAFTER(_xlpm.before," ",-1)), _xlpm.isReach,LOWER(TRIM(_xlpm.after))="reach", _xlpm.cleaned, IF( ISNUMBER(--_xlpm.lastToken), _xlfn.TEXTBEFORE(_xlpm.before," ",-1) & " \ " & _xlpm.after, _xlpm.txt ), IF(_xlpm.isReach,_xlpm.txt,TRIM(_xlpm.cleaned)) ), B159 ) -> 0 | I159: =IFERROR( _xlfn.LET( _xlpm.txt,B159, _xlpm.before,TRIM(_xlfn.TEXTBEFORE(_xlpm.txt,"\")), _xlpm.after,TRIM(_xlfn.TEXTAFTER(_xlpm.txt,"\")), _xlpm.lastToken,TRIM(_xlfn.TEXTAFTER(_xlpm.before," ",-1)), _xlpm.isNum,IFERROR(ISNUMBER(--_xlpm.lastToken),FALSE), IF( OR( LOWER(_xlpm.after)="headflow", LOWER(_xlpm.after)="reach" ), "", IF( _xlpm.isNum, _xlpm.lastToken & " \ " & _xlpm.after, "" ) ) ), "" )
A160: D_CCH030_20_NA1 | C160: SacWAM | D160: =IFERROR( _xlfn.XLOOKUP($H160,WEAP!$F:$F,WEAP!$A:$A), IF($I160="","",_xlfn.XLOOKUP($I160,WEAP!$G:$G,WEAP!$A:$A,"")) ) | E160: =IFERROR( _xlfn.XLOOKUP($H160,WEAP!$F:$F,WEAP!$B:$B), IF($I160="","",_xlfn.XLOOKUP($I160,WEAP!$G:$G,WEAP!$B:$B,"")) ) | F160: =IFERROR( _xlfn.XLOOKUP($H160,WEAP!$F:$F,WEAP!$C:$C), IF($I160="","",_xlfn.XLOOKUP($I160,WEAP!$G:$G,WEAP!$C:$C,"")) ) | G160: =IFERROR( _xlfn.XLOOKUP($H160,WEAP!$F:$F,WEAP!$E:$E), IF($I160="","",_xlfn.XLOOKUP($I160,WEAP!$G:$G,WEAP!$E:$E,"")) ) | H160: =IFERROR( _xlfn.LET( _xlpm.txt,TRIM(B160), _xlpm.before,TRIM(_xlfn.TEXTBEFORE(_xlpm.txt,"\",-1)), _xlpm.after,_xlfn.TEXTAFTER(_xlpm.txt,"\"), _xlpm.lastToken,TRIM(_xlfn.TEXTAFTER(_xlpm.before," ",-1)), _xlpm.isReach,LOWER(TRIM(_xlpm.after))="reach", _xlpm.cleaned, IF( ISNUMBER(--_xlpm.lastToken), _xlfn.TEXTBEFORE(_xlpm.before," ",-1) & " \ " & _xlpm.after, _xlpm.txt ), IF(_xlpm.isReach,_xlpm.txt,TRIM(_xlpm.cleaned)) ), B160 ) -> 0 | I160: =IFERROR( _xlfn.LET( _xlpm.txt,B160, _xlpm.before,TRIM(_xlfn.TEXTBEFORE(_xlpm.txt,"\")), _xlpm.after,TRIM(_xlfn.TEXTAFTER(_xlpm.txt,"\")), _xlpm.lastToken,TRIM(_xlfn.TEXTAFTER(_xlpm.before," ",-1)), _xlpm.isNum,IFERROR(ISNUMBER(--_xlpm.lastToken),FALSE), IF( OR( LOWER(_xlpm.after)="headflow", LOWER(_xlpm.after)="reach" ), "", IF( _xlpm.isNum, _xlpm.lastToken & " \ " & _xlpm.after, "" ) ) ), "" )
A161: D_CCH_YCFCWCD | B161: Transmission Link from Cache Creek RM 030 to A_20_25_NA1 | C161: SacWAM | D161: =IFERROR( _xlfn.XLOOKUP($H161,WEAP!$F:$F,WEAP!$A:$A), IF($I161="","",_xlfn.XLOOKUP($I161,WEAP!$G:$G,WEAP!$A:$A,"")) ) -> 8021 | E161: =IFERROR( _xlfn.XLOOKUP($H161,WEAP!$F:$F,WEAP!$B:$B), IF($I161="","",_xlfn.XLOOKUP($I161,WEAP!$G:$G,WEAP!$B:$B,"")) ) -> Transmission Link from Cache Creek RM 030 to A_20_25_NA1 | F161: =IFERROR( _xlfn.XLOOKUP($H161,WEAP!$F:$F,WEAP!$C:$C), IF($I161="","",_xlfn.XLOOKUP($I161,WEAP!$G:$G,WEAP!$C:$C,"")) ) -> taf | G161: =IFERROR( _xlfn.XLOOKUP($H161,WEAP!$F:$F,WEAP!$E:$E), IF($I161="","",_xlfn.XLOOKUP($I161,WEAP!$G:$G,WEAP!$E:$E,"")) ) -> Transmission Link Flow | H161: =IFERROR( _xlfn.LET( _xlpm.txt,TRIM(B161), _xlpm.before,TRIM(_xlfn.TEXTBEFORE(_xlpm.txt,"\",-1)), _xlpm.after,_xlfn.TEXTAFTER(_xlpm.txt,"\"), _xlpm.lastToken,TRIM(_xlfn.TEXTAFTER(_xlpm.before," ",-1)), _xlpm.isReach,LOWER(TRIM(_xlpm.after))="reach", _xlpm.cleaned, IF( ISNUMBER(--_xlpm.lastToken), _xlfn.TEXTBEFORE(_xlpm.before," ",-1) & " \ " & _xlpm.after, _xlpm.txt ), IF(_xlpm.isReach,_xlpm.txt,TRIM(_xlpm.cleaned)) ), B161 ) -> Transmission Link from Cache Creek RM 030 to A_20_25_NA1 | I161: =IFERROR( _xlfn.LET( _xlpm.txt,B161, _xlpm.before,TRIM(_xlfn.TEXTBEFORE(_xlpm.txt,"\")), _xlpm.after,TRIM(_xlfn.TEXTAFTER(_xlpm.txt,"\")), _xlpm.lastToken,TRIM(_xlfn.TEXTAFTER(_xlpm.before," ",-1)), _xlpm.isNum,IFERROR(ISNUMBER(--_xlpm.lastToken),FALSE), IF( OR( LOWER(_xlpm.after)="headflow", LOWER(_xlpm.after)="reach" ), "", IF( _xlpm.isNum, _xlpm.lastToken & " \ " & _xlpm.after, "" ) ) ), "" )
A162: Total Diversions Calaveras River | B162: Total Diversions Calaveras River | C162: SacWAM | D162: =IFERROR( _xlfn.XLOOKUP($H162,WEAP!$F:$F,WEAP!$A:$A), IF($I162="","",_xlfn.XLOOKUP($I162,WEAP!$G:$G,WEAP!$A:$A,"")) ) | E162: =IFERROR( _xlfn.XLOOKUP($H162,WEAP!$F:$F,WEAP!$B:$B), IF($I162="","",_xlfn.XLOOKUP($I162,WEAP!$G:$G,WEAP!$B:$B,"")) ) | F162: =IFERROR( _xlfn.XLOOKUP($H162,WEAP!$F:$F,WEAP!$C:$C), IF($I162="","",_xlfn.XLOOKUP($I162,WEAP!$G:$G,WEAP!$C:$C,"")) ) | G162: =IFERROR( _xlfn.XLOOKUP($H162,WEAP!$F:$F,WEAP!$E:$E), IF($I162="","",_xlfn.XLOOKUP($I162,WEAP!$G:$G,WEAP!$E:$E,"")) ) | H162: =IFERROR( _xlfn.LET( _xlpm.txt,TRIM(B162), _xlpm.before,TRIM(_xlfn.TEXTBEFORE(_xlpm.txt,"\",-1)), _xlpm.after,_xlfn.TEXTAFTER(_xlpm.txt,"\"), _xlpm.lastToken,TRIM(_xlfn.TEXTAFTER(_xlpm.before," ",-1)), _xlpm.isReach,LOWER(TRIM(_xlpm.after))="reach", _xlpm.cleaned, IF( ISNUMBER(--_xlpm.lastToken), _xlfn.TEXTBEFORE(_xlpm.before," ",-1) & " \ " & _xlpm.after, _xlpm.txt ), IF(_xlpm.isReach,_xlpm.txt,TRIM(_xlpm.cleaned)) ), B162 ) -> Total Diversions Calaveras River | I162: =IFERROR( _xlfn.LET( _xlpm.txt,B162, _xlpm.before,TRIM(_xlfn.TEXTBEFORE(_xlpm.txt,"\")), _xlpm.after,TRIM(_xlfn.TEXTAFTER(_xlpm.txt,"\")), _xlpm.lastToken,TRIM(_xlfn.TEXTAFTER(_xlpm.before," ",-1)), _xlpm.isNum,IFERROR(ISNUMBER(--_xlpm.lastToken),FALSE), IF( OR( LOWER(_xlpm.after)="headflow", LOWER(_xlpm.after)="reach" ), "", IF( _xlpm.isNum, _xlpm.lastToken & " \ " & _xlpm.after, "" ) ) ), "" )
A163: D_CLV026_60S_PA1 | B163: Transmission Link from Calaveras River RM 026 to A_60S_PA | C163: SacWAM | D163: =IFERROR( _xlfn.XLOOKUP($H163,WEAP!$F:$F,WEAP!$A:$A), IF($I163="","",_xlfn.XLOOKUP($I163,WEAP!$G:$G,WEAP!$A:$A,"")) ) -> 13284 | E163: =IFERROR( _xlfn.XLOOKUP($H163,WEAP!$F:$F,WEAP!$B:$B), IF($I163="","",_xlfn.XLOOKUP($I163,WEAP!$G:$G,WEAP!$B:$B,"")) ) -> Transmission Link from Calaveras River RM 026 to A_60S_PA | F163: =IFERROR( _xlfn.XLOOKUP($H163,WEAP!$F:$F,WEAP!$C:$C), IF($I163="","",_xlfn.XLOOKUP($I163,WEAP!$G:$G,WEAP!$C:$C,"")) ) -> taf | G163: =IFERROR( _xlfn.XLOOKUP($H163,WEAP!$F:$F,WEAP!$E:$E), IF($I163="","",_xlfn.XLOOKUP($I163,WEAP!$G:$G,WEAP!$E:$E,"")) ) -> Transmission Link Flow | H163: =IFERROR( _xlfn.LET( _xlpm.txt,TRIM(B163), _xlpm.before,TRIM(_xlfn.TEXTBEFORE(_xlpm.txt,"\",-1)), _xlpm.after,_xlfn.TEXTAFTER(_xlpm.txt,"\"), _xlpm.lastToken,TRIM(_xlfn.TEXTAFTER(_xlpm.before," ",-1)), _xlpm.isReach,LOWER(TRIM(_xlpm.after))="reach", _xlpm.cleaned, IF( ISNUMBER(--_xlpm.lastToken), _xlfn.TEXTBEFORE(_xlpm.before," ",-1) & " \ " & _xlpm.after, _xlpm.txt ), IF(_xlpm.isReach,_xlpm.txt,TRIM(_xlpm.cleaned)) ), B163 ) -> Transmission Link from Calaveras River RM 026 to A_60S_PA | I163: =IFERROR( _xlfn.LET( _xlpm.txt,B163, _xlpm.before,TRIM(_xlfn.TEXTBEFORE(_xlpm.txt,"\")), _xlpm.after,TRIM(_xlfn.TEXTAFTER(_xlpm.txt,"\")), _xlpm.lastToken,TRIM(_xlfn.TEXTAFTER(_xlpm.before," ",-1)), _xlpm.isNum,IFERROR(ISNUMBER(--_xlpm.lastToken),FALSE), IF( OR( LOWER(_xlpm.after)="headflow", LOWER(_xlpm.after)="reach" ), "", IF( _xlpm.isNum, _xlpm.lastToken & " \ " & _xlpm.after, "" ) ) ), "" )
A164: D_CLV037_CACWD | C164: SacWAM | D164: =IFERROR( _xlfn.XLOOKUP($H164,WEAP!$F:$F,WEAP!$A:$A), IF($I164="","",_xlfn.XLOOKUP($I164,WEAP!$G:$G,WEAP!$A:$A,"")) ) | E164: =IFERROR( _xlfn.XLOOKUP($H164,WEAP!$F:$F,WEAP!$B:$B), IF($I164="","",_xlfn.XLOOKUP($I164,WEAP!$G:$G,WEAP!$B:$B,"")) ) | F164: =IFERROR( _xlfn.XLOOKUP($H164,WEAP!$F:$F,WEAP!$C:$C), IF($I164="","",_xlfn.XLOOKUP($I164,WEAP!$G:$G,WEAP!$C:$C,"")) ) | G164: =IFERROR( _xlfn.XLOOKUP($H164,WEAP!$F:$F,WEAP!$E:$E), IF($I164="","",_xlfn.XLOOKUP($I164,WEAP!$G:$G,WEAP!$E:$E,"")) ) | H164: =IFERROR( _xlfn.LET( _xlpm.txt,TRIM(B164), _xlpm.before,TRIM(_xlfn.TEXTBEFORE(_xlpm.txt,"\",-1)), _xlpm.after,_xlfn.TEXTAFTER(_xlpm.txt,"\"), _xlpm.lastToken,TRIM(_xlfn.TEXTAFTER(_xlpm.before," ",-1)), _xlpm.isReach,LOWER(TRIM(_xlpm.after))="reach", _xlpm.cleaned, IF( ISNUMBER(--_xlpm.lastToken), _xlfn.TEXTBEFORE(_xlpm.before," ",-1) & " \ " & _xlpm.after, _xlpm.txt ), IF(_xlpm.isReach,_xlpm.txt,TRIM(_xlpm.cleaned)) ), B164 ) -> 0 | I164: =IFERROR( _xlfn.LET( _xlpm.txt,B164, _xlpm.before,TRIM(_xlfn.TEXTBEFORE(_xlpm.txt,"\")), _xlpm.after,TRIM(_xlfn.TEXTAFTER(_xlpm.txt,"\")), _xlpm.lastToken,TRIM(_xlfn.TEXTAFTER(_xlpm.before," ",-1)), _xlpm.isNum,IFERROR(ISNUMBER(--_xlpm.lastToken),FALSE), IF( OR( LOWER(_xlpm.after)="headflow", LOWER(_xlpm.after)="reach" ), "", IF( _xlpm.isNum, _xlpm.lastToken & " \ " & _xlpm.after, "" ) ) ), "" )
A165: D_CLV026_WTPWDH | B165: Transmission Link from Calaveras River RM 026 to U_60S_NU1 | C165: SacWAM | D165: =IFERROR( _xlfn.XLOOKUP($H165,WEAP!$F:$F,WEAP!$A:$A), IF($I165="","",_xlfn.XLOOKUP($I165,WEAP!$G:$G,WEAP!$A:$A,"")) ) -> 13283 | E165: =IFERROR( _xlfn.XLOOKUP($H165,WEAP!$F:$F,WEAP!$B:$B), IF($I165="","",_xlfn.XLOOKUP($I165,WEAP!$G:$G,WEAP!$B:$B,"")) ) -> Transmission Link from Calaveras River RM 026 to U_60S_NU1 | F165: =IFERROR( _xlfn.XLOOKUP($H165,WEAP!$F:$F,WEAP!$C:$C), IF($I165="","",_xlfn.XLOOKUP($I165,WEAP!$G:$G,WEAP!$C:$C,"")) ) -> taf | G165: =IFERROR( _xlfn.XLOOKUP($H165,WEAP!$F:$F,WEAP!$E:$E), IF($I165="","",_xlfn.XLOOKUP($I165,WEAP!$G:$G,WEAP!$E:$E,"")) ) -> Transmission Link Flow | H165: =IFERROR( _xlfn.LET( _xlpm.txt,TRIM(B165), _xlpm.before,TRIM(_xlfn.TEXTBEFORE(_xlpm.txt,"\",-1)), _xlpm.after,_xlfn.TEXTAFTER(_xlpm.txt,"\"), _xlpm.lastToken,TRIM(_xlfn.TEXTAFTER(_xlpm.before," ",-1)), _xlpm.isReach,LOWER(TRIM(_xlpm.after))="reach", _xlpm.cleaned, IF( ISNUMBER(--_xlpm.lastToken), _xlfn.TEXTBEFORE(_xlpm.before," ",-1) & " \ " & _xlpm.after, _xlpm.txt ), IF(_xlpm.isReach,_xlpm.txt,TRIM(_xlpm.cleaned)) ), B165 ) -> Transmission Link from Calaveras River RM 026 to U_60S_NU1 | I165: =IFERROR( _xlfn.LET( _xlpm.txt,B165, _xlpm.before,TRIM(_xlfn.TEXTBEFORE(_xlpm.txt,"\")), _xlpm.after,TRIM(_xlfn.TEXTAFTER(_xlpm.txt,"\")), _xlpm.lastToken,TRIM(_xlfn.TEXTAFTER(_xlpm.before," ",-1)), _xlpm.isNum,IFERROR(ISNUMBER(--_xlpm.lastToken),FALSE), IF( OR( LOWER(_xlpm.after)="headflow", LOWER(_xlpm.after)="reach" ), "", IF( _xlpm.isNum, _xlpm.lastToken & " \ " & _xlpm.after, "" ) ) ), "" )
A166: D_CLV043_WTPJYL | B166: Transmission Link from Calaveras River RM 043 to U_JLIND_NU | C166: SacWAM | D166: =IFERROR( _xlfn.XLOOKUP($H166,WEAP!$F:$F,WEAP!$A:$A), IF($I166="","",_xlfn.XLOOKUP($I166,WEAP!$G:$G,WEAP!$A:$A,"")) ) -> 7959 | E166: =IFERROR( _xlfn.XLOOKUP($H166,WEAP!$F:$F,WEAP!$B:$B), IF($I166="","",_xlfn.XLOOKUP($I166,WEAP!$G:$G,WEAP!$B:$B,"")) ) -> Transmission Link from Calaveras River RM 043 to U_JLIND_NU | F166: =IFERROR( _xlfn.XLOOKUP($H166,WEAP!$F:$F,WEAP!$C:$C), IF($I166="","",_xlfn.XLOOKUP($I166,WEAP!$G:$G,WEAP!$C:$C,"")) ) -> taf | G166: =IFERROR( _xlfn.XLOOKUP($H166,WEAP!$F:$F,WEAP!$E:$E), IF($I166="","",_xlfn.XLOOKUP($I166,WEAP!$G:$G,WEAP!$E:$E,"")) ) -> Transmission Link Flow | H166: =IFERROR( _xlfn.LET( _xlpm.txt,TRIM(B166), _xlpm.before,TRIM(_xlfn.TEXTBEFORE(_xlpm.txt,"\",-1)), _xlpm.after,_xlfn.TEXTAFTER(_xlpm.txt,"\"), _xlpm.lastToken,TRIM(_xlfn.TEXTAFTER(_xlpm.before," ",-1)), _xlpm.isReach,LOWER(TRIM(_xlpm.after))="reach", _xlpm.cleaned, IF( ISNUMBER(--_xlpm.lastToken), _xlfn.TEXTBEFORE(_xlpm.before," ",-1) & " \ " & _xlpm.after, _xlpm.txt ), IF(_xlpm.isReach,_xlpm.txt,TRIM(_xlpm.cleaned)) ), B166 ) -> Transmission Link from Calaveras River RM 043 to U_JLIND_NU | I166: =IFERROR( _xlfn.LET( _xlpm.txt,B166, _xlpm.before,TRIM(_xlfn.TEXTBEFORE(_xlpm.txt,"\")), _xlpm.after,TRIM(_xlfn.TEXTAFTER(_xlpm.txt,"\")), _xlpm.lastToken,TRIM(_xlfn.TEXTAFTER(_xlpm.before," ",-1)), _xlpm.isNum,IFERROR(ISNUMBER(--_xlpm.lastToken),FALSE), IF( OR( LOWER(_xlpm.after)="headflow", LOWER(_xlpm.after)="reach" ), "", IF( _xlpm.isNum, _xlpm.lastToken & " \ " & _xlpm.after, "" ) ) ), "" )
A167: Total Diversions Feather River | B167: Total Diversions Feather River | C167: SacWAM | D167: =IFERROR( _xlfn.XLOOKUP($H167,WEAP!$F:$F,WEAP!$A:$A), IF($I167="","",_xlfn.XLOOKUP($I167,WEAP!$G:$G,WEAP!$A:$A,"")) ) | E167: =IFERROR( _xlfn.XLOOKUP($H167,WEAP!$F:$F,WEAP!$B:$B), IF($I167="","",_xlfn.XLOOKUP($I167,WEAP!$G:$G,WEAP!$B:$B,"")) ) | F167: =IFERROR( _xlfn.XLOOKUP($H167,WEAP!$F:$F,WEAP!$C:$C), IF($I167="","",_xlfn.XLOOKUP($I167,WEAP!$G:$G,WEAP!$C:$C,"")) ) | G167: =IFERROR( _xlfn.XLOOKUP($H167,WEAP!$F:$F,WEAP!$E:$E), IF($I167="","",_xlfn.XLOOKUP($I167,WEAP!$G:$G,WEAP!$E:$E,"")) ) | H167: =IFERROR( _xlfn.LET( _xlpm.txt,TRIM(B167), _xlpm.before,TRIM(_xlfn.TEXTBEFORE(_xlpm.txt,"\",-1)), _xlpm.after,_xlfn.TEXTAFTER(_xlpm.txt,"\"), _xlpm.lastToken,TRIM(_xlfn.TEXTAFTER(_xlpm.before," ",-1)), _xlpm.isReach,LOWER(TRIM(_xlpm.after))="reach", _xlpm.cleaned, IF( ISNUMBER(--_xlpm.lastToken), _xlfn.TEXTBEFORE(_xlpm.before," ",-1) & " \ " & _xlpm.after, _xlpm.txt ), IF(_xlpm.isReach,_xlpm.txt,TRIM(_xlpm.cleaned)) ), B167 ) -> Total Diversions Feather River | I167: =IFERROR( _xlfn.LET( _xlpm.txt,B167, _xlpm.before,TRIM(_xlfn.TEXTBEFORE(_xlpm.txt,"\")), _xlpm.after,TRIM(_xlfn.TEXTAFTER(_xlpm.txt,"\")), _xlpm.lastToken,TRIM(_xlfn.TEXTAFTER(_xlpm.before," ",-1)), _xlpm.isNum,IFERROR(ISNUMBER(--_xlpm.lastToken),FALSE), IF( OR( LOWER(_xlpm.after)="headflow", LOWER(_xlpm.after)="reach" ), "", IF( _xlpm.isNum, _xlpm.lastToken & " \ " & _xlpm.after, "" ) ) ), "" )
A168: D_LST004_OWC000 | B168: Transmission Link from Oroville Wyandotte Canal CM 000 to A_12_13_NA | C168: SacWAM | D168: =IFERROR( _xlfn.XLOOKUP($H168,WEAP!$F:$F,WEAP!$A:$A), IF($I168="","",_xlfn.XLOOKUP($I168,WEAP!$G:$G,WEAP!$A:$A,"")) ) -> 6877 | E168: =IFERROR( _xlfn.XLOOKUP($H168,WEAP!$F:$F,WEAP!$B:$B), IF($I168="","",_xlfn.XLOOKUP($I168,WEAP!$G:$G,WEAP!$B:$B,"")) ) -> Transmission Link from Oroville Wyandotte Canal CM 000 to A_12_13_NA | F168: =IFERROR( _xlfn.XLOOKUP($H168,WEAP!$F:$F,WEAP!$C:$C), IF($I168="","",_xlfn.XLOOKUP($I168,WEAP!$G:$G,WEAP!$C:$C,"")) ) -> taf | G168: =IFERROR( _xlfn.XLOOKUP($H168,WEAP!$F:$F,WEAP!$E:$E), IF($I168="","",_xlfn.XLOOKUP($I168,WEAP!$G:$G,WEAP!$E:$E,"")) ) -> Transmission Link Flow | H168: =IFERROR( _xlfn.LET( _xlpm.txt,TRIM(B168), _xlpm.before,TRIM(_xlfn.TEXTBEFORE(_xlpm.txt,"\",-1)), _xlpm.after,_xlfn.TEXTAFTER(_xlpm.txt,"\"), _xlpm.lastToken,TRIM(_xlfn.TEXTAFTER(_xlpm.before," ",-1)), _xlpm.isReach,LOWER(TRIM(_xlpm.after))="reach", _xlpm.cleaned, IF( ISNUMBER(--_xlpm.lastToken), _xlfn.TEXTBEFORE(_xlpm.before," ",-1) & " \ " & _xlpm.after, _xlpm.txt ), IF(_xlpm.isReach,_xlpm.txt,TRIM(_xlpm.cleaned)) ), B168 ) -> Transmission Link from Oroville Wyandotte Canal CM 000 to A_12_13_NA | I168: =IFERROR( _xlfn.LET( _xlpm.txt,B168, _xlpm.before,TRIM(_xlfn.TEXTBEFORE(_xlpm.txt,"\")), _xlpm.after,TRIM(_xlfn.TEXTAFTER(_xlpm.txt,"\")), _xlpm.lastToken,TRIM(_xlfn.TEXTAFTER(_xlpm.before," ",-1)), _xlpm.isNum,IFERROR(ISNUMBER(--_xlpm.lastToken),FALSE), IF( OR( LOWER(_xlpm.after)="headflow", LOWER(_xlpm.after)="reach" ), "", IF( _xlpm.isNum, _xlpm.lastToken & " \ " & _xlpm.after, "" ) ) ), "" )
A169: D_SFF011_MNRRH | B169: Miners Ranch Canal 0 \ Headflow | C169: SacWAM | D169: =IFERROR( _xlfn.XLOOKUP($H169,WEAP!$F:$F,WEAP!$A:$A), IF($I169="","",_xlfn.XLOOKUP($I169,WEAP!$G:$G,WEAP!$A:$A,"")) ) -> 6898 | E169: =IFERROR( _xlfn.XLOOKUP($H169,WEAP!$F:$F,WEAP!$B:$B), IF($I169="","",_xlfn.XLOOKUP($I169,WEAP!$G:$G,WEAP!$B:$B,"")) ) -> Miners Ranch Canal 0 \ Headflow | F169: =IFERROR( _xlfn.XLOOKUP($H169,WEAP!$F:$F,WEAP!$C:$C), IF($I169="","",_xlfn.XLOOKUP($I169,WEAP!$G:$G,WEAP!$C:$C,"")) ) -> taf | G169: =IFERROR( _xlfn.XLOOKUP($H169,WEAP!$F:$F,WEAP!$E:$E), IF($I169="","",_xlfn.XLOOKUP($I169,WEAP!$G:$G,WEAP!$E:$E,"")) ) -> Streamflow (below node or reach listed) | H169: =IFERROR( _xlfn.LET( _xlpm.txt,TRIM(B169), _xlpm.before,TRIM(_xlfn.TEXTBEFORE(_xlpm.txt,"\",-1)), _xlpm.after,_xlfn.TEXTAFTER(_xlpm.txt,"\"), _xlpm.lastToken,TRIM(_xlfn.TEXTAFTER(_xlpm.before," ",-1)), _xlpm.isReach,LOWER(TRIM(_xlpm.after))="reach", _xlpm.cleaned, IF( ISNUMBER(--_xlpm.lastToken), _xlfn.TEXTBEFORE(_xlpm.before," ",-1) & " \ " & _xlpm.after, _xlpm.txt ), IF(_xlpm.isReach,_xlpm.txt,TRIM(_xlpm.cleaned)) ), B169 ) -> Miners Ranch Canal \ Headflow | I169: =IFERROR( _xlfn.LET( _xlpm.txt,B169, _xlpm.before,TRIM(_xlfn.TEXTBEFORE(_xlpm.txt,"\")), _xlpm.after,TRIM(_xlfn.TEXTAFTER(_xlpm.txt,"\")), _xlpm.lastToken,TRIM(_xlfn.TEXTAFTER(_xlpm.before," ",-1)), _xlpm.isNum,IFERROR(ISNUMBER(--_xlpm.lastToken),FALSE), IF( OR( LOWER(_xlpm.after)="headflow", LOWER(_xlpm.after)="reach" ), "", IF( _xlpm.isNum, _xlpm.lastToken & " \ " & _xlpm.after, "" ) ) ), "" )
A170: D_OROVL_13_NU1 | B170: Palermo Canal 0 \ Headflow | C170: SacWAM | D170: =IFERROR( _xlfn.XLOOKUP($H170,WEAP!$F:$F,WEAP!$A:$A), IF($I170="","",_xlfn.XLOOKUP($I170,WEAP!$G:$G,WEAP!$A:$A,"")) ) -> 8480 | E170: =IFERROR( _xlfn.XLOOKUP($H170,WEAP!$F:$F,WEAP!$B:$B), IF($I170="","",_xlfn.XLOOKUP($I170,WEAP!$G:$G,WEAP!$B:$B,"")) ) -> Palermo Canal 0 \ Headflow | F170: =IFERROR( _xlfn.XLOOKUP($H170,WEAP!$F:$F,WEAP!$C:$C), IF($I170="","",_xlfn.XLOOKUP($I170,WEAP!$G:$G,WEAP!$C:$C,"")) ) -> taf | G170: =IFERROR( _xlfn.XLOOKUP($H170,WEAP!$F:$F,WEAP!$E:$E), IF($I170="","",_xlfn.XLOOKUP($I170,WEAP!$G:$G,WEAP!$E:$E,"")) ) -> Streamflow (below node or reach listed) | H170: =IFERROR( _xlfn.LET( _xlpm.txt,TRIM(B170), _xlpm.before,TRIM(_xlfn.TEXTBEFORE(_xlpm.txt,"\",-1)), _xlpm.after,_xlfn.TEXTAFTER(_xlpm.txt,"\"), _xlpm.lastToken,TRIM(_xlfn.TEXTAFTER(_xlpm.before," ",-1)), _xlpm.isReach,LOWER(TRIM(_xlpm.after))="reach", _xlpm.cleaned, IF( ISNUMBER(--_xlpm.lastToken), _xlfn.TEXTBEFORE(_xlpm.before," ",-1) & " \ " & _xlpm.after, _xlpm.txt ), IF(_xlpm.isReach,_xlpm.txt,TRIM(_xlpm.cleaned)) ), B170 ) -> Palermo Canal \ Headflow | I170: =IFERROR( _xlfn.LET( _xlpm.txt,B170, _xlpm.before,TRIM(_xlfn.TEXTBEFORE(_xlpm.txt,"\")), _xlpm.after,TRIM(_xlfn.TEXTAFTER(_xlpm.txt,"\")), _xlpm.lastToken,TRIM(_xlfn.TEXTAFTER(_xlpm.before," ",-1)), _xlpm.isNum,IFERROR(ISNUMBER(--_xlpm.lastToken),FALSE), IF( OR( LOWER(_xlpm.after)="headflow", LOWER(_xlpm.after)="reach" ), "", IF( _xlpm.isNum, _xlpm.lastToken & " \ " & _xlpm.after, "" ) ) ), "" )
A171: D_THRMF_11_NU1 | B171: Transmission Link from Power Canal SWP water to U_11_NU1 | C171: SacWAM | D171: =IFERROR( _xlfn.XLOOKUP($H171,WEAP!$F:$F,WEAP!$A:$A), IF($I171="","",_xlfn.XLOOKUP($I171,WEAP!$G:$G,WEAP!$A:$A,"")) ) -> 7538 | E171: =IFERROR( _xlfn.XLOOKUP($H171,WEAP!$F:$F,WEAP!$B:$B), IF($I171="","",_xlfn.XLOOKUP($I171,WEAP!$G:$G,WEAP!$B:$B,"")) ) -> Transmission Link from Power Canal SWP water to U_11_NU1 | F171: =IFERROR( _xlfn.XLOOKUP($H171,WEAP!$F:$F,WEAP!$C:$C), IF($I171="","",_xlfn.XLOOKUP($I171,WEAP!$G:$G,WEAP!$C:$C,"")) ) -> taf | G171: =IFERROR( _xlfn.XLOOKUP($H171,WEAP!$F:$F,WEAP!$E:$E), IF($I171="","",_xlfn.XLOOKUP($I171,WEAP!$G:$G,WEAP!$E:$E,"")) ) -> Transmission Link Flow | H171: =IFERROR( _xlfn.LET( _xlpm.txt,TRIM(B171), _xlpm.before,TRIM(_xlfn.TEXTBEFORE(_xlpm.txt,"\",-1)), _xlpm.after,_xlfn.TEXTAFTER(_xlpm.txt,"\"), _xlpm.lastToken,TRIM(_xlfn.TEXTAFTER(_xlpm.before," ",-1)), _xlpm.isReach,LOWER(TRIM(_xlpm.after))="reach", _xlpm.cleaned, IF( ISNUMBER(--_xlpm.lastToken), _xlfn.TEXTBEFORE(_xlpm.before," ",-1) & " \ " & _xlpm.after, _xlpm.txt ), IF(_xlpm.isReach,_xlpm.txt,TRIM(_xlpm.cleaned)) ), B171 ) -> Transmission Link from Power Canal SWP water to U_11_NU1 | I171: =IFERROR( _xlfn.LET( _xlpm.txt,B171, _xlpm.before,TRIM(_xlfn.TEXTBEFORE(_xlpm.txt,"\")), _xlpm.after,TRIM(_xlfn.TEXTAFTER(_xlpm.txt,"\")), _xlpm.lastToken,TRIM(_xlfn.TEXTAFTER(_xlpm.before," ",-1)), _xlpm.isNum,IFERROR(ISNUMBER(--_xlpm.lastToken),FALSE), IF( OR( LOWER(_xlpm.after)="headflow", LOWER(_xlpm.after)="reach" ), "", IF( _xlpm.isNum, _xlpm.lastToken & " \ " & _xlpm.after, "" ) ) ), "" )
A172: D_THRMF_12_NU1 | B172: Transmission Link from Power Canal SWP water to U_12_13_NU1 | C172: SacWAM | D172: =IFERROR( _xlfn.XLOOKUP($H172,WEAP!$F:$F,WEAP!$A:$A), IF($I172="","",_xlfn.XLOOKUP($I172,WEAP!$G:$G,WEAP!$A:$A,"")) ) -> 7550 | E172: =IFERROR( _xlfn.XLOOKUP($H172,WEAP!$F:$F,WEAP!$B:$B), IF($I172="","",_xlfn.XLOOKUP($I172,WEAP!$G:$G,WEAP!$B:$B,"")) ) -> Transmission Link from Power Canal SWP water to U_12_13_NU1 | F172: =IFERROR( _xlfn.XLOOKUP($H172,WEAP!$F:$F,WEAP!$C:$C), IF($I172="","",_xlfn.XLOOKUP($I172,WEAP!$G:$G,WEAP!$C:$C,"")) ) -> taf | G172: =IFERROR( _xlfn.XLOOKUP($H172,WEAP!$F:$F,WEAP!$E:$E), IF($I172="","",_xlfn.XLOOKUP($I172,WEAP!$G:$G,WEAP!$E:$E,"")) ) -> Transmission Link Flow | H172: =IFERROR( _xlfn.LET( _xlpm.txt,TRIM(B172), _xlpm.before,TRIM(_xlfn.TEXTBEFORE(_xlpm.txt,"\",-1)), _xlpm.after,_xlfn.TEXTAFTER(_xlpm.txt,"\"), _xlpm.lastToken,TRIM(_xlfn.TEXTAFTER(_xlpm.before," ",-1)), _xlpm.isReach,LOWER(TRIM(_xlpm.after))="reach", _xlpm.cleaned, IF( ISNUMBER(--_xlpm.lastToken), _xlfn.TEXTBEFORE(_xlpm.before," ",-1) & " \ " & _xlpm.after, _xlpm.txt ), IF(_xlpm.isReach,_xlpm.txt,TRIM(_xlpm.cleaned)) ), B172 ) -> Transmission Link from Power Canal SWP water to U_12_13_NU1 | I172: =IFERROR( _xlfn.LET( _xlpm.txt,B172, _xlpm.before,TRIM(_xlfn.TEXTBEFORE(_xlpm.txt,"\")), _xlpm.after,TRIM(_xlfn.TEXTAFTER(_xlpm.txt,"\")), _xlpm.lastToken,TRIM(_xlfn.TEXTAFTER(_xlpm.before," ",-1)), _xlpm.isNum,IFERROR(ISNUMBER(--_xlpm.lastToken),FALSE), IF( OR( LOWER(_xlpm.after)="headflow", LOWER(_xlpm.after)="reach" ), "", IF( _xlpm.isNum, _xlpm.lastToken & " \ " & _xlpm.after, "" ) ) ), "" )
B173: Transmission Link from Power Canal PGE water to U_12_13_NU1 | C173: SacWAM | D173: =IFERROR( _xlfn.XLOOKUP($H173,WEAP!$F:$F,WEAP!$A:$A), IF($I173="","",_xlfn.XLOOKUP($I173,WEAP!$G:$G,WEAP!$A:$A,"")) ) -> 15368 | E173: =IFERROR( _xlfn.XLOOKUP($H173,WEAP!$F:$F,WEAP!$B:$B), IF($I173="","",_xlfn.XLOOKUP($I173,WEAP!$G:$G,WEAP!$B:$B,"")) ) -> Transmission Link from Power Canal PGE Water to U_12_13_NU1 | F173: =IFERROR( _xlfn.XLOOKUP($H173,WEAP!$F:$F,WEAP!$C:$C), IF($I173="","",_xlfn.XLOOKUP($I173,WEAP!$G:$G,WEAP!$C:$C,"")) ) -> taf | G173: =IFERROR( _xlfn.XLOOKUP($H173,WEAP!$F:$F,WEAP!$E:$E), IF($I173="","",_xlfn.XLOOKUP($I173,WEAP!$G:$G,WEAP!$E:$E,"")) ) -> Transmission Link Flow | H173: =IFERROR( _xlfn.LET( _xlpm.txt,TRIM(B173), _xlpm.before,TRIM(_xlfn.TEXTBEFORE(_xlpm.txt,"\",-1)), _xlpm.after,_xlfn.TEXTAFTER(_xlpm.txt,"\"), _xlpm.lastToken,TRIM(_xlfn.TEXTAFTER(_xlpm.before," ",-1)), _xlpm.isReach,LOWER(TRIM(_xlpm.after))="reach", _xlpm.cleaned, IF( ISNUMBER(--_xlpm.lastToken), _xlfn.TEXTBEFORE(_xlpm.before," ",-1) & " \ " & _xlpm.after, _xlpm.txt ), IF(_xlpm.isReach,_xlpm.txt,TRIM(_xlpm.cleaned)) ), B173 ) -> Transmission Link from Power Canal PGE water to U_12_13_NU1 | I173: =IFERROR( _xlfn.LET( _xlpm.txt,B173, _xlpm.before,TRIM(_xlfn.TEXTBEFORE(_xlpm.txt,"\")), _xlpm.after,TRIM(_xlfn.TEXTAFTER(_xlpm.txt,"\")), _xlpm.lastToken,TRIM(_xlfn.TEXTAFTER(_xlpm.before," ",-1)), _xlpm.isNum,IFERROR(ISNUMBER(--_xlpm.lastToken),FALSE), IF( OR( LOWER(_xlpm.after)="headflow", LOWER(_xlpm.after)="reach" ), "", IF( _xlpm.isNum, _xlpm.lastToken & " \ " & _xlpm.after, "" ) ) ), "" )
A174: D_THRMA_WEC000 | B174: Western Canal 0 \ Headflow | C174: SacWAM | D174: =IFERROR( _xlfn.XLOOKUP($H174,WEAP!$F:$F,WEAP!$A:$A), IF($I174="","",_xlfn.XLOOKUP($I174,WEAP!$G:$G,WEAP!$A:$A,"")) ) -> 9835 | E174: =IFERROR( _xlfn.XLOOKUP($H174,WEAP!$F:$F,WEAP!$B:$B), IF($I174="","",_xlfn.XLOOKUP($I174,WEAP!$G:$G,WEAP!$B:$B,"")) ) -> Western Canal 0 \ Headflow | F174: =IFERROR( _xlfn.XLOOKUP($H174,WEAP!$F:$F,WEAP!$C:$C), IF($I174="","",_xlfn.XLOOKUP($I174,WEAP!$G:$G,WEAP!$C:$C,"")) ) -> taf | G174: =IFERROR( _xlfn.XLOOKUP($H174,WEAP!$F:$F,WEAP!$E:$E), IF($I174="","",_xlfn.XLOOKUP($I174,WEAP!$G:$G,WEAP!$E:$E,"")) ) -> Streamflow (below node or reach listed) | H174: =IFERROR( _xlfn.LET( _xlpm.txt,TRIM(B174), _xlpm.before,TRIM(_xlfn.TEXTBEFORE(_xlpm.txt,"\",-1)), _xlpm.after,_xlfn.TEXTAFTER(_xlpm.txt,"\"), _xlpm.lastToken,TRIM(_xlfn.TEXTAFTER(_xlpm.before," ",-1)), _xlpm.isReach,LOWER(TRIM(_xlpm.after))="reach", _xlpm.cleaned, IF( ISNUMBER(--_xlpm.lastToken), _xlfn.TEXTBEFORE(_xlpm.before," ",-1) & " \ " & _xlpm.after, _xlpm.txt ), IF(_xlpm.isReach,_xlpm.txt,TRIM(_xlpm.cleaned)) ), B174 ) -> Western Canal \ Headflow | I174: =IFERROR( _xlfn.LET( _xlpm.txt,B174, _xlpm.before,TRIM(_xlfn.TEXTBEFORE(_xlpm.txt,"\")), _xlpm.after,TRIM(_xlfn.TEXTAFTER(_xlpm.txt,"\")), _xlpm.lastToken,TRIM(_xlfn.TEXTAFTER(_xlpm.before," ",-1)), _xlpm.isNum,IFERROR(ISNUMBER(--_xlpm.lastToken),FALSE), IF( OR( LOWER(_xlpm.after)="headflow", LOWER(_xlpm.after)="reach" ), "", IF( _xlpm.isNum, _xlpm.lastToken & " \ " & _xlpm.after, "" ) ) ), "" )
A175: D_THRMA_RVC000 | B175: Richvale Canal 0 \ Headflow | C175: SacWAM | D175: =IFERROR( _xlfn.XLOOKUP($H175,WEAP!$F:$F,WEAP!$A:$A), IF($I175="","",_xlfn.XLOOKUP($I175,WEAP!$G:$G,WEAP!$A:$A,"")) ) -> 9846 | E175: =IFERROR( _xlfn.XLOOKUP($H175,WEAP!$F:$F,WEAP!$B:$B), IF($I175="","",_xlfn.XLOOKUP($I175,WEAP!$G:$G,WEAP!$B:$B,"")) ) -> Richvale Canal 0 \ Headflow | F175: =IFERROR( _xlfn.XLOOKUP($H175,WEAP!$F:$F,WEAP!$C:$C), IF($I175="","",_xlfn.XLOOKUP($I175,WEAP!$G:$G,WEAP!$C:$C,"")) ) -> taf | G175: =IFERROR( _xlfn.XLOOKUP($H175,WEAP!$F:$F,WEAP!$E:$E), IF($I175="","",_xlfn.XLOOKUP($I175,WEAP!$G:$G,WEAP!$E:$E,"")) ) -> Streamflow (below node or reach listed) | H175: =IFERROR( _xlfn.LET( _xlpm.txt,TRIM(B175), _xlpm.before,TRIM(_xlfn.TEXTBEFORE(_xlpm.txt,"\",-1)), _xlpm.after,_xlfn.TEXTAFTER(_xlpm.txt,"\"), _xlpm.lastToken,TRIM(_xlfn.TEXTAFTER(_xlpm.before," ",-1)), _xlpm.isReach,LOWER(TRIM(_xlpm.after))="reach", _xlpm.cleaned, IF( ISNUMBER(--_xlpm.lastToken), _xlfn.TEXTBEFORE(_xlpm.before," ",-1) & " \ " & _xlpm.after, _xlpm.txt ), IF(_xlpm.isReach,_xlpm.txt,TRIM(_xlpm.cleaned)) ), B175 ) -> Richvale Canal \ Headflow | I175: =IFERROR( _xlfn.LET( _xlpm.txt,B175, _xlpm.before,TRIM(_xlfn.TEXTBEFORE(_xlpm.txt,"\")), _xlpm.after,TRIM(_xlfn.TEXTAFTER(_xlpm.txt,"\")), _xlpm.lastToken,TRIM(_xlfn.TEXTAFTER(_xlpm.before," ",-1)), _xlpm.isNum,IFERROR(ISNUMBER(--_xlpm.lastToken),FALSE), IF( OR( LOWER(_xlpm.after)="headflow", LOWER(_xlpm.after)="reach" ), "", IF( _xlpm.isNum, _xlpm.lastToken & " \ " & _xlpm.after, "" ) ) ), "" )
A176: D_THRMA_JBC000 | B176: Joint Board Canal 0 \ Headflow | C176: SacWAM | D176: =IFERROR( _xlfn.XLOOKUP($H176,WEAP!$F:$F,WEAP!$A:$A), IF($I176="","",_xlfn.XLOOKUP($I176,WEAP!$G:$G,WEAP!$A:$A,"")) ) -> 8485 | E176: =IFERROR( _xlfn.XLOOKUP($H176,WEAP!$F:$F,WEAP!$B:$B), IF($I176="","",_xlfn.XLOOKUP($I176,WEAP!$G:$G,WEAP!$B:$B,"")) ) -> Joint Board Canal 0 \ Headflow | F176: =IFERROR( _xlfn.XLOOKUP($H176,WEAP!$F:$F,WEAP!$C:$C), IF($I176="","",_xlfn.XLOOKUP($I176,WEAP!$G:$G,WEAP!$C:$C,"")) ) -> taf | G176: =IFERROR( _xlfn.XLOOKUP($H176,WEAP!$F:$F,WEAP!$E:$E), IF($I176="","",_xlfn.XLOOKUP($I176,WEAP!$G:$G,WEAP!$E:$E,"")) ) -> Streamflow (below node or reach listed) | H176: =IFERROR( _xlfn.LET( _xlpm.txt,TRIM(B176), _xlpm.before,TRIM(_xlfn.TEXTBEFORE(_xlpm.txt,"\",-1)), _xlpm.after,_xlfn.TEXTAFTER(_xlpm.txt,"\"), _xlpm.lastToken,TRIM(_xlfn.TEXTAFTER(_xlpm.before," ",-1)), _xlpm.isReach,LOWER(TRIM(_xlpm.after))="reach", _xlpm.cleaned, IF( ISNUMBER(--_xlpm.lastToken), _xlfn.TEXTBEFORE(_xlpm.before," ",-1) & " \ " & _xlpm.after, _xlpm.txt ), IF(_xlpm.isReach,_xlpm.txt,TRIM(_xlpm.cleaned)) ), B176 ) -> Joint Board Canal \ Headflow | I176: =IFERROR( _xlfn.LET( _xlpm.txt,B176, _xlpm.before,TRIM(_xlfn.TEXTBEFORE(_xlpm.txt,"\")), _xlpm.after,TRIM(_xlfn.TEXTAFTER(_xlpm.txt,"\")), _xlpm.lastToken,TRIM(_xlfn.TEXTAFTER(_xlpm.before," ",-1)), _xlpm.isNum,IFERROR(ISNUMBER(--_xlpm.lastToken),FALSE), IF( OR( LOWER(_xlpm.after)="headflow", LOWER(_xlpm.after)="reach" ), "", IF( _xlpm.isNum, _xlpm.lastToken & " \ " & _xlpm.after, "" ) ) ), "" )
A177: Thermalito Afterbay Diversions | B177: Thermalito Afterbay Diversions | C177: SacWAM | D177: =IFERROR( _xlfn.XLOOKUP($H177,WEAP!$F:$F,WEAP!$A:$A), IF($I177="","",_xlfn.XLOOKUP($I177,WEAP!$G:$G,WEAP!$A:$A,"")) ) | E177: =IFERROR( _xlfn.XLOOKUP($H177,WEAP!$F:$F,WEAP!$B:$B), IF($I177="","",_xlfn.XLOOKUP($I177,WEAP!$G:$G,WEAP!$B:$B,"")) ) | F177: =IFERROR( _xlfn.XLOOKUP($H177,WEAP!$F:$F,WEAP!$C:$C), IF($I177="","",_xlfn.XLOOKUP($I177,WEAP!$G:$G,WEAP!$C:$C,"")) ) | G177: =IFERROR( _xlfn.XLOOKUP($H177,WEAP!$F:$F,WEAP!$E:$E), IF($I177="","",_xlfn.XLOOKUP($I177,WEAP!$G:$G,WEAP!$E:$E,"")) ) | H177: =IFERROR( _xlfn.LET( _xlpm.txt,TRIM(B177), _xlpm.before,TRIM(_xlfn.TEXTBEFORE(_xlpm.txt,"\",-1)), _xlpm.after,_xlfn.TEXTAFTER(_xlpm.txt,"\"), _xlpm.lastToken,TRIM(_xlfn.TEXTAFTER(_xlpm.before," ",-1)), _xlpm.isReach,LOWER(TRIM(_xlpm.after))="reach", _xlpm.cleaned, IF( ISNUMBER(--_xlpm.lastToken), _xlfn.TEXTBEFORE(_xlpm.before," ",-1) & " \ " & _xlpm.after, _xlpm.txt ), IF(_xlpm.isReach,_xlpm.txt,TRIM(_xlpm.cleaned)) ), B177 ) -> Thermalito Afterbay Diversions | I177: =IFERROR( _xlfn.LET( _xlpm.txt,B177, _xlpm.before,TRIM(_xlfn.TEXTBEFORE(_xlpm.txt,"\")), _xlpm.after,TRIM(_xlfn.TEXTAFTER(_xlpm.txt,"\")), _xlpm.lastToken,TRIM(_xlfn.TEXTAFTER(_xlpm.before," ",-1)), _xlpm.isNum,IFERROR(ISNUMBER(--_xlpm.lastToken),FALSE), IF( OR( LOWER(_xlpm.after)="headflow", LOWER(_xlpm.after)="reach" ), "", IF( _xlpm.isNum, _xlpm.lastToken & " \ " & _xlpm.after, "" ) ) ), "" )
A178: Joint Board Districts - Total Diversion | B178: Joint Board Districts - Total Diversion | C178: SacWAM | D178: =IFERROR( _xlfn.XLOOKUP($H178,WEAP!$F:$F,WEAP!$A:$A), IF($I178="","",_xlfn.XLOOKUP($I178,WEAP!$G:$G,WEAP!$A:$A,"")) ) | E178: =IFERROR( _xlfn.XLOOKUP($H178,WEAP!$F:$F,WEAP!$B:$B), IF($I178="","",_xlfn.XLOOKUP($I178,WEAP!$G:$G,WEAP!$B:$B,"")) ) | F178: =IFERROR( _xlfn.XLOOKUP($H178,WEAP!$F:$F,WEAP!$C:$C), IF($I178="","",_xlfn.XLOOKUP($I178,WEAP!$G:$G,WEAP!$C:$C,"")) ) | G178: =IFERROR( _xlfn.XLOOKUP($H178,WEAP!$F:$F,WEAP!$E:$E), IF($I178="","",_xlfn.XLOOKUP($I178,WEAP!$G:$G,WEAP!$E:$E,"")) ) | H178: =IFERROR( _xlfn.LET( _xlpm.txt,TRIM(B178), _xlpm.before,TRIM(_xlfn.TEXTBEFORE(_xlpm.txt,"\",-1)), _xlpm.after,_xlfn.TEXTAFTER(_xlpm.txt,"\"), _xlpm.lastToken,TRIM(_xlfn.TEXTAFTER(_xlpm.before," ",-1)), _xlpm.isReach,LOWER(TRIM(_xlpm.after))="reach", _xlpm.cleaned, IF( ISNUMBER(--_xlpm.lastToken), _xlfn.TEXTBEFORE(_xlpm.before," ",-1) & " \ " & _xlpm.after, _xlpm.txt ), IF(_xlpm.isReach,_xlpm.txt,TRIM(_xlpm.cleaned)) ), B178 ) -> Joint Board Districts - Total Diversion | I178: =IFERROR( _xlfn.LET( _xlpm.txt,B178, _xlpm.before,TRIM(_xlfn.TEXTBEFORE(_xlpm.txt,"\")), _xlpm.after,TRIM(_xlfn.TEXTAFTER(_xlpm.txt,"\")), _xlpm.lastToken,TRIM(_xlfn.TEXTAFTER(_xlpm.before," ",-1)), _xlpm.isNum,IFERROR(ISNUMBER(--_xlpm.lastToken),FALSE), IF( OR( LOWER(_xlpm.after)="headflow", LOWER(_xlpm.after)="reach" ), "", IF( _xlpm.isNum, _xlpm.lastToken & " \ " & _xlpm.after, "" ) ) ), "" )
A179: D_FTR059_12_SA | B179: Transmission Link from Feather River RM 059 to A_12_13_SA | C179: SacWAM | D179: =IFERROR( _xlfn.XLOOKUP($H179,WEAP!$F:$F,WEAP!$A:$A), IF($I179="","",_xlfn.XLOOKUP($I179,WEAP!$G:$G,WEAP!$A:$A,"")) ) -> 7545 | E179: =IFERROR( _xlfn.XLOOKUP($H179,WEAP!$F:$F,WEAP!$B:$B), IF($I179="","",_xlfn.XLOOKUP($I179,WEAP!$G:$G,WEAP!$B:$B,"")) ) -> Transmission Link from Feather River RM 059 to A_12_13_SA | F179: =IFERROR( _xlfn.XLOOKUP($H179,WEAP!$F:$F,WEAP!$C:$C), IF($I179="","",_xlfn.XLOOKUP($I179,WEAP!$G:$G,WEAP!$C:$C,"")) ) -> taf | G179: =IFERROR( _xlfn.XLOOKUP($H179,WEAP!$F:$F,WEAP!$E:$E), IF($I179="","",_xlfn.XLOOKUP($I179,WEAP!$G:$G,WEAP!$E:$E,"")) ) -> Transmission Link Flow | H179: =IFERROR( _xlfn.LET( _xlpm.txt,TRIM(B179), _xlpm.before,TRIM(_xlfn.TEXTBEFORE(_xlpm.txt,"\",-1)), _xlpm.after,_xlfn.TEXTAFTER(_xlpm.txt,"\"), _xlpm.lastToken,TRIM(_xlfn.TEXTAFTER(_xlpm.before," ",-1)), _xlpm.isReach,LOWER(TRIM(_xlpm.after))="reach", _xlpm.cleaned, IF( ISNUMBER(--_xlpm.lastToken), _xlfn.TEXTBEFORE(_xlpm.before," ",-1) & " \ " & _xlpm.after, _xlpm.txt ), IF(_xlpm.isReach,_xlpm.txt,TRIM(_xlpm.cleaned)) ), B179 ) -> Transmission Link from Feather River RM 059 to A_12_13_SA | I179: =IFERROR( _xlfn.LET( _xlpm.txt,B179, _xlpm.before,TRIM(_xlfn.TEXTBEFORE(_xlpm.txt,"\")), _xlpm.after,TRIM(_xlfn.TEXTAFTER(_xlpm.txt,"\")), _xlpm.lastToken,TRIM(_xlfn.TEXTAFTER(_xlpm.before," ",-1)), _xlpm.isNum,IFERROR(ISNUMBER(--_xlpm.lastToken),FALSE), IF( OR( LOWER(_xlpm.after)="headflow", LOWER(_xlpm.after)="reach" ), "", IF( _xlpm.isNum, _xlpm.lastToken & " \ " & _xlpm.after, "" ) ) ), "" )
A180: D_FTR045_15N_SA | B180: Transmission Link from Feather River RM 045 to A_14_15N_SA | C180: SacWAM | D180: =IFERROR( _xlfn.XLOOKUP($H180,WEAP!$F:$F,WEAP!$A:$A), IF($I180="","",_xlfn.XLOOKUP($I180,WEAP!$G:$G,WEAP!$A:$A,"")) ) -> 11498 | E180: =IFERROR( _xlfn.XLOOKUP($H180,WEAP!$F:$F,WEAP!$B:$B), IF($I180="","",_xlfn.XLOOKUP($I180,WEAP!$G:$G,WEAP!$B:$B,"")) ) -> Transmission Link from Feather River RM 045 to A_14_15N_SA | F180: =IFERROR( _xlfn.XLOOKUP($H180,WEAP!$F:$F,WEAP!$C:$C), IF($I180="","",_xlfn.XLOOKUP($I180,WEAP!$G:$G,WEAP!$C:$C,"")) ) -> taf | G180: =IFERROR( _xlfn.XLOOKUP($H180,WEAP!$F:$F,WEAP!$E:$E), IF($I180="","",_xlfn.XLOOKUP($I180,WEAP!$G:$G,WEAP!$E:$E,"")) ) -> Transmission Link Flow | H180: =IFERROR( _xlfn.LET( _xlpm.txt,TRIM(B180), _xlpm.before,TRIM(_xlfn.TEXTBEFORE(_xlpm.txt,"\",-1)), _xlpm.after,_xlfn.TEXTAFTER(_xlpm.txt,"\"), _xlpm.lastToken,TRIM(_xlfn.TEXTAFTER(_xlpm.before," ",-1)), _xlpm.isReach,LOWER(TRIM(_xlpm.after))="reach", _xlpm.cleaned, IF( ISNUMBER(--_xlpm.lastToken), _xlfn.TEXTBEFORE(_xlpm.before," ",-1) & " \ " & _xlpm.after, _xlpm.txt ), IF(_xlpm.isReach,_xlpm.txt,TRIM(_xlpm.cleaned)) ), B180 ) -> Transmission Link from Feather River RM 045 to A_14_15N_SA | I180: =IFERROR( _xlfn.LET( _xlpm.txt,B180, _xlpm.before,TRIM(_xlfn.TEXTBEFORE(_xlpm.txt,"\")), _xlpm.after,TRIM(_xlfn.TEXTAFTER(_xlpm.txt,"\")), _xlpm.lastToken,TRIM(_xlfn.TEXTAFTER(_xlpm.before," ",-1)), _xlpm.isNum,IFERROR(ISNUMBER(--_xlpm.lastToken),FALSE), IF( OR( LOWER(_xlpm.after)="headflow", LOWER(_xlpm.after)="reach" ), "", IF( _xlpm.isNum, _xlpm.lastToken & " \ " & _xlpm.after, "" ) ) ), "" )
A181: D_FTR039_SEC009 | B181: Transmission Link from Feather River RM 039 to A_11_SA4 | C181: SacWAM | D181: =IFERROR( _xlfn.XLOOKUP($H181,WEAP!$F:$F,WEAP!$A:$A), IF($I181="","",_xlfn.XLOOKUP($I181,WEAP!$G:$G,WEAP!$A:$A,"")) ) -> 4448 | E181: =IFERROR( _xlfn.XLOOKUP($H181,WEAP!$F:$F,WEAP!$B:$B), IF($I181="","",_xlfn.XLOOKUP($I181,WEAP!$G:$G,WEAP!$B:$B,"")) ) -> Transmission Link from Feather River RM 039 to A_11_SA4 | F181: =IFERROR( _xlfn.XLOOKUP($H181,WEAP!$F:$F,WEAP!$C:$C), IF($I181="","",_xlfn.XLOOKUP($I181,WEAP!$G:$G,WEAP!$C:$C,"")) ) -> taf | G181: =IFERROR( _xlfn.XLOOKUP($H181,WEAP!$F:$F,WEAP!$E:$E), IF($I181="","",_xlfn.XLOOKUP($I181,WEAP!$G:$G,WEAP!$E:$E,"")) ) -> Transmission Link Flow | H181: =IFERROR( _xlfn.LET( _xlpm.txt,TRIM(B181), _xlpm.before,TRIM(_xlfn.TEXTBEFORE(_xlpm.txt,"\",-1)), _xlpm.after,_xlfn.TEXTAFTER(_xlpm.txt,"\"), _xlpm.lastToken,TRIM(_xlfn.TEXTAFTER(_xlpm.before," ",-1)), _xlpm.isReach,LOWER(TRIM(_xlpm.after))="reach", _xlpm.cleaned, IF( ISNUMBER(--_xlpm.lastToken), _xlfn.TEXTBEFORE(_xlpm.before," ",-1) & " \ " & _xlpm.after, _xlpm.txt ), IF(_xlpm.isReach,_xlpm.txt,TRIM(_xlpm.cleaned)) ), B181 ) -> Transmission Link from Feather River RM 039 to A_11_SA4 | I181: =IFERROR( _xlfn.LET( _xlpm.txt,B181, _xlpm.before,TRIM(_xlfn.TEXTBEFORE(_xlpm.txt,"\")), _xlpm.after,TRIM(_xlfn.TEXTAFTER(_xlpm.txt,"\")), _xlpm.lastToken,TRIM(_xlfn.TEXTAFTER(_xlpm.before," ",-1)), _xlpm.isNum,IFERROR(ISNUMBER(--_xlpm.lastToken),FALSE), IF( OR( LOWER(_xlpm.after)="headflow", LOWER(_xlpm.after)="reach" ), "", IF( _xlpm.isNum, _xlpm.lastToken & " \ " & _xlpm.after, "" ) ) ), "" )
A182: D_FTR031_WTPCYC | B182: Transmission Link from Feather River RM 031 to U_16_PU | C182: SacWAM | D182: =IFERROR( _xlfn.XLOOKUP($H182,WEAP!$F:$F,WEAP!$A:$A), IF($I182="","",_xlfn.XLOOKUP($I182,WEAP!$G:$G,WEAP!$A:$A,"")) ) -> 7595 | E182: =IFERROR( _xlfn.XLOOKUP($H182,WEAP!$F:$F,WEAP!$B:$B), IF($I182="","",_xlfn.XLOOKUP($I182,WEAP!$G:$G,WEAP!$B:$B,"")) ) -> Transmission Link from Feather River RM 031 to U_16_PU | F182: =IFERROR( _xlfn.XLOOKUP($H182,WEAP!$F:$F,WEAP!$C:$C), IF($I182="","",_xlfn.XLOOKUP($I182,WEAP!$G:$G,WEAP!$C:$C,"")) ) -> taf | G182: =IFERROR( _xlfn.XLOOKUP($H182,WEAP!$F:$F,WEAP!$E:$E), IF($I182="","",_xlfn.XLOOKUP($I182,WEAP!$G:$G,WEAP!$E:$E,"")) ) -> Transmission Link Flow | H182: =IFERROR( _xlfn.LET( _xlpm.txt,TRIM(B182), _xlpm.before,TRIM(_xlfn.TEXTBEFORE(_xlpm.txt,"\",-1)), _xlpm.after,_xlfn.TEXTAFTER(_xlpm.txt,"\"), _xlpm.lastToken,TRIM(_xlfn.TEXTAFTER(_xlpm.before," ",-1)), _xlpm.isReach,LOWER(TRIM(_xlpm.after))="reach", _xlpm.cleaned, IF( ISNUMBER(--_xlpm.lastToken), _xlfn.TEXTBEFORE(_xlpm.before," ",-1) & " \ " & _xlpm.after, _xlpm.txt ), IF(_xlpm.isReach,_xlpm.txt,TRIM(_xlpm.cleaned)) ), B182 ) -> Transmission Link from Feather River RM 031 to U_16_PU | I182: =IFERROR( _xlfn.LET( _xlpm.txt,B182, _xlpm.before,TRIM(_xlfn.TEXTBEFORE(_xlpm.txt,"\")), _xlpm.after,TRIM(_xlfn.TEXTAFTER(_xlpm.txt,"\")), _xlpm.lastToken,TRIM(_xlfn.TEXTAFTER(_xlpm.before," ",-1)), _xlpm.isNum,IFERROR(ISNUMBER(--_xlpm.lastToken),FALSE), IF( OR( LOWER(_xlpm.after)="headflow", LOWER(_xlpm.after)="reach" ), "", IF( _xlpm.isNum, _xlpm.lastToken & " \ " & _xlpm.after, "" ) ) ), "" )
A183: D_FTR028_15S_SA | B183: Transmission Link from Feather River RM 028 to A_15S_SA | C183: SacWAM | D183: =IFERROR( _xlfn.XLOOKUP($H183,WEAP!$F:$F,WEAP!$A:$A), IF($I183="","",_xlfn.XLOOKUP($I183,WEAP!$G:$G,WEAP!$A:$A,"")) ) -> 7570 | E183: =IFERROR( _xlfn.XLOOKUP($H183,WEAP!$F:$F,WEAP!$B:$B), IF($I183="","",_xlfn.XLOOKUP($I183,WEAP!$G:$G,WEAP!$B:$B,"")) ) -> Transmission Link from Feather River RM 028 to A_15S_SA | F183: =IFERROR( _xlfn.XLOOKUP($H183,WEAP!$F:$F,WEAP!$C:$C), IF($I183="","",_xlfn.XLOOKUP($I183,WEAP!$G:$G,WEAP!$C:$C,"")) ) -> taf | G183: =IFERROR( _xlfn.XLOOKUP($H183,WEAP!$F:$F,WEAP!$E:$E), IF($I183="","",_xlfn.XLOOKUP($I183,WEAP!$G:$G,WEAP!$E:$E,"")) ) -> Transmission Link Flow | H183: =IFERROR( _xlfn.LET( _xlpm.txt,TRIM(B183), _xlpm.before,TRIM(_xlfn.TEXTBEFORE(_xlpm.txt,"\",-1)), _xlpm.after,_xlfn.TEXTAFTER(_xlpm.txt,"\"), _xlpm.lastToken,TRIM(_xlfn.TEXTAFTER(_xlpm.before," ",-1)), _xlpm.isReach,LOWER(TRIM(_xlpm.after))="reach", _xlpm.cleaned, IF( ISNUMBER(--_xlpm.lastToken), _xlfn.TEXTBEFORE(_xlpm.before," ",-1) & " \ " & _xlpm.after, _xlpm.txt ), IF(_xlpm.isReach,_xlpm.txt,TRIM(_xlpm.cleaned)) ), B183 ) -> Transmission Link from Feather River RM 028 to A_15S_SA | I183: =IFERROR( _xlfn.LET( _xlpm.txt,B183, _xlpm.before,TRIM(_xlfn.TEXTBEFORE(_xlpm.txt,"\")), _xlpm.after,TRIM(_xlfn.TEXTAFTER(_xlpm.txt,"\")), _xlpm.lastToken,TRIM(_xlfn.TEXTAFTER(_xlpm.before," ",-1)), _xlpm.isNum,IFERROR(ISNUMBER(--_xlpm.lastToken),FALSE), IF( OR( LOWER(_xlpm.after)="headflow", LOWER(_xlpm.after)="reach" ), "", IF( _xlpm.isNum, _xlpm.lastToken & " \ " & _xlpm.after, "" ) ) ), "" )
A184: D_FTR021_16_PA | B184: Transmission Link from Feather River RM 021 to A_16_PA | C184: SacWAM | D184: =IFERROR( _xlfn.XLOOKUP($H184,WEAP!$F:$F,WEAP!$A:$A), IF($I184="","",_xlfn.XLOOKUP($I184,WEAP!$G:$G,WEAP!$A:$A,"")) ) -> 4527 | E184: =IFERROR( _xlfn.XLOOKUP($H184,WEAP!$F:$F,WEAP!$B:$B), IF($I184="","",_xlfn.XLOOKUP($I184,WEAP!$G:$G,WEAP!$B:$B,"")) ) -> Transmission Link from Feather River RM 021 to A_16_PA | F184: =IFERROR( _xlfn.XLOOKUP($H184,WEAP!$F:$F,WEAP!$C:$C), IF($I184="","",_xlfn.XLOOKUP($I184,WEAP!$G:$G,WEAP!$C:$C,"")) ) -> taf | G184: =IFERROR( _xlfn.XLOOKUP($H184,WEAP!$F:$F,WEAP!$E:$E), IF($I184="","",_xlfn.XLOOKUP($I184,WEAP!$G:$G,WEAP!$E:$E,"")) ) -> Transmission Link Flow | H184: =IFERROR( _xlfn.LET( _xlpm.txt,TRIM(B184), _xlpm.before,TRIM(_xlfn.TEXTBEFORE(_xlpm.txt,"\",-1)), _xlpm.after,_xlfn.TEXTAFTER(_xlpm.txt,"\"), _xlpm.lastToken,TRIM(_xlfn.TEXTAFTER(_xlpm.before," ",-1)), _xlpm.isReach,LOWER(TRIM(_xlpm.after))="reach", _xlpm.cleaned, IF( ISNUMBER(--_xlpm.lastToken), _xlfn.TEXTBEFORE(_xlpm.before," ",-1) & " \ " & _xlpm.after, _xlpm.txt ), IF(_xlpm.isReach,_xlpm.txt,TRIM(_xlpm.cleaned)) ), B184 ) -> Transmission Link from Feather River RM 021 to A_16_PA | I184: =IFERROR( _xlfn.LET( _xlpm.txt,B184, _xlpm.before,TRIM(_xlfn.TEXTBEFORE(_xlpm.txt,"\")), _xlpm.after,TRIM(_xlfn.TEXTAFTER(_xlpm.txt,"\")), _xlpm.lastToken,TRIM(_xlfn.TEXTAFTER(_xlpm.before," ",-1)), _xlpm.isNum,IFERROR(ISNUMBER(--_xlpm.lastToken),FALSE), IF( OR( LOWER(_xlpm.after)="headflow", LOWER(_xlpm.after)="reach" ), "", IF( _xlpm.isNum, _xlpm.lastToken & " \ " & _xlpm.after, "" ) ) ), "" )
A185: D_FTR021_16_SA | B185: Transmission Link from Feather River RM 021 to A_16_SA | C185: SacWAM | D185: =IFERROR( _xlfn.XLOOKUP($H185,WEAP!$F:$F,WEAP!$A:$A), IF($I185="","",_xlfn.XLOOKUP($I185,WEAP!$G:$G,WEAP!$A:$A,"")) ) -> 11506 | E185: =IFERROR( _xlfn.XLOOKUP($H185,WEAP!$F:$F,WEAP!$B:$B), IF($I185="","",_xlfn.XLOOKUP($I185,WEAP!$G:$G,WEAP!$B:$B,"")) ) -> Transmission Link from Feather River RM 021 to A_16_SA | F185: =IFERROR( _xlfn.XLOOKUP($H185,WEAP!$F:$F,WEAP!$C:$C), IF($I185="","",_xlfn.XLOOKUP($I185,WEAP!$G:$G,WEAP!$C:$C,"")) ) -> taf | G185: =IFERROR( _xlfn.XLOOKUP($H185,WEAP!$F:$F,WEAP!$E:$E), IF($I185="","",_xlfn.XLOOKUP($I185,WEAP!$G:$G,WEAP!$E:$E,"")) ) -> Transmission Link Flow | H185: =IFERROR( _xlfn.LET( _xlpm.txt,TRIM(B185), _xlpm.before,TRIM(_xlfn.TEXTBEFORE(_xlpm.txt,"\",-1)), _xlpm.after,_xlfn.TEXTAFTER(_xlpm.txt,"\"), _xlpm.lastToken,TRIM(_xlfn.TEXTAFTER(_xlpm.before," ",-1)), _xlpm.isReach,LOWER(TRIM(_xlpm.after))="reach", _xlpm.cleaned, IF( ISNUMBER(--_xlpm.lastToken), _xlfn.TEXTBEFORE(_xlpm.before," ",-1) & " \ " & _xlpm.after, _xlpm.txt ), IF(_xlpm.isReach,_xlpm.txt,TRIM(_xlpm.cleaned)) ), B185 ) -> Transmission Link from Feather River RM 021 to A_16_SA | I185: =IFERROR( _xlfn.LET( _xlpm.txt,B185, _xlpm.before,TRIM(_xlfn.TEXTBEFORE(_xlpm.txt,"\")), _xlpm.after,TRIM(_xlfn.TEXTAFTER(_xlpm.txt,"\")), _xlpm.lastToken,TRIM(_xlfn.TEXTAFTER(_xlpm.before," ",-1)), _xlpm.isNum,IFERROR(ISNUMBER(--_xlpm.lastToken),FALSE), IF( OR( LOWER(_xlpm.after)="headflow", LOWER(_xlpm.after)="reach" ), "", IF( _xlpm.isNum, _xlpm.lastToken & " \ " & _xlpm.after, "" ) ) ), "" )
... A254: D_SAC_ACID | B254: Anderson-Cottonwood ID | C254: SacWAM | D254: =IFERROR( _xlfn.XLOOKUP($H254,WEAP!$F:$F,WEAP!$A:$A), IF($I254="","",_xlfn.XLOOKUP($I254,WEAP!$G:$G,WEAP!$A:$A,"")) ) | E254: =IFERROR( _xlfn.XLOOKUP($H254,WEAP!$F:$F,WEAP!$B:$B), IF($I254="","",_xlfn.XLOOKUP($I254,WEAP!$G:$G,WEAP!$B:$B,"")) ) | F254: =IFERROR( _xlfn.XLOOKUP($H254,WEAP!$F:$F,WEAP!$C:$C), IF($I254="","",_xlfn.XLOOKUP($I254,WEAP!$G:$G,WEAP!$C:$C,"")) ) | G254: =IFERROR( _xlfn.XLOOKUP($H254,WEAP!$F:$F,WEAP!$E:$E), IF($I254="","",_xlfn.XLOOKUP($I254,WEAP!$G:$G,WEAP!$E:$E,"")) ) | H254: =IFERROR( _xlfn.LET( _xlpm.txt,TRIM(B254), _xlpm.before,TRIM(_xlfn.TEXTBEFORE(_xlpm.txt,"\",-1)), _xlpm.after,_xlfn.TEXTAFTER(_xlpm.txt,"\"), _xlpm.lastToken,TRIM(_xlfn.TEXTAFTER(_xlpm.before," ",-1)), _xlpm.isReach,LOWER(TRIM(_xlpm.after))="reach", _xlpm.cleaned, IF( ISNUMBER(--_xlpm.lastToken), _xlfn.TEXTBEFORE(_xlpm.before," ",-1) & " \ " & _xlpm.after, _xlpm.txt ), IF(_xlpm.isReach,_xlpm.txt,TRIM(_xlpm.cleaned)) ), B254 ) -> Anderson-Cottonwood ID | I254: =IFERROR( _xlfn.LET( _xlpm.txt,B254, _xlpm.before,TRIM(_xlfn.TEXTBEFORE(_xlpm.txt,"\")), _xlpm.after,TRIM(_xlfn.TEXTAFTER(_xlpm.txt,"\")), _xlpm.lastToken,TRIM(_xlfn.TEXTAFTER(_xlpm.before," ",-1)), _xlpm.isNum,IFERROR(ISNUMBER(--_xlpm.lastToken),FALSE), IF( OR( LOWER(_xlpm.after)="headflow", LOWER(_xlpm.after)="reach" ), "", IF( _xlpm.isNum, _xlpm.lastToken & " \ " & _xlpm.after, "" ) ) ), "" )
B255: Minor CVP Settlement Diversions Redding Basin | C255: SacWAM | D255: =IFERROR( _xlfn.XLOOKUP($H255,WEAP!$F:$F,WEAP!$A:$A), IF($I255="","",_xlfn.XLOOKUP($I255,WEAP!$G:$G,WEAP!$A:$A,"")) ) | E255: =IFERROR( _xlfn.XLOOKUP($H255,WEAP!$F:$F,WEAP!$B:$B), IF($I255="","",_xlfn.XLOOKUP($I255,WEAP!$G:$G,WEAP!$B:$B,"")) ) | F255: =IFERROR( _xlfn.XLOOKUP($H255,WEAP!$F:$F,WEAP!$C:$C), IF($I255="","",_xlfn.XLOOKUP($I255,WEAP!$G:$G,WEAP!$C:$C,"")) ) | G255: =IFERROR( _xlfn.XLOOKUP($H255,WEAP!$F:$F,WEAP!$E:$E), IF($I255="","",_xlfn.XLOOKUP($I255,WEAP!$G:$G,WEAP!$E:$E,"")) ) | H255: =IFERROR( _xlfn.LET( _xlpm.txt,TRIM(B255), _xlpm.before,TRIM(_xlfn.TEXTBEFORE(_xlpm.txt,"\",-1)), _xlpm.after,_xlfn.TEXTAFTER(_xlpm.txt,"\"), _xlpm.lastToken,TRIM(_xlfn.TEXTAFTER(_xlpm.before," ",-1)), _xlpm.isReach,LOWER(TRIM(_xlpm.after))="reach", _xlpm.cleaned, IF( ISNUMBER(--_xlpm.lastToken), _xlfn.TEXTBEFORE(_xlpm.before," ",-1) & " \ " & _xlpm.after, _xlpm.txt ), IF(_xlpm.isReach,_xlpm.txt,TRIM(_xlpm.cleaned)) ), B255 ) -> Minor CVP Settlement Diversions Redding Basin | I255: =IFERROR( _xlfn.LET( _xlpm.txt,B255, _xlpm.before,TRIM(_xlfn.TEXTBEFORE(_xlpm.txt,"\")), _xlpm.after,TRIM(_xlfn.TEXTAFTER(_xlpm.txt,"\")), _xlpm.lastToken,TRIM(_xlfn.TEXTAFTER(_xlpm.before," ",-1)), _xlpm.isNum,IFERROR(ISNUMBER(--_xlpm.lastToken),FALSE), IF( OR( LOWER(_xlpm.after)="headflow", LOWER(_xlpm.after)="reach" ), "", IF( _xlpm.isNum, _xlpm.lastToken & " \ " & _xlpm.after, "" ) ) ), "" )
A256: D_SAC_BVWD | B256: Bella Vista WD | C256: SacWAM | D256: =IFERROR( _xlfn.XLOOKUP($H256,WEAP!$F:$F,WEAP!$A:$A), IF($I256="","",_xlfn.XLOOKUP($I256,WEAP!$G:$G,WEAP!$A:$A,"")) ) | E256: =IFERROR( _xlfn.XLOOKUP($H256,WEAP!$F:$F,WEAP!$B:$B), IF($I256="","",_xlfn.XLOOKUP($I256,WEAP!$G:$G,WEAP!$B:$B,"")) ) | F256: =IFERROR( _xlfn.XLOOKUP($H256,WEAP!$F:$F,WEAP!$C:$C), IF($I256="","",_xlfn.XLOOKUP($I256,WEAP!$G:$G,WEAP!$C:$C,"")) ) | G256: =IFERROR( _xlfn.XLOOKUP($H256,WEAP!$F:$F,WEAP!$E:$E), IF($I256="","",_xlfn.XLOOKUP($I256,WEAP!$G:$G,WEAP!$E:$E,"")) ) | H256: =IFERROR( _xlfn.LET( _xlpm.txt,TRIM(B256), _xlpm.before,TRIM(_xlfn.TEXTBEFORE(_xlpm.txt,"\",-1)), _xlpm.after,_xlfn.TEXTAFTER(_xlpm.txt,"\"), _xlpm.lastToken,TRIM(_xlfn.TEXTAFTER(_xlpm.before," ",-1)), _xlpm.isReach,LOWER(TRIM(_xlpm.after))="reach", _xlpm.cleaned, IF( ISNUMBER(--_xlpm.lastToken), _xlfn.TEXTBEFORE(_xlpm.before," ",-1) & " \ " & _xlpm.after, _xlpm.txt ), IF(_xlpm.isReach,_xlpm.txt,TRIM(_xlpm.cleaned)) ), B256 ) -> Bella Vista WD | I256: =IFERROR( _xlfn.LET( _xlpm.txt,B256, _xlpm.before,TRIM(_xlfn.TEXTBEFORE(_xlpm.txt,"\")), _xlpm.after,TRIM(_xlfn.TEXTAFTER(_xlpm.txt,"\")), _xlpm.lastToken,TRIM(_xlfn.TEXTAFTER(_xlpm.before," ",-1)), _xlpm.isNum,IFERROR(ISNUMBER(--_xlpm.lastToken),FALSE), IF( OR( LOWER(_xlpm.after)="headflow", LOWER(_xlpm.after)="reach" ), "", IF( _xlpm.isNum, _xlpm.lastToken & " \ " & _xlpm.after, "" ) ) ), "" )
A257: D_SAC240_TCC001 | B257: Tehama Colusa Canal 0 \ Headflow | C257: SacWAM | D257: =IFERROR( _xlfn.XLOOKUP($H257,WEAP!$F:$F,WEAP!$A:$A), IF($I257="","",_xlfn.XLOOKUP($I257,WEAP!$G:$G,WEAP!$A:$A,"")) ) -> 1188 | E257: =IFERROR( _xlfn.XLOOKUP($H257,WEAP!$F:$F,WEAP!$B:$B), IF($I257="","",_xlfn.XLOOKUP($I257,WEAP!$G:$G,WEAP!$B:$B,"")) ) -> Tehama Colusa Canal 0 \ Headflow | F257: =IFERROR( _xlfn.XLOOKUP($H257,WEAP!$F:$F,WEAP!$C:$C), IF($I257="","",_xlfn.XLOOKUP($I257,WEAP!$G:$G,WEAP!$C:$C,"")) ) -> taf | G257: =IFERROR( _xlfn.XLOOKUP($H257,WEAP!$F:$F,WEAP!$E:$E), IF($I257="","",_xlfn.XLOOKUP($I257,WEAP!$G:$G,WEAP!$E:$E,"")) ) -> Streamflow (below node or reach listed) | H257: =IFERROR( _xlfn.LET( _xlpm.txt,TRIM(B257), _xlpm.before,TRIM(_xlfn.TEXTBEFORE(_xlpm.txt,"\",-1)), _xlpm.after,_xlfn.TEXTAFTER(_xlpm.txt,"\"), _xlpm.lastToken,TRIM(_xlfn.TEXTAFTER(_xlpm.before," ",-1)), _xlpm.isReach,LOWER(TRIM(_xlpm.after))="reach", _xlpm.cleaned, IF( ISNUMBER(--_xlpm.lastToken), _xlfn.TEXTBEFORE(_xlpm.before," ",-1) & " \ " & _xlpm.after, _xlpm.txt ), IF(_xlpm.isReach,_xlpm.txt,TRIM(_xlpm.cleaned)) ), B257 ) -> Tehama Colusa Canal \ Headflow | I257: =IFERROR( _xlfn.LET( _xlpm.txt,B257, _xlpm.before,TRIM(_xlfn.TEXTBEFORE(_xlpm.txt,"\")), _xlpm.after,TRIM(_xlfn.TEXTAFTER(_xlpm.txt,"\")), _xlpm.lastToken,TRIM(_xlfn.TEXTAFTER(_xlpm.before," ",-1)), _xlpm.isNum,IFERROR(ISNUMBER(--_xlpm.lastToken),FALSE), IF( OR( LOWER(_xlpm.after)="headflow", LOWER(_xlpm.after)="reach" ), "", IF( _xlpm.isNum, _xlpm.lastToken & " \ " & _xlpm.after, "" ) ) ), "" )
B258: Minor CVP Settlement Diversions North Sacramento Valley | C258: SacWAM | D258: =IFERROR( _xlfn.XLOOKUP($H258,WEAP!$F:$F,WEAP!$A:$A), IF($I258="","",_xlfn.XLOOKUP($I258,WEAP!$G:$G,WEAP!$A:$A,"")) ) | E258: =IFERROR( _xlfn.XLOOKUP($H258,WEAP!$F:$F,WEAP!$B:$B), IF($I258="","",_xlfn.XLOOKUP($I258,WEAP!$G:$G,WEAP!$B:$B,"")) ) | F258: =IFERROR( _xlfn.XLOOKUP($H258,WEAP!$F:$F,WEAP!$C:$C), IF($I258="","",_xlfn.XLOOKUP($I258,WEAP!$G:$G,WEAP!$C:$C,"")) ) | G258: =IFERROR( _xlfn.XLOOKUP($H258,WEAP!$F:$F,WEAP!$E:$E), IF($I258="","",_xlfn.XLOOKUP($I258,WEAP!$G:$G,WEAP!$E:$E,"")) ) | H258: =IFERROR( _xlfn.LET( _xlpm.txt,TRIM(B258), _xlpm.before,TRIM(_xlfn.TEXTBEFORE(_xlpm.txt,"\",-1)), _xlpm.after,_xlfn.TEXTAFTER(_xlpm.txt,"\"), _xlpm.lastToken,TRIM(_xlfn.TEXTAFTER(_xlpm.before," ",-1)), _xlpm.isReach,LOWER(TRIM(_xlpm.after))="reach", _xlpm.cleaned, IF( ISNUMBER(--_xlpm.lastToken), _xlfn.TEXTBEFORE(_xlpm.before," ",-1) & " \ " & _xlpm.after, _xlpm.txt ), IF(_xlpm.isReach,_xlpm.txt,TRIM(_xlpm.cleaned)) ), B258 ) -> Minor CVP Settlement Diversions North Sacramento Valley | I258: =IFERROR( _xlfn.LET( _xlpm.txt,B258, _xlpm.before,TRIM(_xlfn.TEXTBEFORE(_xlpm.txt,"\")), _xlpm.after,TRIM(_xlfn.TEXTAFTER(_xlpm.txt,"\")), _xlpm.lastToken,TRIM(_xlfn.TEXTAFTER(_xlpm.before," ",-1)), _xlpm.isNum,IFERROR(ISNUMBER(--_xlpm.lastToken),FALSE), IF( OR( LOWER(_xlpm.after)="headflow", LOWER(_xlpm.after)="reach" ), "", IF( _xlpm.isNum, _xlpm.lastToken & " \ " & _xlpm.after, "" ) ) ), "" )
A259: D_SAC207_GCC007 | B259: Glenn Colusa Canal 0 \ Headflow | C259: SacWAM | D259: =IFERROR( _xlfn.XLOOKUP($H259,WEAP!$F:$F,WEAP!$A:$A), IF($I259="","",_xlfn.XLOOKUP($I259,WEAP!$G:$G,WEAP!$A:$A,"")) ) -> 1192 | E259: =IFERROR( _xlfn.XLOOKUP($H259,WEAP!$F:$F,WEAP!$B:$B), IF($I259="","",_xlfn.XLOOKUP($I259,WEAP!$G:$G,WEAP!$B:$B,"")) ) -> Glenn Colusa Canal 0 \ Headflow | F259: =IFERROR( _xlfn.XLOOKUP($H259,WEAP!$F:$F,WEAP!$C:$C), IF($I259="","",_xlfn.XLOOKUP($I259,WEAP!$G:$G,WEAP!$C:$C,"")) ) -> taf | G259: =IFERROR( _xlfn.XLOOKUP($H259,WEAP!$F:$F,WEAP!$E:$E), IF($I259="","",_xlfn.XLOOKUP($I259,WEAP!$G:$G,WEAP!$E:$E,"")) ) -> Streamflow (below node or reach listed) | H259: =IFERROR( _xlfn.LET( _xlpm.txt,TRIM(B259), _xlpm.before,TRIM(_xlfn.TEXTBEFORE(_xlpm.txt,"\",-1)), _xlpm.after,_xlfn.TEXTAFTER(_xlpm.txt,"\"), _xlpm.lastToken,TRIM(_xlfn.TEXTAFTER(_xlpm.before," ",-1)), _xlpm.isReach,LOWER(TRIM(_xlpm.after))="reach", _xlpm.cleaned, IF( ISNUMBER(--_xlpm.lastToken), _xlfn.TEXTBEFORE(_xlpm.before," ",-1) & " \ " & _xlpm.after, _xlpm.txt ), IF(_xlpm.isReach,_xlpm.txt,TRIM(_xlpm.cleaned)) ), B259 ) -> Glenn Colusa Canal \ Headflow | I259: =IFERROR( _xlfn.LET( _xlpm.txt,B259, _xlpm.before,TRIM(_xlfn.TEXTBEFORE(_xlpm.txt,"\")), _xlpm.after,TRIM(_xlfn.TEXTAFTER(_xlpm.txt,"\")), _xlpm.lastToken,TRIM(_xlfn.TEXTAFTER(_xlpm.before," ",-1)), _xlpm.isNum,IFERROR(ISNUMBER(--_xlpm.lastToken),FALSE), IF( OR( LOWER(_xlpm.after)="headflow", LOWER(_xlpm.after)="reach" ), "", IF( _xlpm.isNum, _xlpm.lastToken & " \ " & _xlpm.after, "" ) ) ), "" )
A260: D_MTC000_09_SA1 | B260: Transmission Link from Sacramento River RM 196 to A_09_SA1 | C260: SacWAM | D260: =IFERROR( _xlfn.XLOOKUP($H260,WEAP!$F:$F,WEAP!$A:$A), IF($I260="","",_xlfn.XLOOKUP($I260,WEAP!$G:$G,WEAP!$A:$A,"")) ) -> 5038 | E260: =IFERROR( _xlfn.XLOOKUP($H260,WEAP!$F:$F,WEAP!$B:$B), IF($I260="","",_xlfn.XLOOKUP($I260,WEAP!$G:$G,WEAP!$B:$B,"")) ) -> Transmission Link from Sacramento River RM 196 to A_09_SA1 | F260: =IFERROR( _xlfn.XLOOKUP($H260,WEAP!$F:$F,WEAP!$C:$C), IF($I260="","",_xlfn.XLOOKUP($I260,WEAP!$G:$G,WEAP!$C:$C,"")) ) -> taf | G260: =IFERROR( _xlfn.XLOOKUP($H260,WEAP!$F:$F,WEAP!$E:$E), IF($I260="","",_xlfn.XLOOKUP($I260,WEAP!$G:$G,WEAP!$E:$E,"")) ) -> Transmission Link Flow | H260: =IFERROR( _xlfn.LET( _xlpm.txt,TRIM(B260), _xlpm.before,TRIM(_xlfn.TEXTBEFORE(_xlpm.txt,"\",-1)), _xlpm.after,_xlfn.TEXTAFTER(_xlpm.txt,"\"), _xlpm.lastToken,TRIM(_xlfn.TEXTAFTER(_xlpm.before," ",-1)), _xlpm.isReach,LOWER(TRIM(_xlpm.after))="reach", _xlpm.cleaned, IF( ISNUMBER(--_xlpm.lastToken), _xlfn.TEXTBEFORE(_xlpm.before," ",-1) & " \ " & _xlpm.after, _xlpm.txt ), IF(_xlpm.isReach,_xlpm.txt,TRIM(_xlpm.cleaned)) ), B260 ) -> Transmission Link from Sacramento River RM 196 to A_09_SA1 | I260: =IFERROR( _xlfn.LET( _xlpm.txt,B260, _xlpm.before,TRIM(_xlfn.TEXTBEFORE(_xlpm.txt,"\")), _xlpm.after,TRIM(_xlfn.TEXTAFTER(_xlpm.txt,"\")), _xlpm.lastToken,TRIM(_xlfn.TEXTAFTER(_xlpm.before," ",-1)), _xlpm.isNum,IFERROR(ISNUMBER(--_xlpm.lastToken),FALSE), IF( OR( LOWER(_xlpm.after)="headflow", LOWER(_xlpm.after)="reach" ), "", IF( _xlpm.isNum, _xlpm.lastToken & " \ " & _xlpm.after, "" ) ) ), "" )
B261: Llano Seco Ranch inc Refuges | C261: SacWAM | D261: =IFERROR( _xlfn.XLOOKUP($H261,WEAP!$F:$F,WEAP!$A:$A), IF($I261="","",_xlfn.XLOOKUP($I261,WEAP!$G:$G,WEAP!$A:$A,"")) ) | E261: =IFERROR( _xlfn.XLOOKUP($H261,WEAP!$F:$F,WEAP!$B:$B), IF($I261="","",_xlfn.XLOOKUP($I261,WEAP!$G:$G,WEAP!$B:$B,"")) ) | F261: =IFERROR( _xlfn.XLOOKUP($H261,WEAP!$F:$F,WEAP!$C:$C), IF($I261="","",_xlfn.XLOOKUP($I261,WEAP!$G:$G,WEAP!$C:$C,"")) ) | G261: =IFERROR( _xlfn.XLOOKUP($H261,WEAP!$F:$F,WEAP!$E:$E), IF($I261="","",_xlfn.XLOOKUP($I261,WEAP!$G:$G,WEAP!$E:$E,"")) ) | H261: =IFERROR( _xlfn.LET( _xlpm.txt,TRIM(B261), _xlpm.before,TRIM(_xlfn.TEXTBEFORE(_xlpm.txt,"\",-1)), _xlpm.after,_xlfn.TEXTAFTER(_xlpm.txt,"\"), _xlpm.lastToken,TRIM(_xlfn.TEXTAFTER(_xlpm.before," ",-1)), _xlpm.isReach,LOWER(TRIM(_xlpm.after))="reach", _xlpm.cleaned, IF( ISNUMBER(--_xlpm.lastToken), _xlfn.TEXTBEFORE(_xlpm.before," ",-1) & " \ " & _xlpm.after, _xlpm.txt ), IF(_xlpm.isReach,_xlpm.txt,TRIM(_xlpm.cleaned)) ), B261 ) -> Llano Seco Ranch inc Refuges | I261: =IFERROR( _xlfn.LET( _xlpm.txt,B261, _xlpm.before,TRIM(_xlfn.TEXTBEFORE(_xlpm.txt,"\")), _xlpm.after,TRIM(_xlfn.TEXTAFTER(_xlpm.txt,"\")), _xlpm.lastToken,TRIM(_xlfn.TEXTAFTER(_xlpm.before," ",-1)), _xlpm.isNum,IFERROR(ISNUMBER(--_xlpm.lastToken),FALSE), IF( OR( LOWER(_xlpm.after)="headflow", LOWER(_xlpm.after)="reach" ), "", IF( _xlpm.isNum, _xlpm.lastToken & " \ " & _xlpm.after, "" ) ) ), "" )
A262: D_SAC_RD1004 | B262: Reclamation District 1004 | C262: SacWAM | D262: =IFERROR( _xlfn.XLOOKUP($H262,WEAP!$F:$F,WEAP!$A:$A), IF($I262="","",_xlfn.XLOOKUP($I262,WEAP!$G:$G,WEAP!$A:$A,"")) ) | E262: =IFERROR( _xlfn.XLOOKUP($H262,WEAP!$F:$F,WEAP!$B:$B), IF($I262="","",_xlfn.XLOOKUP($I262,WEAP!$G:$G,WEAP!$B:$B,"")) ) | F262: =IFERROR( _xlfn.XLOOKUP($H262,WEAP!$F:$F,WEAP!$C:$C), IF($I262="","",_xlfn.XLOOKUP($I262,WEAP!$G:$G,WEAP!$C:$C,"")) ) | G262: =IFERROR( _xlfn.XLOOKUP($H262,WEAP!$F:$F,WEAP!$E:$E), IF($I262="","",_xlfn.XLOOKUP($I262,WEAP!$G:$G,WEAP!$E:$E,"")) ) | H262: =IFERROR( _xlfn.LET( _xlpm.txt,TRIM(B262), _xlpm.before,TRIM(_xlfn.TEXTBEFORE(_xlpm.txt,"\",-1)), _xlpm.after,_xlfn.TEXTAFTER(_xlpm.txt,"\"), _xlpm.lastToken,TRIM(_xlfn.TEXTAFTER(_xlpm.before," ",-1)), _xlpm.isReach,LOWER(TRIM(_xlpm.after))="reach", _xlpm.cleaned, IF( ISNUMBER(--_xlpm.lastToken), _xlfn.TEXTBEFORE(_xlpm.before," ",-1) & " \ " & _xlpm.after, _xlpm.txt ), IF(_xlpm.isReach,_xlpm.txt,TRIM(_xlpm.cleaned)) ), B262 ) -> Reclamation District 1004 | I262: =IFERROR( _xlfn.LET( _xlpm.txt,B262, _xlpm.before,TRIM(_xlfn.TEXTBEFORE(_xlpm.txt,"\")), _xlpm.after,TRIM(_xlfn.TEXTAFTER(_xlpm.txt,"\")), _xlpm.lastToken,TRIM(_xlfn.TEXTAFTER(_xlpm.before," ",-1)), _xlpm.isNum,IFERROR(ISNUMBER(--_xlpm.lastToken),FALSE), IF( OR( LOWER(_xlpm.after)="headflow", LOWER(_xlpm.after)="reach" ), "", IF( _xlpm.isNum, _xlpm.lastToken & " \ " & _xlpm.after, "" ) ) ), "" )
B263: Minor CVP Settlement Diversions to Butte Basin | C263: SacWAM | D263: =IFERROR( _xlfn.XLOOKUP($H263,WEAP!$F:$F,WEAP!$A:$A), IF($I263="","",_xlfn.XLOOKUP($I263,WEAP!$G:$G,WEAP!$A:$A,"")) ) | E263: =IFERROR( _xlfn.XLOOKUP($H263,WEAP!$F:$F,WEAP!$B:$B), IF($I263="","",_xlfn.XLOOKUP($I263,WEAP!$G:$G,WEAP!$B:$B,"")) ) | F263: =IFERROR( _xlfn.XLOOKUP($H263,WEAP!$F:$F,WEAP!$C:$C), IF($I263="","",_xlfn.XLOOKUP($I263,WEAP!$G:$G,WEAP!$C:$C,"")) ) | G263: =IFERROR( _xlfn.XLOOKUP($H263,WEAP!$F:$F,WEAP!$E:$E), IF($I263="","",_xlfn.XLOOKUP($I263,WEAP!$G:$G,WEAP!$E:$E,"")) ) | H263: =IFERROR( _xlfn.LET( _xlpm.txt,TRIM(B263), _xlpm.before,TRIM(_xlfn.TEXTBEFORE(_xlpm.txt,"\",-1)), _xlpm.after,_xlfn.TEXTAFTER(_xlpm.txt,"\"), _xlpm.lastToken,TRIM(_xlfn.TEXTAFTER(_xlpm.before," ",-1)), _xlpm.isReach,LOWER(TRIM(_xlpm.after))="reach", _xlpm.cleaned, IF( ISNUMBER(--_xlpm.lastToken), _xlfn.TEXTBEFORE(_xlpm.before," ",-1) & " \ " & _xlpm.after, _xlpm.txt ), IF(_xlpm.isReach,_xlpm.txt,TRIM(_xlpm.cleaned)) ), B263 ) -> Minor CVP Settlement Diversions to Butte Basin | I263: =IFERROR( _xlfn.LET( _xlpm.txt,B263, _xlpm.before,TRIM(_xlfn.TEXTBEFORE(_xlpm.txt,"\")), _xlpm.after,TRIM(_xlfn.TEXTAFTER(_xlpm.txt,"\")), _xlpm.lastToken,TRIM(_xlfn.TEXTAFTER(_xlpm.before," ",-1)), _xlpm.isNum,IFERROR(ISNUMBER(--_xlpm.lastToken),FALSE), IF( OR( LOWER(_xlpm.after)="headflow", LOWER(_xlpm.after)="reach" ), "", IF( _xlpm.isNum, _xlpm.lastToken & " \ " & _xlpm.after, "" ) ) ), "" )
A264: D_SAC_PCGID | B264: Princeton-Cordora-Glenn ID | C264: SacWAM | D264: =IFERROR( _xlfn.XLOOKUP($H264,WEAP!$F:$F,WEAP!$A:$A), IF($I264="","",_xlfn.XLOOKUP($I264,WEAP!$G:$G,WEAP!$A:$A,"")) ) | E264: =IFERROR( _xlfn.XLOOKUP($H264,WEAP!$F:$F,WEAP!$B:$B), IF($I264="","",_xlfn.XLOOKUP($I264,WEAP!$G:$G,WEAP!$B:$B,"")) ) | F264: =IFERROR( _xlfn.XLOOKUP($H264,WEAP!$F:$F,WEAP!$C:$C), IF($I264="","",_xlfn.XLOOKUP($I264,WEAP!$G:$G,WEAP!$C:$C,"")) ) | G264: =IFERROR( _xlfn.XLOOKUP($H264,WEAP!$F:$F,WEAP!$E:$E), IF($I264="","",_xlfn.XLOOKUP($I264,WEAP!$G:$G,WEAP!$E:$E,"")) ) | H264: =IFERROR( _xlfn.LET( _xlpm.txt,TRIM(B264), _xlpm.before,TRIM(_xlfn.TEXTBEFORE(_xlpm.txt,"\",-1)), _xlpm.after,_xlfn.TEXTAFTER(_xlpm.txt,"\"), _xlpm.lastToken,TRIM(_xlfn.TEXTAFTER(_xlpm.before," ",-1)), _xlpm.isReach,LOWER(TRIM(_xlpm.after))="reach", _xlpm.cleaned, IF( ISNUMBER(--_xlpm.lastToken), _xlfn.TEXTBEFORE(_xlpm.before," ",-1) & " \ " & _xlpm.after, _xlpm.txt ), IF(_xlpm.isReach,_xlpm.txt,TRIM(_xlpm.cleaned)) ), B264 ) -> Princeton-Cordora-Glenn ID | I264: =IFERROR( _xlfn.LET( _xlpm.txt,B264, _xlpm.before,TRIM(_xlfn.TEXTBEFORE(_xlpm.txt,"\")), _xlpm.after,TRIM(_xlfn.TEXTAFTER(_xlpm.txt,"\")), _xlpm.lastToken,TRIM(_xlfn.TEXTAFTER(_xlpm.before," ",-1)), _xlpm.isNum,IFERROR(ISNUMBER(--_xlpm.lastToken),FALSE), IF( OR( LOWER(_xlpm.after)="headflow", LOWER(_xlpm.after)="reach" ), "", IF( _xlpm.isNum, _xlpm.lastToken & " \ " & _xlpm.after, "" ) ) ), "" )
A265: D_SAC_PID | B265: Provident ID | C265: SacWAM | D265: =IFERROR( _xlfn.XLOOKUP($H265,WEAP!$F:$F,WEAP!$A:$A), IF($I265="","",_xlfn.XLOOKUP($I265,WEAP!$G:$G,WEAP!$A:$A,"")) ) | E265: =IFERROR( _xlfn.XLOOKUP($H265,WEAP!$F:$F,WEAP!$B:$B), IF($I265="","",_xlfn.XLOOKUP($I265,WEAP!$G:$G,WEAP!$B:$B,"")) ) | F265: =IFERROR( _xlfn.XLOOKUP($H265,WEAP!$F:$F,WEAP!$C:$C), IF($I265="","",_xlfn.XLOOKUP($I265,WEAP!$G:$G,WEAP!$C:$C,"")) ) | G265: =IFERROR( _xlfn.XLOOKUP($H265,WEAP!$F:$F,WEAP!$E:$E), IF($I265="","",_xlfn.XLOOKUP($I265,WEAP!$G:$G,WEAP!$E:$E,"")) ) | H265: =IFERROR( _xlfn.LET( _xlpm.txt,TRIM(B265), _xlpm.before,TRIM(_xlfn.TEXTBEFORE(_xlpm.txt,"\",-1)), _xlpm.after,_xlfn.TEXTAFTER(_xlpm.txt,"\"), _xlpm.lastToken,TRIM(_xlfn.TEXTAFTER(_xlpm.before," ",-1)), _xlpm.isReach,LOWER(TRIM(_xlpm.after))="reach", _xlpm.cleaned, IF( ISNUMBER(--_xlpm.lastToken), _xlfn.TEXTBEFORE(_xlpm.before," ",-1) & " \ " & _xlpm.after, _xlpm.txt ), IF(_xlpm.isReach,_xlpm.txt,TRIM(_xlpm.cleaned)) ), B265 ) -> Provident ID | I265: =IFERROR( _xlfn.LET( _xlpm.txt,B265, _xlpm.before,TRIM(_xlfn.TEXTBEFORE(_xlpm.txt,"\")), _xlpm.after,TRIM(_xlfn.TEXTAFTER(_xlpm.txt,"\")), _xlpm.lastToken,TRIM(_xlfn.TEXTAFTER(_xlpm.before," ",-1)), _xlpm.isNum,IFERROR(ISNUMBER(--_xlpm.lastToken),FALSE), IF( OR( LOWER(_xlpm.after)="headflow", LOWER(_xlpm.after)="reach" ), "", IF( _xlpm.isNum, _xlpm.lastToken & " \ " & _xlpm.after, "" ) ) ), "" )
A266: D_SAC_MID | B266: Maxwell ID | C266: SacWAM | D266: =IFERROR( _xlfn.XLOOKUP($H266,WEAP!$F:$F,WEAP!$A:$A), IF($I266="","",_xlfn.XLOOKUP($I266,WEAP!$G:$G,WEAP!$A:$A,"")) ) | E266: =IFERROR( _xlfn.XLOOKUP($H266,WEAP!$F:$F,WEAP!$B:$B), IF($I266="","",_xlfn.XLOOKUP($I266,WEAP!$G:$G,WEAP!$B:$B,"")) ) | F266: =IFERROR( _xlfn.XLOOKUP($H266,WEAP!$F:$F,WEAP!$C:$C), IF($I266="","",_xlfn.XLOOKUP($I266,WEAP!$G:$G,WEAP!$C:$C,"")) ) | G266: =IFERROR( _xlfn.XLOOKUP($H266,WEAP!$F:$F,WEAP!$E:$E), IF($I266="","",_xlfn.XLOOKUP($I266,WEAP!$G:$G,WEAP!$E:$E,"")) ) | H266: =IFERROR( _xlfn.LET( _xlpm.txt,TRIM(B266), _xlpm.before,TRIM(_xlfn.TEXTBEFORE(_xlpm.txt,"\",-1)), _xlpm.after,_xlfn.TEXTAFTER(_xlpm.txt,"\"), _xlpm.lastToken,TRIM(_xlfn.TEXTAFTER(_xlpm.before," ",-1)), _xlpm.isReach,LOWER(TRIM(_xlpm.after))="reach", _xlpm.cleaned, IF( ISNUMBER(--_xlpm.lastToken), _xlfn.TEXTBEFORE(_xlpm.before," ",-1) & " \ " & _xlpm.after, _xlpm.txt ), IF(_xlpm.isReach,_xlpm.txt,TRIM(_xlpm.cleaned)) ), B266 ) -> Maxwell ID | I266: =IFERROR( _xlfn.LET( _xlpm.txt,B266, _xlpm.before,TRIM(_xlfn.TEXTBEFORE(_xlpm.txt,"\")), _xlpm.after,TRIM(_xlfn.TEXTAFTER(_xlpm.txt,"\")), _xlpm.lastToken,TRIM(_xlfn.TEXTAFTER(_xlpm.before," ",-1)), _xlpm.isNum,IFERROR(ISNUMBER(--_xlpm.lastToken),FALSE), IF( OR( LOWER(_xlpm.after)="headflow", LOWER(_xlpm.after)="reach" ), "", IF( _xlpm.isNum, _xlpm.lastToken & " \ " & _xlpm.after, "" ) ) ), "" )
A267: D_SAC_SFT | B267: Sycamore Family Trust | C267: SacWAM | D267: =IFERROR( _xlfn.XLOOKUP($H267,WEAP!$F:$F,WEAP!$A:$A), IF($I267="","",_xlfn.XLOOKUP($I267,WEAP!$G:$G,WEAP!$A:$A,"")) ) | E267: =IFERROR( _xlfn.XLOOKUP($H267,WEAP!$F:$F,WEAP!$B:$B), IF($I267="","",_xlfn.XLOOKUP($I267,WEAP!$G:$G,WEAP!$B:$B,"")) ) | F267: =IFERROR( _xlfn.XLOOKUP($H267,WEAP!$F:$F,WEAP!$C:$C), IF($I267="","",_xlfn.XLOOKUP($I267,WEAP!$G:$G,WEAP!$C:$C,"")) ) | G267: =IFERROR( _xlfn.XLOOKUP($H267,WEAP!$F:$F,WEAP!$E:$E), IF($I267="","",_xlfn.XLOOKUP($I267,WEAP!$G:$G,WEAP!$E:$E,"")) ) | H267: =IFERROR( _xlfn.LET( _xlpm.txt,TRIM(B267), _xlpm.before,TRIM(_xlfn.TEXTBEFORE(_xlpm.txt,"\",-1)), _xlpm.after,_xlfn.TEXTAFTER(_xlpm.txt,"\"), _xlpm.lastToken,TRIM(_xlfn.TEXTAFTER(_xlpm.before," ",-1)), _xlpm.isReach,LOWER(TRIM(_xlpm.after))="reach", _xlpm.cleaned, IF( ISNUMBER(--_xlpm.lastToken), _xlfn.TEXTBEFORE(_xlpm.before," ",-1) & " \ " & _xlpm.after, _xlpm.txt ), IF(_xlpm.isReach,_xlpm.txt,TRIM(_xlpm.cleaned)) ), B267 ) -> Sycamore Family Trust | I267: =IFERROR( _xlfn.LET( _xlpm.txt,B267, _xlpm.before,TRIM(_xlfn.TEXTBEFORE(_xlpm.txt,"\")), _xlpm.after,TRIM(_xlfn.TEXTAFTER(_xlpm.txt,"\")), _xlpm.lastToken,TRIM(_xlfn.TEXTAFTER(_xlpm.before," ",-1)), _xlpm.isNum,IFERROR(ISNUMBER(--_xlpm.lastToken),FALSE), IF( OR( LOWER(_xlpm.after)="headflow", LOWER(_xlpm.after)="reach" ), "", IF( _xlpm.isNum, _xlpm.lastToken & " \ " & _xlpm.after, "" ) ) ), "" )
A268: D_SAC_RD108 | B268: Reclamation District 108 | C268: SacWAM | D268: =IFERROR( _xlfn.XLOOKUP($H268,WEAP!$F:$F,WEAP!$A:$A), IF($I268="","",_xlfn.XLOOKUP($I268,WEAP!$G:$G,WEAP!$A:$A,"")) ) | E268: =IFERROR( _xlfn.XLOOKUP($H268,WEAP!$F:$F,WEAP!$B:$B), IF($I268="","",_xlfn.XLOOKUP($I268,WEAP!$G:$G,WEAP!$B:$B,"")) ) | F268: =IFERROR( _xlfn.XLOOKUP($H268,WEAP!$F:$F,WEAP!$C:$C), IF($I268="","",_xlfn.XLOOKUP($I268,WEAP!$G:$G,WEAP!$C:$C,"")) ) | G268: =IFERROR( _xlfn.XLOOKUP($H268,WEAP!$F:$F,WEAP!$E:$E), IF($I268="","",_xlfn.XLOOKUP($I268,WEAP!$G:$G,WEAP!$E:$E,"")) ) | H268: =IFERROR( _xlfn.LET( _xlpm.txt,TRIM(B268), _xlpm.before,TRIM(_xlfn.TEXTBEFORE(_xlpm.txt,"\",-1)), _xlpm.after,_xlfn.TEXTAFTER(_xlpm.txt,"\"), _xlpm.lastToken,TRIM(_xlfn.TEXTAFTER(_xlpm.before," ",-1)), _xlpm.isReach,LOWER(TRIM(_xlpm.after))="reach", _xlpm.cleaned, IF( ISNUMBER(--_xlpm.lastToken), _xlfn.TEXTBEFORE(_xlpm.before," ",-1) & " \ " & _xlpm.after, _xlpm.txt ), IF(_xlpm.isReach,_xlpm.txt,TRIM(_xlpm.cleaned)) ), B268 ) -> Reclamation District 108 | I268: =IFERROR( _xlfn.LET( _xlpm.txt,B268, _xlpm.before,TRIM(_xlfn.TEXTBEFORE(_xlpm.txt,"\")), _xlpm.after,TRIM(_xlfn.TEXTAFTER(_xlpm.txt,"\")), _xlpm.lastToken,TRIM(_xlfn.TEXTAFTER(_xlpm.before," ",-1)), _xlpm.isNum,IFERROR(ISNUMBER(--_xlpm.lastToken),FALSE), IF( OR( LOWER(_xlpm.after)="headflow", LOWER(_xlpm.after)="reach" ), "", IF( _xlpm.isNum, _xlpm.lastToken & " \ " & _xlpm.after, "" ) ) ), "" )
A269: D_SAC_RGF | B269: River Garden Farms | C269: SacWAM | D269: =IFERROR( _xlfn.XLOOKUP($H269,WEAP!$F:$F,WEAP!$A:$A), IF($I269="","",_xlfn.XLOOKUP($I269,WEAP!$G:$G,WEAP!$A:$A,"")) ) | E269: =IFERROR( _xlfn.XLOOKUP($H269,WEAP!$F:$F,WEAP!$B:$B), IF($I269="","",_xlfn.XLOOKUP($I269,WEAP!$G:$G,WEAP!$B:$B,"")) ) | F269: =IFERROR( _xlfn.XLOOKUP($H269,WEAP!$F:$F,WEAP!$C:$C), IF($I269="","",_xlfn.XLOOKUP($I269,WEAP!$G:$G,WEAP!$C:$C,"")) ) | G269: =IFERROR( _xlfn.XLOOKUP($H269,WEAP!$F:$F,WEAP!$E:$E), IF($I269="","",_xlfn.XLOOKUP($I269,WEAP!$G:$G,WEAP!$E:$E,"")) ) | H269: =IFERROR( _xlfn.LET( _xlpm.txt,TRIM(B269), _xlpm.before,TRIM(_xlfn.TEXTBEFORE(_xlpm.txt,"\",-1)), _xlpm.after,_xlfn.TEXTAFTER(_xlpm.txt,"\"), _xlpm.lastToken,TRIM(_xlfn.TEXTAFTER(_xlpm.before," ",-1)), _xlpm.isReach,LOWER(TRIM(_xlpm.after))="reach", _xlpm.cleaned, IF( ISNUMBER(--_xlpm.lastToken), _xlfn.TEXTBEFORE(_xlpm.before," ",-1) & " \ " & _xlpm.after, _xlpm.txt ), IF(_xlpm.isReach,_xlpm.txt,TRIM(_xlpm.cleaned)) ), B269 ) -> River Garden Farms | I269: =IFERROR( _xlfn.LET( _xlpm.txt,B269, _xlpm.before,TRIM(_xlfn.TEXTBEFORE(_xlpm.txt,"\")), _xlpm.after,TRIM(_xlfn.TEXTAFTER(_xlpm.txt,"\")), _xlpm.lastToken,TRIM(_xlfn.TEXTAFTER(_xlpm.before," ",-1)), _xlpm.isNum,IFERROR(ISNUMBER(--_xlpm.lastToken),FALSE), IF( OR( LOWER(_xlpm.after)="headflow", LOWER(_xlpm.after)="reach" ), "", IF( _xlpm.isNum, _xlpm.lastToken & " \ " & _xlpm.after, "" ) ) ), "" )
B270: Minor CVP Settlement Diversions to Colusa Basin | C270: SacWAM | D270: =IFERROR( _xlfn.XLOOKUP($H270,WEAP!$F:$F,WEAP!$A:$A), IF($I270="","",_xlfn.XLOOKUP($I270,WEAP!$G:$G,WEAP!$A:$A,"")) ) | E270: =IFERROR( _xlfn.XLOOKUP($H270,WEAP!$F:$F,WEAP!$B:$B), IF($I270="","",_xlfn.XLOOKUP($I270,WEAP!$G:$G,WEAP!$B:$B,"")) ) | F270: =IFERROR( _xlfn.XLOOKUP($H270,WEAP!$F:$F,WEAP!$C:$C), IF($I270="","",_xlfn.XLOOKUP($I270,WEAP!$G:$G,WEAP!$C:$C,"")) ) | G270: =IFERROR( _xlfn.XLOOKUP($H270,WEAP!$F:$F,WEAP!$E:$E), IF($I270="","",_xlfn.XLOOKUP($I270,WEAP!$G:$G,WEAP!$E:$E,"")) ) | H270: =IFERROR( _xlfn.LET( _xlpm.txt,TRIM(B270), _xlpm.before,TRIM(_xlfn.TEXTBEFORE(_xlpm.txt,"\",-1)), _xlpm.after,_xlfn.TEXTAFTER(_xlpm.txt,"\"), _xlpm.lastToken,TRIM(_xlfn.TEXTAFTER(_xlpm.before," ",-1)), _xlpm.isReach,LOWER(TRIM(_xlpm.after))="reach", _xlpm.cleaned, IF( ISNUMBER(--_xlpm.lastToken), _xlfn.TEXTBEFORE(_xlpm.before," ",-1) & " \ " & _xlpm.after, _xlpm.txt ), IF(_xlpm.isReach,_xlpm.txt,TRIM(_xlpm.cleaned)) ), B270 ) -> Minor CVP Settlement Diversions to Colusa Basin | I270: =IFERROR( _xlfn.LET( _xlpm.txt,B270, _xlpm.before,TRIM(_xlfn.TEXTBEFORE(_xlpm.txt,"\")), _xlpm.after,TRIM(_xlfn.TEXTAFTER(_xlpm.txt,"\")), _xlpm.lastToken,TRIM(_xlfn.TEXTAFTER(_xlpm.before," ",-1)), _xlpm.isNum,IFERROR(ISNUMBER(--_xlpm.lastToken),FALSE), IF( OR( LOWER(_xlpm.after)="headflow", LOWER(_xlpm.after)="reach" ), "", IF( _xlpm.isNum, _xlpm.lastToken & " \ " & _xlpm.after, "" ) ) ), "" )
A271: D_SAC_MFWC | B271: Meridian Farms WC | C271: SacWAM | D271: =IFERROR( _xlfn.XLOOKUP($H271,WEAP!$F:$F,WEAP!$A:$A), IF($I271="","",_xlfn.XLOOKUP($I271,WEAP!$G:$G,WEAP!$A:$A,"")) ) | E271: =IFERROR( _xlfn.XLOOKUP($H271,WEAP!$F:$F,WEAP!$B:$B), IF($I271="","",_xlfn.XLOOKUP($I271,WEAP!$G:$G,WEAP!$B:$B,"")) ) | F271: =IFERROR( _xlfn.XLOOKUP($H271,WEAP!$F:$F,WEAP!$C:$C), IF($I271="","",_xlfn.XLOOKUP($I271,WEAP!$G:$G,WEAP!$C:$C,"")) ) | G271: =IFERROR( _xlfn.XLOOKUP($H271,WEAP!$F:$F,WEAP!$E:$E), IF($I271="","",_xlfn.XLOOKUP($I271,WEAP!$G:$G,WEAP!$E:$E,"")) ) | H271: =IFERROR( _xlfn.LET( _xlpm.txt,TRIM(B271), _xlpm.before,TRIM(_xlfn.TEXTBEFORE(_xlpm.txt,"\",-1)), _xlpm.after,_xlfn.TEXTAFTER(_xlpm.txt,"\"), _xlpm.lastToken,TRIM(_xlfn.TEXTAFTER(_xlpm.before," ",-1)), _xlpm.isReach,LOWER(TRIM(_xlpm.after))="reach", _xlpm.cleaned, IF( ISNUMBER(--_xlpm.lastToken), _xlfn.TEXTBEFORE(_xlpm.before," ",-1) & " \ " & _xlpm.after, _xlpm.txt ), IF(_xlpm.isReach,_xlpm.txt,TRIM(_xlpm.cleaned)) ), B271 ) -> Meridian Farms WC | I271: =IFERROR( _xlfn.LET( _xlpm.txt,B271, _xlpm.before,TRIM(_xlfn.TEXTBEFORE(_xlpm.txt,"\")), _xlpm.after,TRIM(_xlfn.TEXTAFTER(_xlpm.txt,"\")), _xlpm.lastToken,TRIM(_xlfn.TEXTAFTER(_xlpm.before," ",-1)), _xlpm.isNum,IFERROR(ISNUMBER(--_xlpm.lastToken),FALSE), IF( OR( LOWER(_xlpm.after)="headflow", LOWER(_xlpm.after)="reach" ), "", IF( _xlpm.isNum, _xlpm.lastToken & " \ " & _xlpm.after, "" ) ) ), "" )
A272: D_SAC_SMWC | B272: Sutter Mutual WC | C272: SacWAM | D272: =IFERROR( _xlfn.XLOOKUP($H272,WEAP!$F:$F,WEAP!$A:$A), IF($I272="","",_xlfn.XLOOKUP($I272,WEAP!$G:$G,WEAP!$A:$A,"")) ) | E272: =IFERROR( _xlfn.XLOOKUP($H272,WEAP!$F:$F,WEAP!$B:$B), IF($I272="","",_xlfn.XLOOKUP($I272,WEAP!$G:$G,WEAP!$B:$B,"")) ) | F272: =IFERROR( _xlfn.XLOOKUP($H272,WEAP!$F:$F,WEAP!$C:$C), IF($I272="","",_xlfn.XLOOKUP($I272,WEAP!$G:$G,WEAP!$C:$C,"")) ) | G272: =IFERROR( _xlfn.XLOOKUP($H272,WEAP!$F:$F,WEAP!$E:$E), IF($I272="","",_xlfn.XLOOKUP($I272,WEAP!$G:$G,WEAP!$E:$E,"")) ) | H272: =IFERROR( _xlfn.LET( _xlpm.txt,TRIM(B272), _xlpm.before,TRIM(_xlfn.TEXTBEFORE(_xlpm.txt,"\",-1)), _xlpm.after,_xlfn.TEXTAFTER(_xlpm.txt,"\"), _xlpm.lastToken,TRIM(_xlfn.TEXTAFTER(_xlpm.before," ",-1)), _xlpm.isReach,LOWER(TRIM(_xlpm.after))="reach", _xlpm.cleaned, IF( ISNUMBER(--_xlpm.lastToken), _xlfn.TEXTBEFORE(_xlpm.before," ",-1) & " \ " & _xlpm.after, _xlpm.txt ), IF(_xlpm.isReach,_xlpm.txt,TRIM(_xlpm.cleaned)) ), B272 ) -> Sutter Mutual WC | I272: =IFERROR( _xlfn.LET( _xlpm.txt,B272, _xlpm.before,TRIM(_xlfn.TEXTBEFORE(_xlpm.txt,"\")), _xlpm.after,TRIM(_xlfn.TEXTAFTER(_xlpm.txt,"\")), _xlpm.lastToken,TRIM(_xlfn.TEXTAFTER(_xlpm.before," ",-1)), _xlpm.isNum,IFERROR(ISNUMBER(--_xlpm.lastToken),FALSE), IF( OR( LOWER(_xlpm.after)="headflow", LOWER(_xlpm.after)="reach" ), "", IF( _xlpm.isNum, _xlpm.lastToken & " \ " & _xlpm.after, "" ) ) ), "" )
B273: Minor CVP Settlement Diversions to Sutter Basin | C273: SacWAM | D273: =IFERROR( _xlfn.XLOOKUP($H273,WEAP!$F:$F,WEAP!$A:$A), IF($I273="","",_xlfn.XLOOKUP($I273,WEAP!$G:$G,WEAP!$A:$A,"")) ) | E273: =IFERROR( _xlfn.XLOOKUP($H273,WEAP!$F:$F,WEAP!$B:$B), IF($I273="","",_xlfn.XLOOKUP($I273,WEAP!$G:$G,WEAP!$B:$B,"")) ) | F273: =IFERROR( _xlfn.XLOOKUP($H273,WEAP!$F:$F,WEAP!$C:$C), IF($I273="","",_xlfn.XLOOKUP($I273,WEAP!$G:$G,WEAP!$C:$C,"")) ) | G273: =IFERROR( _xlfn.XLOOKUP($H273,WEAP!$F:$F,WEAP!$E:$E), IF($I273="","",_xlfn.XLOOKUP($I273,WEAP!$G:$G,WEAP!$E:$E,"")) ) | H273: =IFERROR( _xlfn.LET( _xlpm.txt,TRIM(B273), _xlpm.before,TRIM(_xlfn.TEXTBEFORE(_xlpm.txt,"\",-1)), _xlpm.after,_xlfn.TEXTAFTER(_xlpm.txt,"\"), _xlpm.lastToken,TRIM(_xlfn.TEXTAFTER(_xlpm.before," ",-1)), _xlpm.isReach,LOWER(TRIM(_xlpm.after))="reach", _xlpm.cleaned, IF( ISNUMBER(--_xlpm.lastToken), _xlfn.TEXTBEFORE(_xlpm.before," ",-1) & " \ " & _xlpm.after, _xlpm.txt ), IF(_xlpm.isReach,_xlpm.txt,TRIM(_xlpm.cleaned)) ), B273 ) -> Minor CVP Settlement Diversions to Sutter Basin | I273: =IFERROR( _xlfn.LET( _xlpm.txt,B273, _xlpm.before,TRIM(_xlfn.TEXTBEFORE(_xlpm.txt,"\")), _xlpm.after,TRIM(_xlfn.TEXTAFTER(_xlpm.txt,"\")), _xlpm.lastToken,TRIM(_xlfn.TEXTAFTER(_xlpm.before," ",-1)), _xlpm.isNum,IFERROR(ISNUMBER(--_xlpm.lastToken),FALSE), IF( OR( LOWER(_xlpm.after)="headflow", LOWER(_xlpm.after)="reach" ), "", IF( _xlpm.isNum, _xlpm.lastToken & " \ " & _xlpm.after, "" ) ) ), "" )
A274: D_SAC_CPG | B274: Conaway Ranch | C274: SacWAM | D274: =IFERROR( _xlfn.XLOOKUP($H274,WEAP!$F:$F,WEAP!$A:$A), IF($I274="","",_xlfn.XLOOKUP($I274,WEAP!$G:$G,WEAP!$A:$A,"")) ) | E274: =IFERROR( _xlfn.XLOOKUP($H274,WEAP!$F:$F,WEAP!$B:$B), IF($I274="","",_xlfn.XLOOKUP($I274,WEAP!$G:$G,WEAP!$B:$B,"")) ) | F274: =IFERROR( _xlfn.XLOOKUP($H274,WEAP!$F:$F,WEAP!$C:$C), IF($I274="","",_xlfn.XLOOKUP($I274,WEAP!$G:$G,WEAP!$C:$C,"")) ) | G274: =IFERROR( _xlfn.XLOOKUP($H274,WEAP!$F:$F,WEAP!$E:$E), IF($I274="","",_xlfn.XLOOKUP($I274,WEAP!$G:$G,WEAP!$E:$E,"")) ) | H274: =IFERROR( _xlfn.LET( _xlpm.txt,TRIM(B274), _xlpm.before,TRIM(_xlfn.TEXTBEFORE(_xlpm.txt,"\",-1)), _xlpm.after,_xlfn.TEXTAFTER(_xlpm.txt,"\"), _xlpm.lastToken,TRIM(_xlfn.TEXTAFTER(_xlpm.before," ",-1)), _xlpm.isReach,LOWER(TRIM(_xlpm.after))="reach", _xlpm.cleaned, IF( ISNUMBER(--_xlpm.lastToken), _xlfn.TEXTBEFORE(_xlpm.before," ",-1) & " \ " & _xlpm.after, _xlpm.txt ), IF(_xlpm.isReach,_xlpm.txt,TRIM(_xlpm.cleaned)) ), B274 ) -> Conaway Ranch | I274: =IFERROR( _xlfn.LET( _xlpm.txt,B274, _xlpm.before,TRIM(_xlfn.TEXTBEFORE(_xlpm.txt,"\")), _xlpm.after,TRIM(_xlfn.TEXTAFTER(_xlpm.txt,"\")), _xlpm.lastToken,TRIM(_xlfn.TEXTAFTER(_xlpm.before," ",-1)), _xlpm.isNum,IFERROR(ISNUMBER(--_xlpm.lastToken),FALSE), IF( OR( LOWER(_xlpm.after)="headflow", LOWER(_xlpm.after)="reach" ), "", IF( _xlpm.isNum, _xlpm.lastToken & " \ " & _xlpm.after, "" ) ) ), "" )
B275: Minor CVP Settlement Diversions to Yolo Basin | C275: SacWAM | D275: =IFERROR( _xlfn.XLOOKUP($H275,WEAP!$F:$F,WEAP!$A:$A), IF($I275="","",_xlfn.XLOOKUP($I275,WEAP!$G:$G,WEAP!$A:$A,"")) ) | E275: =IFERROR( _xlfn.XLOOKUP($H275,WEAP!$F:$F,WEAP!$B:$B), IF($I275="","",_xlfn.XLOOKUP($I275,WEAP!$G:$G,WEAP!$B:$B,"")) ) | F275: =IFERROR( _xlfn.XLOOKUP($H275,WEAP!$F:$F,WEAP!$C:$C), IF($I275="","",_xlfn.XLOOKUP($I275,WEAP!$G:$G,WEAP!$C:$C,"")) ) | G275: =IFERROR( _xlfn.XLOOKUP($H275,WEAP!$F:$F,WEAP!$E:$E), IF($I275="","",_xlfn.XLOOKUP($I275,WEAP!$G:$G,WEAP!$E:$E,"")) ) | H275: =IFERROR( _xlfn.LET( _xlpm.txt,TRIM(B275), _xlpm.before,TRIM(_xlfn.TEXTBEFORE(_xlpm.txt,"\",-1)), _xlpm.after,_xlfn.TEXTAFTER(_xlpm.txt,"\"), _xlpm.lastToken,TRIM(_xlfn.TEXTAFTER(_xlpm.before," ",-1)), _xlpm.isReach,LOWER(TRIM(_xlpm.after))="reach", _xlpm.cleaned, IF( ISNUMBER(--_xlpm.lastToken), _xlfn.TEXTBEFORE(_xlpm.before," ",-1) & " \ " & _xlpm.after, _xlpm.txt ), IF(_xlpm.isReach,_xlpm.txt,TRIM(_xlpm.cleaned)) ), B275 ) -> Minor CVP Settlement Diversions to Yolo Basin | I275: =IFERROR( _xlfn.LET( _xlpm.txt,B275, _xlpm.before,TRIM(_xlfn.TEXTBEFORE(_xlpm.txt,"\")), _xlpm.after,TRIM(_xlfn.TEXTAFTER(_xlpm.txt,"\")), _xlpm.lastToken,TRIM(_xlfn.TEXTAFTER(_xlpm.before," ",-1)), _xlpm.isNum,IFERROR(ISNUMBER(--_xlpm.lastToken),FALSE), IF( OR( LOWER(_xlpm.after)="headflow", LOWER(_xlpm.after)="reach" ), "", IF( _xlpm.isNum, _xlpm.lastToken & " \ " & _xlpm.after, "" ) ) ), "" )
A276: D_SAC065_WTPBTB | B276: Transmission Link from Sacramento River RM 065 to U_21_PU | C276: SacWAM | D276: =IFERROR( _xlfn.XLOOKUP($H276,WEAP!$F:$F,WEAP!$A:$A), IF($I276="","",_xlfn.XLOOKUP($I276,WEAP!$G:$G,WEAP!$A:$A,"")) ) -> 7647 | E276: =IFERROR( _xlfn.XLOOKUP($H276,WEAP!$F:$F,WEAP!$B:$B), IF($I276="","",_xlfn.XLOOKUP($I276,WEAP!$G:$G,WEAP!$B:$B,"")) ) -> Transmission Link from Sacramento River RM 065 to U_21_PU | F276: =IFERROR( _xlfn.XLOOKUP($H276,WEAP!$F:$F,WEAP!$C:$C), IF($I276="","",_xlfn.XLOOKUP($I276,WEAP!$G:$G,WEAP!$C:$C,"")) ) -> taf | G276: =IFERROR( _xlfn.XLOOKUP($H276,WEAP!$F:$F,WEAP!$E:$E), IF($I276="","",_xlfn.XLOOKUP($I276,WEAP!$G:$G,WEAP!$E:$E,"")) ) -> Transmission Link Flow | H276: =IFERROR( _xlfn.LET( _xlpm.txt,TRIM(B276), _xlpm.before,TRIM(_xlfn.TEXTBEFORE(_xlpm.txt,"\",-1)), _xlpm.after,_xlfn.TEXTAFTER(_xlpm.txt,"\"), _xlpm.lastToken,TRIM(_xlfn.TEXTAFTER(_xlpm.before," ",-1)), _xlpm.isReach,LOWER(TRIM(_xlpm.after))="reach", _xlpm.cleaned, IF( ISNUMBER(--_xlpm.lastToken), _xlfn.TEXTBEFORE(_xlpm.before," ",-1) & " \ " & _xlpm.after, _xlpm.txt ), IF(_xlpm.isReach,_xlpm.txt,TRIM(_xlpm.cleaned)) ), B276 ) -> Transmission Link from Sacramento River RM 065 to U_21_PU | I276: =IFERROR( _xlfn.LET( _xlpm.txt,B276, _xlpm.before,TRIM(_xlfn.TEXTBEFORE(_xlpm.txt,"\")), _xlpm.after,TRIM(_xlfn.TEXTAFTER(_xlpm.txt,"\")), _xlpm.lastToken,TRIM(_xlfn.TEXTAFTER(_xlpm.before," ",-1)), _xlpm.isNum,IFERROR(ISNUMBER(--_xlpm.lastToken),FALSE), IF( OR( LOWER(_xlpm.after)="headflow", LOWER(_xlpm.after)="reach" ), "", IF( _xlpm.isNum, _xlpm.lastToken & " \ " & _xlpm.after, "" ) ) ), "" )
B277: Transmission Link from Sacramento River WTP to U_26_NU3 | C277: SacWAM | D277: =IFERROR( _xlfn.XLOOKUP($H277,WEAP!$F:$F,WEAP!$A:$A), IF($I277="","",_xlfn.XLOOKUP($I277,WEAP!$G:$G,WEAP!$A:$A,"")) ) -> 7755 | E277: =IFERROR( _xlfn.XLOOKUP($H277,WEAP!$F:$F,WEAP!$B:$B), IF($I277="","",_xlfn.XLOOKUP($I277,WEAP!$G:$G,WEAP!$B:$B,"")) ) -> Transmission Link from Sacramento River WTP to U_26_NU3 | F277: =IFERROR( _xlfn.XLOOKUP($H277,WEAP!$F:$F,WEAP!$C:$C), IF($I277="","",_xlfn.XLOOKUP($I277,WEAP!$G:$G,WEAP!$C:$C,"")) ) -> taf | G277: =IFERROR( _xlfn.XLOOKUP($H277,WEAP!$F:$F,WEAP!$E:$E), IF($I277="","",_xlfn.XLOOKUP($I277,WEAP!$G:$G,WEAP!$E:$E,"")) ) -> Transmission Link Flow | H277: =IFERROR( _xlfn.LET( _xlpm.txt,TRIM(B277), _xlpm.before,TRIM(_xlfn.TEXTBEFORE(_xlpm.txt,"\",-1)), _xlpm.after,_xlfn.TEXTAFTER(_xlpm.txt,"\"), _xlpm.lastToken,TRIM(_xlfn.TEXTAFTER(_xlpm.before," ",-1)), _xlpm.isReach,LOWER(TRIM(_xlpm.after))="reach", _xlpm.cleaned, IF( ISNUMBER(--_xlpm.lastToken), _xlfn.TEXTBEFORE(_xlpm.before," ",-1) & " \ " & _xlpm.after, _xlpm.txt ), IF(_xlpm.isReach,_xlpm.txt,TRIM(_xlpm.cleaned)) ), B277 ) -> Transmission Link from Sacramento River WTP to U_26_NU3 | I277: =IFERROR( _xlfn.LET( _xlpm.txt,B277, _xlpm.before,TRIM(_xlfn.TEXTBEFORE(_xlpm.txt,"\")), _xlpm.after,TRIM(_xlfn.TEXTAFTER(_xlpm.txt,"\")), _xlpm.lastToken,TRIM(_xlfn.TEXTAFTER(_xlpm.before," ",-1)), _xlpm.isNum,IFERROR(ISNUMBER(--_xlpm.lastToken),FALSE), IF( OR( LOWER(_xlpm.after)="headflow", LOWER(_xlpm.after)="reach" ), "", IF( _xlpm.isNum, _xlpm.lastToken & " \ " & _xlpm.after, "" ) ) ), "" )
B278: Transmission Link from Sacramento River WTP to U_26_PU4 | C278: SacWAM | D278: =IFERROR( _xlfn.XLOOKUP($H278,WEAP!$F:$F,WEAP!$A:$A), IF($I278="","",_xlfn.XLOOKUP($I278,WEAP!$G:$G,WEAP!$A:$A,"")) ) -> 7810 | E278: =IFERROR( _xlfn.XLOOKUP($H278,WEAP!$F:$F,WEAP!$B:$B), IF($I278="","",_xlfn.XLOOKUP($I278,WEAP!$G:$G,WEAP!$B:$B,"")) ) -> Transmission Link from Sacramento River WTP to U_26_PU4 | F278: =IFERROR( _xlfn.XLOOKUP($H278,WEAP!$F:$F,WEAP!$C:$C), IF($I278="","",_xlfn.XLOOKUP($I278,WEAP!$G:$G,WEAP!$C:$C,"")) ) -> taf | G278: =IFERROR( _xlfn.XLOOKUP($H278,WEAP!$F:$F,WEAP!$E:$E), IF($I278="","",_xlfn.XLOOKUP($I278,WEAP!$G:$G,WEAP!$E:$E,"")) ) -> Transmission Link Flow | H278: =IFERROR( _xlfn.LET( _xlpm.txt,TRIM(B278), _xlpm.before,TRIM(_xlfn.TEXTBEFORE(_xlpm.txt,"\",-1)), _xlpm.after,_xlfn.TEXTAFTER(_xlpm.txt,"\"), _xlpm.lastToken,TRIM(_xlfn.TEXTAFTER(_xlpm.before," ",-1)), _xlpm.isReach,LOWER(TRIM(_xlpm.after))="reach", _xlpm.cleaned, IF( ISNUMBER(--_xlpm.lastToken), _xlfn.TEXTBEFORE(_xlpm.before," ",-1) & " \ " & _xlpm.after, _xlpm.txt ), IF(_xlpm.isReach,_xlpm.txt,TRIM(_xlpm.cleaned)) ), B278 ) -> Transmission Link from Sacramento River WTP to U_26_PU4 | I278: =IFERROR( _xlfn.LET( _xlpm.txt,B278, _xlpm.before,TRIM(_xlfn.TEXTBEFORE(_xlpm.txt,"\")), _xlpm.after,TRIM(_xlfn.TEXTAFTER(_xlpm.txt,"\")), _xlpm.lastToken,TRIM(_xlfn.TEXTAFTER(_xlpm.before," ",-1)), _xlpm.isNum,IFERROR(ISNUMBER(--_xlpm.lastToken),FALSE), IF( OR( LOWER(_xlpm.after)="headflow", LOWER(_xlpm.after)="reach" ), "", IF( _xlpm.isNum, _xlpm.lastToken & " \ " & _xlpm.after, "" ) ) ), "" )
A279: D_SAC050_FPT013 | B279: Freeport Pumping Plant 0 \ Headflow | C279: SacWAM | D279: =IFERROR( _xlfn.XLOOKUP($H279,WEAP!$F:$F,WEAP!$A:$A), IF($I279="","",_xlfn.XLOOKUP($I279,WEAP!$G:$G,WEAP!$A:$A,"")) ) -> 13077 | E279: =IFERROR( _xlfn.XLOOKUP($H279,WEAP!$F:$F,WEAP!$B:$B), IF($I279="","",_xlfn.XLOOKUP($I279,WEAP!$G:$G,WEAP!$B:$B,"")) ) -> Freeport Pumping Plant 0 \ Headflow | F279: =IFERROR( _xlfn.XLOOKUP($H279,WEAP!$F:$F,WEAP!$C:$C), IF($I279="","",_xlfn.XLOOKUP($I279,WEAP!$G:$G,WEAP!$C:$C,"")) ) -> taf | G279: =IFERROR( _xlfn.XLOOKUP($H279,WEAP!$F:$F,WEAP!$E:$E), IF($I279="","",_xlfn.XLOOKUP($I279,WEAP!$G:$G,WEAP!$E:$E,"")) ) -> Streamflow (below node or reach listed) | H279: =IFERROR( _xlfn.LET( _xlpm.txt,TRIM(B279), _xlpm.before,TRIM(_xlfn.TEXTBEFORE(_xlpm.txt,"\",-1)), _xlpm.after,_xlfn.TEXTAFTER(_xlpm.txt,"\"), _xlpm.lastToken,TRIM(_xlfn.TEXTAFTER(_xlpm.before," ",-1)), _xlpm.isReach,LOWER(TRIM(_xlpm.after))="reach", _xlpm.cleaned, IF( ISNUMBER(--_xlpm.lastToken), _xlfn.TEXTBEFORE(_xlpm.before," ",-1) & " \ " & _xlpm.after, _xlpm.txt ), IF(_xlpm.isReach,_xlpm.txt,TRIM(_xlpm.cleaned)) ), B279 ) -> Freeport Pumping Plant \ Headflow | I279: =IFERROR( _xlfn.LET( _xlpm.txt,B279, _xlpm.before,TRIM(_xlfn.TEXTBEFORE(_xlpm.txt,"\")), _xlpm.after,TRIM(_xlfn.TEXTAFTER(_xlpm.txt,"\")), _xlpm.lastToken,TRIM(_xlfn.TEXTAFTER(_xlpm.before," ",-1)), _xlpm.isNum,IFERROR(ISNUMBER(--_xlpm.lastToken),FALSE), IF( OR( LOWER(_xlpm.after)="headflow", LOWER(_xlpm.after)="reach" ), "", IF( _xlpm.isNum, _xlpm.lastToken & " \ " & _xlpm.after, "" ) ) ), "" )
B280: Transmission Link from Sacramento River RM 074 to U_20_25_NU | C280: SacWAM | D280: =IFERROR( _xlfn.XLOOKUP($H280,WEAP!$F:$F,WEAP!$A:$A), IF($I280="","",_xlfn.XLOOKUP($I280,WEAP!$G:$G,WEAP!$A:$A,"")) ) -> 7608 | E280: =IFERROR( _xlfn.XLOOKUP($H280,WEAP!$F:$F,WEAP!$B:$B), IF($I280="","",_xlfn.XLOOKUP($I280,WEAP!$G:$G,WEAP!$B:$B,"")) ) -> Transmission Link from Sacramento River RM 074 to U_20_25_NU | F280: =IFERROR( _xlfn.XLOOKUP($H280,WEAP!$F:$F,WEAP!$C:$C), IF($I280="","",_xlfn.XLOOKUP($I280,WEAP!$G:$G,WEAP!$C:$C,"")) ) -> taf | G280: =IFERROR( _xlfn.XLOOKUP($H280,WEAP!$F:$F,WEAP!$E:$E), IF($I280="","",_xlfn.XLOOKUP($I280,WEAP!$G:$G,WEAP!$E:$E,"")) ) -> Transmission Link Flow | H280: =IFERROR( _xlfn.LET( _xlpm.txt,TRIM(B280), _xlpm.before,TRIM(_xlfn.TEXTBEFORE(_xlpm.txt,"\",-1)), _xlpm.after,_xlfn.TEXTAFTER(_xlpm.txt,"\"), _xlpm.lastToken,TRIM(_xlfn.TEXTAFTER(_xlpm.before," ",-1)), _xlpm.isReach,LOWER(TRIM(_xlpm.after))="reach", _xlpm.cleaned, IF( ISNUMBER(--_xlpm.lastToken), _xlfn.TEXTBEFORE(_xlpm.before," ",-1) & " \ " & _xlpm.after, _xlpm.txt ), IF(_xlpm.isReach,_xlpm.txt,TRIM(_xlpm.cleaned)) ), B280 ) -> Transmission Link from Sacramento River RM 074 to U_20_25_NU | I280: =IFERROR( _xlfn.LET( _xlpm.txt,B280, _xlpm.before,TRIM(_xlfn.TEXTBEFORE(_xlpm.txt,"\")), _xlpm.after,TRIM(_xlfn.TEXTAFTER(_xlpm.txt,"\")), _xlpm.lastToken,TRIM(_xlfn.TEXTAFTER(_xlpm.before," ",-1)), _xlpm.isNum,IFERROR(ISNUMBER(--_xlpm.lastToken),FALSE), IF( OR( LOWER(_xlpm.after)="headflow", LOWER(_xlpm.after)="reach" ), "", IF( _xlpm.isNum, _xlpm.lastToken & " \ " & _xlpm.after, "" ) ) ), "" )
B281: Transmission Link from Sacramento River RM 075 to A_22_NA | C281: SacWAM | D281: =IFERROR( _xlfn.XLOOKUP($H281,WEAP!$F:$F,WEAP!$A:$A), IF($I281="","",_xlfn.XLOOKUP($I281,WEAP!$G:$G,WEAP!$A:$A,"")) ) -> 4620 | E281: =IFERROR( _xlfn.XLOOKUP($H281,WEAP!$F:$F,WEAP!$B:$B), IF($I281="","",_xlfn.XLOOKUP($I281,WEAP!$G:$G,WEAP!$B:$B,"")) ) -> Transmission Link from Sacramento River RM 075 to A_22_NA | F281: =IFERROR( _xlfn.XLOOKUP($H281,WEAP!$F:$F,WEAP!$C:$C), IF($I281="","",_xlfn.XLOOKUP($I281,WEAP!$G:$G,WEAP!$C:$C,"")) ) -> taf | G281: =IFERROR( _xlfn.XLOOKUP($H281,WEAP!$F:$F,WEAP!$E:$E), IF($I281="","",_xlfn.XLOOKUP($I281,WEAP!$G:$G,WEAP!$E:$E,"")) ) -> Transmission Link Flow | H281: =IFERROR( _xlfn.LET( _xlpm.txt,TRIM(B281), _xlpm.before,TRIM(_xlfn.TEXTBEFORE(_xlpm.txt,"\",-1)), _xlpm.after,_xlfn.TEXTAFTER(_xlpm.txt,"\"), _xlpm.lastToken,TRIM(_xlfn.TEXTAFTER(_xlpm.before," ",-1)), _xlpm.isReach,LOWER(TRIM(_xlpm.after))="reach", _xlpm.cleaned, IF( ISNUMBER(--_xlpm.lastToken), _xlfn.TEXTBEFORE(_xlpm.before," ",-1) & " \ " & _xlpm.after, _xlpm.txt ), IF(_xlpm.isReach,_xlpm.txt,TRIM(_xlpm.cleaned)) ), B281 ) -> Transmission Link from Sacramento River RM 075 to A_22_NA | I281: =IFERROR( _xlfn.LET( _xlpm.txt,B281, _xlpm.before,TRIM(_xlfn.TEXTBEFORE(_xlpm.txt,"\")), _xlpm.after,TRIM(_xlfn.TEXTAFTER(_xlpm.txt,"\")), _xlpm.lastToken,TRIM(_xlfn.TEXTAFTER(_xlpm.before," ",-1)), _xlpm.isNum,IFERROR(ISNUMBER(--_xlpm.lastToken),FALSE), IF( OR( LOWER(_xlpm.after)="headflow", LOWER(_xlpm.after)="reach" ), "", IF( _xlpm.isNum, _xlpm.lastToken & " \ " & _xlpm.after, "" ) ) ), "" )
B282: Transmission Link from Sacramento River RM 081 to A_21_NA | C282: SacWAM | D282: =IFERROR( _xlfn.XLOOKUP($H282,WEAP!$F:$F,WEAP!$A:$A), IF($I282="","",_xlfn.XLOOKUP($I282,WEAP!$G:$G,WEAP!$A:$A,"")) ) -> 4599 | E282: =IFERROR( _xlfn.XLOOKUP($H282,WEAP!$F:$F,WEAP!$B:$B), IF($I282="","",_xlfn.XLOOKUP($I282,WEAP!$G:$G,WEAP!$B:$B,"")) ) -> Transmission Link from Sacramento River RM 081 to A_21_NA | F282: =IFERROR( _xlfn.XLOOKUP($H282,WEAP!$F:$F,WEAP!$C:$C), IF($I282="","",_xlfn.XLOOKUP($I282,WEAP!$G:$G,WEAP!$C:$C,"")) ) -> taf | G282: =IFERROR( _xlfn.XLOOKUP($H282,WEAP!$F:$F,WEAP!$E:$E), IF($I282="","",_xlfn.XLOOKUP($I282,WEAP!$G:$G,WEAP!$E:$E,"")) ) -> Transmission Link Flow | H282: =IFERROR( _xlfn.LET( _xlpm.txt,TRIM(B282), _xlpm.before,TRIM(_xlfn.TEXTBEFORE(_xlpm.txt,"\",-1)), _xlpm.after,_xlfn.TEXTAFTER(_xlpm.txt,"\"), _xlpm.lastToken,TRIM(_xlfn.TEXTAFTER(_xlpm.before," ",-1)), _xlpm.isReach,LOWER(TRIM(_xlpm.after))="reach", _xlpm.cleaned, IF( ISNUMBER(--_xlpm.lastToken), _xlfn.TEXTBEFORE(_xlpm.before," ",-1) & " \ " & _xlpm.after, _xlpm.txt ), IF(_xlpm.isReach,_xlpm.txt,TRIM(_xlpm.cleaned)) ), B282 ) -> Transmission Link from Sacramento River RM 081 to A_21_NA | I282: =IFERROR( _xlfn.LET( _xlpm.txt,B282, _xlpm.before,TRIM(_xlfn.TEXTBEFORE(_xlpm.txt,"\")), _xlpm.after,TRIM(_xlfn.TEXTAFTER(_xlpm.txt,"\")), _xlpm.lastToken,TRIM(_xlfn.TEXTAFTER(_xlpm.before," ",-1)), _xlpm.isNum,IFERROR(ISNUMBER(--_xlpm.lastToken),FALSE), IF( OR( LOWER(_xlpm.after)="headflow", LOWER(_xlpm.after)="reach" ), "", IF( _xlpm.isNum, _xlpm.lastToken & " \ " & _xlpm.after, "" ) ) ), "" )
B283: Transmission Link from Sacramento River RM 136 to A_18_19_NA | C283: SacWAM | D283: =IFERROR( _xlfn.XLOOKUP($H283,WEAP!$F:$F,WEAP!$A:$A), IF($I283="","",_xlfn.XLOOKUP($I283,WEAP!$G:$G,WEAP!$A:$A,"")) ) -> 4555 | E283: =IFERROR( _xlfn.XLOOKUP($H283,WEAP!$F:$F,WEAP!$B:$B), IF($I283="","",_xlfn.XLOOKUP($I283,WEAP!$G:$G,WEAP!$B:$B,"")) ) -> Transmission Link from Sacramento River RM 136 to A_18_19_NA | F283: =IFERROR( _xlfn.XLOOKUP($H283,WEAP!$F:$F,WEAP!$C:$C), IF($I283="","",_xlfn.XLOOKUP($I283,WEAP!$G:$G,WEAP!$C:$C,"")) ) -> taf | G283: =IFERROR( _xlfn.XLOOKUP($H283,WEAP!$F:$F,WEAP!$E:$E), IF($I283="","",_xlfn.XLOOKUP($I283,WEAP!$G:$G,WEAP!$E:$E,"")) ) -> Transmission Link Flow | H283: =IFERROR( _xlfn.LET( _xlpm.txt,TRIM(B283), _xlpm.before,TRIM(_xlfn.TEXTBEFORE(_xlpm.txt,"\",-1)), _xlpm.after,_xlfn.TEXTAFTER(_xlpm.txt,"\"), _xlpm.lastToken,TRIM(_xlfn.TEXTAFTER(_xlpm.before," ",-1)), _xlpm.isReach,LOWER(TRIM(_xlpm.after))="reach", _xlpm.cleaned, IF( ISNUMBER(--_xlpm.lastToken), _xlfn.TEXTBEFORE(_xlpm.before," ",-1) & " \ " & _xlpm.after, _xlpm.txt ), IF(_xlpm.isReach,_xlpm.txt,TRIM(_xlpm.cleaned)) ), B283 ) -> Transmission Link from Sacramento River RM 136 to A_18_19_NA | I283: =IFERROR( _xlfn.LET( _xlpm.txt,B283, _xlpm.before,TRIM(_xlfn.TEXTBEFORE(_xlpm.txt,"\")), _xlpm.after,TRIM(_xlfn.TEXTAFTER(_xlpm.txt,"\")), _xlpm.lastToken,TRIM(_xlfn.TEXTAFTER(_xlpm.before," ",-1)), _xlpm.isNum,IFERROR(ISNUMBER(--_xlpm.lastToken),FALSE), IF( OR( LOWER(_xlpm.after)="headflow", LOWER(_xlpm.after)="reach" ), "", IF( _xlpm.isNum, _xlpm.lastToken & " \ " & _xlpm.after, "" ) ) ), "" )
B284: Transmission Link from Sacramento River RM 146 to A_08_NA | C284: SacWAM | D284: =IFERROR( _xlfn.XLOOKUP($H284,WEAP!$F:$F,WEAP!$A:$A), IF($I284="","",_xlfn.XLOOKUP($I284,WEAP!$G:$G,WEAP!$A:$A,"")) ) -> 4231 | E284: =IFERROR( _xlfn.XLOOKUP($H284,WEAP!$F:$F,WEAP!$B:$B), IF($I284="","",_xlfn.XLOOKUP($I284,WEAP!$G:$G,WEAP!$B:$B,"")) ) -> Transmission Link from Sacramento River RM 146 to A_08_NA | F284: =IFERROR( _xlfn.XLOOKUP($H284,WEAP!$F:$F,WEAP!$C:$C), IF($I284="","",_xlfn.XLOOKUP($I284,WEAP!$G:$G,WEAP!$C:$C,"")) ) -> taf | G284: =IFERROR( _xlfn.XLOOKUP($H284,WEAP!$F:$F,WEAP!$E:$E), IF($I284="","",_xlfn.XLOOKUP($I284,WEAP!$G:$G,WEAP!$E:$E,"")) ) -> Transmission Link Flow | H284: =IFERROR( _xlfn.LET( _xlpm.txt,TRIM(B284), _xlpm.before,TRIM(_xlfn.TEXTBEFORE(_xlpm.txt,"\",-1)), _xlpm.after,_xlfn.TEXTAFTER(_xlpm.txt,"\"), _xlpm.lastToken,TRIM(_xlfn.TEXTAFTER(_xlpm.before," ",-1)), _xlpm.isReach,LOWER(TRIM(_xlpm.after))="reach", _xlpm.cleaned, IF( ISNUMBER(--_xlpm.lastToken), _xlfn.TEXTBEFORE(_xlpm.before," ",-1) & " \ " & _xlpm.after, _xlpm.txt ), IF(_xlpm.isReach,_xlpm.txt,TRIM(_xlpm.cleaned)) ), B284 ) -> Transmission Link from Sacramento River RM 146 to A_08_NA | I284: =IFERROR( _xlfn.LET( _xlpm.txt,B284, _xlpm.before,TRIM(_xlfn.TEXTBEFORE(_xlpm.txt,"\")), _xlpm.after,TRIM(_xlfn.TEXTAFTER(_xlpm.txt,"\")), _xlpm.lastToken,TRIM(_xlfn.TEXTAFTER(_xlpm.before," ",-1)), _xlpm.isNum,IFERROR(ISNUMBER(--_xlpm.lastToken),FALSE), IF( OR( LOWER(_xlpm.after)="headflow", LOWER(_xlpm.after)="reach" ), "", IF( _xlpm.isNum, _xlpm.lastToken & " \ " & _xlpm.after, "" ) ) ), "" )
B285: Transmission Link from Sacramento River RM 185 to A_09_NA | C285: SacWAM | D285: =IFERROR( _xlfn.XLOOKUP($H285,WEAP!$F:$F,WEAP!$A:$A), IF($I285="","",_xlfn.XLOOKUP($I285,WEAP!$G:$G,WEAP!$A:$A,"")) ) -> 5068 | E285: =IFERROR( _xlfn.XLOOKUP($H285,WEAP!$F:$F,WEAP!$B:$B), IF($I285="","",_xlfn.XLOOKUP($I285,WEAP!$G:$G,WEAP!$B:$B,"")) ) -> Transmission Link from Sacramento River RM 185 to A_09_NA | F285: =IFERROR( _xlfn.XLOOKUP($H285,WEAP!$F:$F,WEAP!$C:$C), IF($I285="","",_xlfn.XLOOKUP($I285,WEAP!$G:$G,WEAP!$C:$C,"")) ) -> taf | G285: =IFERROR( _xlfn.XLOOKUP($H285,WEAP!$F:$F,WEAP!$E:$E), IF($I285="","",_xlfn.XLOOKUP($I285,WEAP!$G:$G,WEAP!$E:$E,"")) ) -> Transmission Link Flow | H285: =IFERROR( _xlfn.LET( _xlpm.txt,TRIM(B285), _xlpm.before,TRIM(_xlfn.TEXTBEFORE(_xlpm.txt,"\",-1)), _xlpm.after,_xlfn.TEXTAFTER(_xlpm.txt,"\"), _xlpm.lastToken,TRIM(_xlfn.TEXTAFTER(_xlpm.before," ",-1)), _xlpm.isReach,LOWER(TRIM(_xlpm.after))="reach", _xlpm.cleaned, IF( ISNUMBER(--_xlpm.lastToken), _xlfn.TEXTBEFORE(_xlpm.before," ",-1) & " \ " & _xlpm.after, _xlpm.txt ), IF(_xlpm.isReach,_xlpm.txt,TRIM(_xlpm.cleaned)) ), B285 ) -> Transmission Link from Sacramento River RM 185 to A_09_NA | I285: =IFERROR( _xlfn.LET( _xlpm.txt,B285, _xlpm.before,TRIM(_xlfn.TEXTBEFORE(_xlpm.txt,"\")), _xlpm.after,TRIM(_xlfn.TEXTAFTER(_xlpm.txt,"\")), _xlpm.lastToken,TRIM(_xlfn.TEXTAFTER(_xlpm.before," ",-1)), _xlpm.isNum,IFERROR(ISNUMBER(--_xlpm.lastToken),FALSE), IF( OR( LOWER(_xlpm.after)="headflow", LOWER(_xlpm.after)="reach" ), "", IF( _xlpm.isNum, _xlpm.lastToken & " \ " & _xlpm.after, "" ) ) ), "" )
B286: Transmission Link from Sacramento River RM 196 to A_09_NA | C286: SacWAM | D286: =IFERROR( _xlfn.XLOOKUP($H286,WEAP!$F:$F,WEAP!$A:$A), IF($I286="","",_xlfn.XLOOKUP($I286,WEAP!$G:$G,WEAP!$A:$A,"")) ) -> 5040 | E286: =IFERROR( _xlfn.XLOOKUP($H286,WEAP!$F:$F,WEAP!$B:$B), IF($I286="","",_xlfn.XLOOKUP($I286,WEAP!$G:$G,WEAP!$B:$B,"")) ) -> Transmission Link from Sacramento River RM 196 to A_09_NA | F286: =IFERROR( _xlfn.XLOOKUP($H286,WEAP!$F:$F,WEAP!$C:$C), IF($I286="","",_xlfn.XLOOKUP($I286,WEAP!$G:$G,WEAP!$C:$C,"")) ) -> taf | G286: =IFERROR( _xlfn.XLOOKUP($H286,WEAP!$F:$F,WEAP!$E:$E), IF($I286="","",_xlfn.XLOOKUP($I286,WEAP!$G:$G,WEAP!$E:$E,"")) ) -> Transmission Link Flow | H286: =IFERROR( _xlfn.LET( _xlpm.txt,TRIM(B286), _xlpm.before,TRIM(_xlfn.TEXTBEFORE(_xlpm.txt,"\",-1)), _xlpm.after,_xlfn.TEXTAFTER(_xlpm.txt,"\"), _xlpm.lastToken,TRIM(_xlfn.TEXTAFTER(_xlpm.before," ",-1)), _xlpm.isReach,LOWER(TRIM(_xlpm.after))="reach", _xlpm.cleaned, IF( ISNUMBER(--_xlpm.lastToken), _xlfn.TEXTBEFORE(_xlpm.before," ",-1) & " \ " & _xlpm.after, _xlpm.txt ), IF(_xlpm.isReach,_xlpm.txt,TRIM(_xlpm.cleaned)) ), B286 ) -> Transmission Link from Sacramento River RM 196 to A_09_NA | I286: =IFERROR( _xlfn.LET( _xlpm.txt,B286, _xlpm.before,TRIM(_xlfn.TEXTBEFORE(_xlpm.txt,"\")), _xlpm.after,TRIM(_xlfn.TEXTAFTER(_xlpm.txt,"\")), _xlpm.lastToken,TRIM(_xlfn.TEXTAFTER(_xlpm.before," ",-1)), _xlpm.isNum,IFERROR(ISNUMBER(--_xlpm.lastToken),FALSE), IF( OR( LOWER(_xlpm.after)="headflow", LOWER(_xlpm.after)="reach" ), "", IF( _xlpm.isNum, _xlpm.lastToken & " \ " & _xlpm.after, "" ) ) ), "" )
...

Sheet WEAP
A1: ObjID | B1: WEAP Variable | C1: WEAP Units | D1: WEAP Model | E1: WEAP Favorite | F1: Match Key | G1: Match Var
A2: -999 | B2: A_02_NA | C2: taf | D2: SacWAM | E2: Theoretical Catchment Irrigation Demand | F2: =IFERROR( _xlfn.LET( _xlpm.txt,TRIM(B2), _xlpm.before,TRIM(_xlfn.TEXTBEFORE(_xlpm.txt,"\",-1)), _xlpm.after,_xlfn.TEXTAFTER(_xlpm.txt,"\"), _xlpm.lastToken,TRIM(_xlfn.TEXTAFTER(_xlpm.before," ",-1)), _xlpm.isReach,LOWER(TRIM(_xlpm.after))="reach", _xlpm.cleaned, IF( ISNUMBER(--_xlpm.lastToken), _xlfn.TEXTBEFORE(_xlpm.before," ",-1) & " \ " & _xlpm.after, _xlpm.txt ), IF(_xlpm.isReach,_xlpm.txt,TRIM(_xlpm.cleaned)) ), B2 ) -> A_02_NA | G2: =IFERROR( _xlfn.LET( _xlpm.txt,B2, _xlpm.before,TRIM(_xlfn.TEXTBEFORE(_xlpm.txt,"\")), _xlpm.after,TRIM(_xlfn.TEXTAFTER(_xlpm.txt,"\")), _xlpm.lastToken, IF( IFERROR(ISNUMBER(--_xlpm.before),FALSE), _xlpm.before, TRIM(_xlfn.TEXTAFTER(_xlpm.before," ",-1)) ), _xlpm.isNum,IFERROR(ISNUMBER(--_xlpm.lastToken),FALSE), IF( OR( LOWER(_xlpm.after)="headflow", LOWER(_xlpm.after)="reach" ), "", IF( _xlpm.isNum, _xlpm.lastToken & " \ " & _xlpm.after, "" ) ) ), "" )
A3: -999 | B3: A_02_PA | C3: taf | D3: SacWAM | E3: Theoretical Catchment Irrigation Demand | F3: =IFERROR( _xlfn.LET( _xlpm.txt,TRIM(B3), _xlpm.before,TRIM(_xlfn.TEXTBEFORE(_xlpm.txt,"\",-1)), _xlpm.after,_xlfn.TEXTAFTER(_xlpm.txt,"\"), _xlpm.lastToken,TRIM(_xlfn.TEXTAFTER(_xlpm.before," ",-1)), _xlpm.isReach,LOWER(TRIM(_xlpm.after))="reach", _xlpm.cleaned, IF( ISNUMBER(--_xlpm.lastToken), _xlfn.TEXTBEFORE(_xlpm.before," ",-1) & " \ " & _xlpm.after, _xlpm.txt ), IF(_xlpm.isReach,_xlpm.txt,TRIM(_xlpm.cleaned)) ), B3 ) -> A_02_PA | G3: =IFERROR( _xlfn.LET( _xlpm.txt,B3, _xlpm.before,TRIM(_xlfn.TEXTBEFORE(_xlpm.txt,"\")), _xlpm.after,TRIM(_xlfn.TEXTAFTER(_xlpm.txt,"\")), _xlpm.lastToken, IF( IFERROR(ISNUMBER(--_xlpm.before),FALSE), _xlpm.before, TRIM(_xlfn.TEXTAFTER(_xlpm.before," ",-1)) ), _xlpm.isNum,IFERROR(ISNUMBER(--_xlpm.lastToken),FALSE), IF( OR( LOWER(_xlpm.after)="headflow", LOWER(_xlpm.after)="reach" ), "", IF( _xlpm.isNum, _xlpm.lastToken & " \ " & _xlpm.after, "" ) ) ), "" )
A4: -999 | B4: A_02_SA | C4: taf | D4: SacWAM | E4: Theoretical Catchment Irrigation Demand | F4: =IFERROR( _xlfn.LET( _xlpm.txt,TRIM(B4), _xlpm.before,TRIM(_xlfn.TEXTBEFORE(_xlpm.txt,"\",-1)), _xlpm.after,_xlfn.TEXTAFTER(_xlpm.txt,"\"), _xlpm.lastToken,TRIM(_xlfn.TEXTAFTER(_xlpm.before," ",-1)), _xlpm.isReach,LOWER(TRIM(_xlpm.after))="reach", _xlpm.cleaned, IF( ISNUMBER(--_xlpm.lastToken), _xlfn.TEXTBEFORE(_xlpm.before," ",-1) & " \ " & _xlpm.after, _xlpm.txt ), IF(_xlpm.isReach,_xlpm.txt,TRIM(_xlpm.cleaned)) ), B4 ) -> A_02_SA | G4: =IFERROR( _xlfn.LET( _xlpm.txt,B4, _xlpm.before,TRIM(_xlfn.TEXTBEFORE(_xlpm.txt,"\")), _xlpm.after,TRIM(_xlfn.TEXTAFTER(_xlpm.txt,"\")), _xlpm.lastToken, IF( IFERROR(ISNUMBER(--_xlpm.before),FALSE), _xlpm.before, TRIM(_xlfn.TEXTAFTER(_xlpm.before," ",-1)) ), _xlpm.isNum,IFERROR(ISNUMBER(--_xlpm.lastToken),FALSE), IF( OR( LOWER(_xlpm.after)="headflow", LOWER(_xlpm.after)="reach" ), "", IF( _xlpm.isNum, _xlpm.lastToken & " \ " & _xlpm.after, "" ) ) ), "" )
A5: -999 | B5: A_03_NA | C5: taf | D5: SacWAM | E5: Theoretical Catchment Irrigation Demand | F5: =IFERROR( _xlfn.LET( _xlpm.txt,TRIM(B5), _xlpm.before,TRIM(_xlfn.TEXTBEFORE(_xlpm.txt,"\",-1)), _xlpm.after,_xlfn.TEXTAFTER(_xlpm.txt,"\"), _xlpm.lastToken,TRIM(_xlfn.TEXTAFTER(_xlpm.before," ",-1)), _xlpm.isReach,LOWER(TRIM(_xlpm.after))="reach", _xlpm.cleaned, IF( ISNUMBER(--_xlpm.lastToken), _xlfn.TEXTBEFORE(_xlpm.before," ",-1) & " \ " & _xlpm.after, _xlpm.txt ), IF(_xlpm.isReach,_xlpm.txt,TRIM(_xlpm.cleaned)) ), B5 ) -> A_03_NA | G5: =IFERROR( _xlfn.LET( _xlpm.txt,B5, _xlpm.before,TRIM(_xlfn.TEXTBEFORE(_xlpm.txt,"\")), _xlpm.after,TRIM(_xlfn.TEXTAFTER(_xlpm.txt,"\")), _xlpm.lastToken, IF( IFERROR(ISNUMBER(--_xlpm.before),FALSE), _xlpm.before, TRIM(_xlfn.TEXTAFTER(_xlpm.before," ",-1)) ), _xlpm.isNum,IFERROR(ISNUMBER(--_xlpm.lastToken),FALSE), IF( OR( LOWER(_xlpm.after)="headflow", LOWER(_xlpm.after)="reach" ), "", IF( _xlpm.isNum, _xlpm.lastToken & " \ " & _xlpm.after, "" ) ) ), "" )
A6: -999 | B6: A_03_PA | C6: taf | D6: SacWAM | E6: Theoretical Catchment Irrigation Demand | F6: =IFERROR( _xlfn.LET( _xlpm.txt,TRIM(B6), _xlpm.before,TRIM(_xlfn.TEXTBEFORE(_xlpm.txt,"\",-1)), _xlpm.after,_xlfn.TEXTAFTER(_xlpm.txt,"\"), _xlpm.lastToken,TRIM(_xlfn.TEXTAFTER(_xlpm.before," ",-1)), _xlpm.isReach,LOWER(TRIM(_xlpm.after))="reach", _xlpm.cleaned, IF( ISNUMBER(--_xlpm.lastToken), _xlfn.TEXTBEFORE(_xlpm.before," ",-1) & " \ " & _xlpm.after, _xlpm.txt ), IF(_xlpm.isReach,_xlpm.txt,TRIM(_xlpm.cleaned)) ), B6 ) -> A_03_PA | G6: =IFERROR( _xlfn.LET( _xlpm.txt,B6, _xlpm.before,TRIM(_xlfn.TEXTBEFORE(_xlpm.txt,"\")), _xlpm.after,TRIM(_xlfn.TEXTAFTER(_xlpm.txt,"\")), _xlpm.lastToken, IF( IFERROR(ISNUMBER(--_xlpm.before),FALSE), _xlpm.before, TRIM(_xlfn.TEXTAFTER(_xlpm.before," ",-1)) ), _xlpm.isNum,IFERROR(ISNUMBER(--_xlpm.lastToken),FALSE), IF( OR( LOWER(_xlpm.after)="headflow", LOWER(_xlpm.after)="reach" ), "", IF( _xlpm.isNum, _xlpm.lastToken & " \ " & _xlpm.after, "" ) ) ), "" )
A7: -999 | B7: A_03_SA | C7: taf | D7: SacWAM | E7: Theoretical Catchment Irrigation Demand | F7: =IFERROR( _xlfn.LET( _xlpm.txt,TRIM(B7), _xlpm.before,TRIM(_xlfn.TEXTBEFORE(_xlpm.txt,"\",-1)), _xlpm.after,_xlfn.TEXTAFTER(_xlpm.txt,"\"), _xlpm.lastToken,TRIM(_xlfn.TEXTAFTER(_xlpm.before," ",-1)), _xlpm.isReach,LOWER(TRIM(_xlpm.after))="reach", _xlpm.cleaned, IF( ISNUMBER(--_xlpm.lastToken), _xlfn.TEXTBEFORE(_xlpm.before," ",-1) & " \ " & _xlpm.after, _xlpm.txt ), IF(_xlpm.isReach,_xlpm.txt,TRIM(_xlpm.cleaned)) ), B7 ) -> A_03_SA | G7: =IFERROR( _xlfn.LET( _xlpm.txt,B7, _xlpm.before,TRIM(_xlfn.TEXTBEFORE(_xlpm.txt,"\")), _xlpm.after,TRIM(_xlfn.TEXTAFTER(_xlpm.txt,"\")), _xlpm.lastToken, IF( IFERROR(ISNUMBER(--_xlpm.before),FALSE), _xlpm.before, TRIM(_xlfn.TEXTAFTER(_xlpm.before," ",-1)) ), _xlpm.isNum,IFERROR(ISNUMBER(--_xlpm.lastToken),FALSE), IF( OR( LOWER(_xlpm.after)="headflow", LOWER(_xlpm.after)="reach" ), "", IF( _xlpm.isNum, _xlpm.lastToken & " \ " & _xlpm.after, "" ) ) ), "" )
A8: -999 | B8: A_04_06_NA1 | C8: taf | D8: SacWAM | E8: Theoretical Catchment Irrigation Demand | F8: =IFERROR( _xlfn.LET( _xlpm.txt,TRIM(B8), _xlpm.before,TRIM(_xlfn.TEXTBEFORE(_xlpm.txt,"\",-1)), _xlpm.after,_xlfn.TEXTAFTER(_xlpm.txt,"\"), _xlpm.lastToken,TRIM(_xlfn.TEXTAFTER(_xlpm.before," ",-1)), _xlpm.isReach,LOWER(TRIM(_xlpm.after))="reach", _xlpm.cleaned, IF( ISNUMBER(--_xlpm.lastToken), _xlfn.TEXTBEFORE(_xlpm.before," ",-1) & " \ " & _xlpm.after, _xlpm.txt ), IF(_xlpm.isReach,_xlpm.txt,TRIM(_xlpm.cleaned)) ), B8 ) -> A_04_06_NA1 | G8: =IFERROR( _xlfn.LET( _xlpm.txt,B8, _xlpm.before,TRIM(_xlfn.TEXTBEFORE(_xlpm.txt,"\")), _xlpm.after,TRIM(_xlfn.TEXTAFTER(_xlpm.txt,"\")), _xlpm.lastToken, IF( IFERROR(ISNUMBER(--_xlpm.before),FALSE), _xlpm.before, TRIM(_xlfn.TEXTAFTER(_xlpm.before," ",-1)) ), _xlpm.isNum,IFERROR(ISNUMBER(--_xlpm.lastToken),FALSE), IF( OR( LOWER(_xlpm.after)="headflow", LOWER(_xlpm.after)="reach" ), "", IF( _xlpm.isNum, _xlpm.lastToken & " \ " & _xlpm.after, "" ) ) ), "" )
A9: -999 | B9: A_04_06_NA2 | C9: taf | D9: SacWAM | E9: Theoretical Catchment Irrigation Demand | F9: =IFERROR( _xlfn.LET( _xlpm.txt,TRIM(B9), _xlpm.before,TRIM(_xlfn.TEXTBEFORE(_xlpm.txt,"\",-1)), _xlpm.after,_xlfn.TEXTAFTER(_xlpm.txt,"\"), _xlpm.lastToken,TRIM(_xlfn.TEXTAFTER(_xlpm.before," ",-1)), _xlpm.isReach,LOWER(TRIM(_xlpm.after))="reach", _xlpm.cleaned, IF( ISNUMBER(--_xlpm.lastToken), _xlfn.TEXTBEFORE(_xlpm.before," ",-1) & " \ " & _xlpm.after, _xlpm.txt ), IF(_xlpm.isReach,_xlpm.txt,TRIM(_xlpm.cleaned)) ), B9 ) -> A_04_06_NA2 | G9: =IFERROR( _xlfn.LET( _xlpm.txt,B9, _xlpm.before,TRIM(_xlfn.TEXTBEFORE(_xlpm.txt,"\")), _xlpm.after,TRIM(_xlfn.TEXTAFTER(_xlpm.txt,"\")), _xlpm.lastToken, IF( IFERROR(ISNUMBER(--_xlpm.before),FALSE), _xlpm.before, TRIM(_xlfn.TEXTAFTER(_xlpm.before," ",-1)) ), _xlpm.isNum,IFERROR(ISNUMBER(--_xlpm.lastToken),FALSE), IF( OR( LOWER(_xlpm.after)="headflow", LOWER(_xlpm.after)="reach" ), "", IF( _xlpm.isNum, _xlpm.lastToken & " \ " & _xlpm.after, "" ) ) ), "" )
A10: -999 | B10: A_04_06_PA1 | C10: taf | D10: SacWAM | E10: Theoretical Catchment Irrigation Demand | F10: =IFERROR( _xlfn.LET( _xlpm.txt,TRIM(B10), _xlpm.before,TRIM(_xlfn.TEXTBEFORE(_xlpm.txt,"\",-1)), _xlpm.after,_xlfn.TEXTAFTER(_xlpm.txt,"\"), _xlpm.lastToken,TRIM(_xlfn.TEXTAFTER(_xlpm.before," ",-1)), _xlpm.isReach,LOWER(TRIM(_xlpm.after))="reach", _xlpm.cleaned, IF( ISNUMBER(--_xlpm.lastToken), _xlfn.TEXTBEFORE(_xlpm.before," ",-1) & " \ " & _xlpm.after, _xlpm.txt ), IF(_xlpm.isReach,_xlpm.txt,TRIM(_xlpm.cleaned)) ), B10 ) -> A_04_06_PA1 | G10: =IFERROR( _xlfn.LET( _xlpm.txt,B10, _xlpm.before,TRIM(_xlfn.TEXTBEFORE(_xlpm.txt,"\")), _xlpm.after,TRIM(_xlfn.TEXTAFTER(_xlpm.txt,"\")), _xlpm.lastToken, IF( IFERROR(ISNUMBER(--_xlpm.before),FALSE), _xlpm.before, TRIM(_xlfn.TEXTAFTER(_xlpm.before," ",-1)) ), _xlpm.isNum,IFERROR(ISNUMBER(--_xlpm.lastToken),FALSE), IF( OR( LOWER(_xlpm.after)="headflow", LOWER(_xlpm.after)="reach" ), "", IF( _xlpm.isNum, _xlpm.lastToken & " \ " & _xlpm.after, "" ) ) ), "" )
A11: -999 | B11: A_04_06_PA2 | C11: taf | D11: SacWAM | E11: Theoretical Catchment Irrigation Demand | F11: =IFERROR( _xlfn.LET( _xlpm.txt,TRIM(B11), _xlpm.before,TRIM(_xlfn.TEXTBEFORE(_xlpm.txt,"\",-1)), _xlpm.after,_xlfn.TEXTAFTER(_xlpm.txt,"\"), _xlpm.lastToken,TRIM(_xlfn.TEXTAFTER(_xlpm.before," ",-1)), _xlpm.isReach,LOWER(TRIM(_xlpm.after))="reach", _xlpm.cleaned, IF( ISNUMBER(--_xlpm.lastToken), _xlfn.TEXTBEFORE(_xlpm.before," ",-1) & " \ " & _xlpm.after, _xlpm.txt ), IF(_xlpm.isReach,_xlpm.txt,TRIM(_xlpm.cleaned)) ), B11 ) -> A_04_06_PA2 | G11: =IFERROR( _xlfn.LET( _xlpm.txt,B11, _xlpm.before,TRIM(_xlfn.TEXTBEFORE(_xlpm.txt,"\")), _xlpm.after,TRIM(_xlfn.TEXTAFTER(_xlpm.txt,"\")), _xlpm.lastToken, IF( IFERROR(ISNUMBER(--_xlpm.before),FALSE), _xlpm.before, TRIM(_xlfn.TEXTAFTER(_xlpm.before," ",-1)) ), _xlpm.isNum,IFERROR(ISNUMBER(--_xlpm.lastToken),FALSE), IF( OR( LOWER(_xlpm.after)="headflow", LOWER(_xlpm.after)="reach" ), "", IF( _xlpm.isNum, _xlpm.lastToken & " \ " & _xlpm.after, "" ) ) ), "" )
A12: -999 | B12: A_05_NA | C12: taf | D12: SacWAM | E12: Theoretical Catchment Irrigation Demand | F12: =IFERROR( _xlfn.LET( _xlpm.txt,TRIM(B12), _xlpm.before,TRIM(_xlfn.TEXTBEFORE(_xlpm.txt,"\",-1)), _xlpm.after,_xlfn.TEXTAFTER(_xlpm.txt,"\"), _xlpm.lastToken,TRIM(_xlfn.TEXTAFTER(_xlpm.before," ",-1)), _xlpm.isReach,LOWER(TRIM(_xlpm.after))="reach", _xlpm.cleaned, IF( ISNUMBER(--_xlpm.lastToken), _xlfn.TEXTBEFORE(_xlpm.before," ",-1) & " \ " & _xlpm.after, _xlpm.txt ), IF(_xlpm.isReach,_xlpm.txt,TRIM(_xlpm.cleaned)) ), B12 ) -> A_05_NA | G12: =IFERROR( _xlfn.LET( _xlpm.txt,B12, _xlpm.before,TRIM(_xlfn.TEXTBEFORE(_xlpm.txt,"\")), _xlpm.after,TRIM(_xlfn.TEXTAFTER(_xlpm.txt,"\")), _xlpm.lastToken, IF( IFERROR(ISNUMBER(--_xlpm.before),FALSE), _xlpm.before, TRIM(_xlfn.TEXTAFTER(_xlpm.before," ",-1)) ), _xlpm.isNum,IFERROR(ISNUMBER(--_xlpm.lastToken),FALSE), IF( OR( LOWER(_xlpm.after)="headflow", LOWER(_xlpm.after)="reach" ), "", IF( _xlpm.isNum, _xlpm.lastToken & " \ " & _xlpm.after, "" ) ) ), "" )
A13: -999 | B13: A_07_NA | C13: taf | D13: SacWAM | E13: Theoretical Catchment Irrigation Demand | F13: =IFERROR( _xlfn.LET( _xlpm.txt,TRIM(B13), _xlpm.before,TRIM(_xlfn.TEXTBEFORE(_xlpm.txt,"\",-1)), _xlpm.after,_xlfn.TEXTAFTER(_xlpm.txt,"\"), _xlpm.lastToken,TRIM(_xlfn.TEXTAFTER(_xlpm.before," ",-1)), _xlpm.isReach,LOWER(TRIM(_xlpm.after))="reach", _xlpm.cleaned, IF( ISNUMBER(--_xlpm.lastToken), _xlfn.TEXTBEFORE(_xlpm.before," ",-1) & " \ " & _xlpm.after, _xlpm.txt ), IF(_xlpm.isReach,_xlpm.txt,TRIM(_xlpm.cleaned)) ), B13 ) -> A_07_NA | G13: =IFERROR( _xlfn.LET( _xlpm.txt,B13, _xlpm.before,TRIM(_xlfn.TEXTBEFORE(_xlpm.txt,"\")), _xlpm.after,TRIM(_xlfn.TEXTAFTER(_xlpm.txt,"\")), _xlpm.lastToken, IF( IFERROR(ISNUMBER(--_xlpm.before),FALSE), _xlpm.before, TRIM(_xlfn.TEXTAFTER(_xlpm.before," ",-1)) ), _xlpm.isNum,IFERROR(ISNUMBER(--_xlpm.lastToken),FALSE), IF( OR( LOWER(_xlpm.after)="headflow", LOWER(_xlpm.after)="reach" ), "", IF( _xlpm.isNum, _xlpm.lastToken & " \ " & _xlpm.after, "" ) ) ), "" )
... A9134: -999 | B9134: GP_A_63_NA3_2 | C9134: taf | D9134: SJWAM | E9134: Transmission Link Flow | F9134: =IFERROR( _xlfn.LET( _xlpm.txt,TRIM(B9134), _xlpm.before,TRIM(_xlfn.TEXTBEFORE(_xlpm.txt,"\",-1)), _xlpm.after,_xlfn.TEXTAFTER(_xlpm.txt,"\"), _xlpm.lastToken,TRIM(_xlfn.TEXTAFTER(_xlpm.before," ",-1)), _xlpm.isReach,LOWER(TRIM(_xlpm.after))="reach", _xlpm.cleaned, IF( ISNUMBER(--_xlpm.lastToken), _xlfn.TEXTBEFORE(_xlpm.before," ",-1) & " \ " & _xlpm.after, _xlpm.txt ), IF(_xlpm.isReach,_xlpm.txt,TRIM(_xlpm.cleaned)) ), B9134 ) -> GP_A_63_NA3_2 | G9134: =IFERROR( _xlfn.LET( _xlpm.txt,B9134, _xlpm.before,TRIM(_xlfn.TEXTBEFORE(_xlpm.txt,"\")), _xlpm.after,TRIM(_xlfn.TEXTAFTER(_xlpm.txt,"\")), _xlpm.lastToken, IF( IFERROR(ISNUMBER(--_xlpm.before),FALSE), _xlpm.before, TRIM(_xlfn.TEXTAFTER(_xlpm.before," ",-1)) ), _xlpm.isNum,IFERROR(ISNUMBER(--_xlpm.lastToken),FALSE), IF( OR( LOWER(_xlpm.after)="headflow", LOWER(_xlpm.after)="reach" ), "", IF( _xlpm.isNum, _xlpm.lastToken & " \ " & _xlpm.after, "" ) ) ), "" )

Sheet WEAP Favorites
A1: CalSim Kind | B1: WEAP Favorite Name | C1: CSV File | D1: WEAP Location | E1: Notes
A2: ALIAS
A3: APPLIED-WATER | B3: Theoretical Catchment Irrigation Demand | C3: Theoretical_Catchment_Irrigation_Demand.csv | D3: Demand/Theoretical Catchment Irrigation Demand | E3: Select all, level 1, and make sure the units are Thousand Acre Feet (or CFS)
A4: CHANGE_STORAGE
A5: CHANNEL | B5: Streamflow | C5: Streamflow.csv | D5: Supply and Resources/River/Streamflow | E5: Select all rivers and make sure the units are Thousand Acre Feet (or CFS); name it Streamflow
A6: CHANNEL-SEEPAGE | E6: Unsure if same as river-seepage
A7: CLOSURE-TERM | E7: Included in streamflow (mapping might be incorrect)
A8: CONSUMPTIVE-USE
A9: DEEP-PERCOLATION | E9: Unsure
A10: DELIVERY-CVP | E10: Included in transmission link flow (not in mapping tab)
A11: DELIVERY-LOSS | D11: Supply and Resources/Transmission Link/Loss from Area | E11: Unsure
A12: DELIVERY-SHORTAGE-CVP | E12: Unsure
A13: DELIVERY-SHORTAGE-SWP | E13: Unsure
A14: DICU_FLOW
A15: DIVERSION | B15: Transmission Link Flow | C15: Transmission_Link_Flow.csv | D15: Supply and Resources/Transmission Link/Flow | E15: Select all and make sure the units are Thousand Acre Feet (or CFS)
A16: DP-FLOW
A17: DRAIN-GW
A18: EI-RATIO-STD
A19: EVAPORATION | B19: Reservoir Net Evaporation | C19: Reservoir_Net_Evaporation.csv | D19: Supply and Resources/Reservoir/Net Evaporation | E19: Select all and make sure the units are Thousand Acre Feet (or CFS)
A20: EVAPORATION-RATE
A21: EXPORT-LIMIT
A22: EXPORT-PRJ
A23: FLOW
A24: FLOW-ADD-INSTREAM
A25: FLOW-ADDITIONAL-INSTREAM
A26: FLOW-CHANNEL
A27: FLOW-DELIVERY
A28: FLOW-EXCESS-INSTREAM
A29: FLOW-INFLOW
A30: FLOW-MIN-INSTREAM | B30: Instream Flow Requirement | C30: Instream_Flow_Requirement.csv | D30: Demand/Instream Flow Requirement | E30: Select all and make sure the units are Thousand Acre Feet (or CFS)
A31: FLOW-REQ-MRDO
A32: FLOW-REQ-X2CHS
A33: FLOW-REQ-X2CNF
A34: FLOW-REQ-X2ROE
A35: FLOW-UNIMPAIRED
A36: FLOW-VA
A37: GATE-DAYS-OPEN
A38: GW-FLOW
A39: GW-PUMPING | E39: Included in transmission link flow
A40: IBU
A41: INDEX
A42: INFLOW | E42: Included in streamflow
A43: IRR
A44: LOSS
A45: PERCENT-DELIVERY
A46: PRECIP
A47: PUMPING
A48: RETURN-FLOW | B48: Return Link Flow | C48: Return_Link_Flow.csv | D48: Supply and Resources/Return Link/Flow | E48: Select all and make sure the units are Thousand Acre Feet (or CFS)
A49: RIVER-SEEPAGE | E49: Unsure if included in GW inflows outflows
A50: RIVER-SPILLS | E50: Included in streamflow
A51: RULE
A52: RULECURVE
A53: SALINITY
A54: SALINITY-EC
A55: STORAGE | B55: Reservoir Storage Volume | C55: Reservoir_Storage_Volume.csv | D55: Supply and Resources/Reservoir/Storage Volume | E55: Select all and make sure the units are Thousand Acre Feet (or CFS)
A56: STORAGE-CHANGE
A57: STORAGE-LEVEL
A58: STORAGE-WDL
A59: STREAM-GAIN | D59: Supply and Resources/Groundwater/Groundwater Inflows and Outflows | E59: Unsure
A60: SURFACE-RUNOFF | E60: Unsure
A61: SW-DELIVERY-GROSS | E61: Unsure
A62: SW-DELIVERY-NET | E62: Unsure
A63: SWP-DELIVERY | E63: Included in transmission link flow (not in mapping tab)
A64: TAILWATER
A65: UNUSED-FS
A66: UNUSED-SS
A67: URBAN-DEMAND | D67: Demand/Water Demand | E67: Unsure
A68: UWFE
A69: VA-FLOW
A70: VA-VOLUME
A71: VOLUME-AUGMENTATION
A72: WASTEWATER | D72: Water Quality/Wastewater Treatment Plant Inflows and Outflows | E72: Unsure
A73: WATERYEARTYPE | B73: Sac WYT | C73: Sac_WYT.csv | D73: Other Assumptions/Ops/Hydrologic Indices/Sac403030/SacWYT/Sac WYT OctSep | E73: SacWAM model; name it Sac WYT
A74: WATERYEARTYPE | B74: SJR WYT | C74: SJR_WYT.csv | D74: Other Assumptions/San Joaquin Model/Hydrologic Indices/SJRRP/SJRR_WYT | E74: SJWAM model; name it SJR WYT
A75: X2-POSITION-PREV | D75: Other Assumptions/Ops/Delta Salinity/X2/PrevPosition | E75: Doesn't have ObjID

Sheet DU Map
A1: WEAP DU | B1: CalSim DU or Validation Variable
A2: 02_NA | B2: 02_NA
A3: 02_PA | B3: 02_PA
A4: 02_SA | B4: 02_SA
A5: 03_NA | B5: 03_NA
A6: 03_PA | B6: 03_PA
A7: 03_SA | B7: 03_SA
A8: 04_06_NA1 | B8: 06_PA
A9: 04_06_NA2 | B9: 04_NA
A10: 04_06_PA1 | B10: 04_PA1
A11: 04_06_PA2 | B11: 04_PA2
A12: 05_NA | B12: 05_NA
... A70: 60S_PA2 | B70: 60S_PA2
A71: 61N_NA1
A72: 61N_NA2
A73: 61N_NA3
A74: 61N_NA4
A75: 61N_PA
A76: 61N_PA1 | B76: 61_PA1
A77: 61N_PA3
A78: 61S_NA1
A79: 61S_NA2 | B79: 61_NA2
A80: 61S_NA3 | B80: 61_NA3
A81: 61S_NA4
A82: 61S_NA5 | B82: 61_NA5
A83: 61S_PA2 | B83: 61_PA2
A84: 62_NA1 | B84: 62_NA1
A85: 62_NA2 | B85: 62_NA2
A86: 62_NA3 | B86: 62_NA3
A87: 62_NA4 | B87: 62_NA4
A88: 62_NA5 | B88: 62_NA5
A89: 62_NA6 | B89: 62_NA6
A90: 63_NA1 | B90: 63_NA1
A91: 63_NA2 | B91: 63_NA2
A92: 63_NA3_1 | B92: 63_NA3
A93: 63_NA4 | B93: 63_NA4
... A96: 64_NA2 | B96: 64_NA2
A97: 64_NA3 | C97: Not in CalSim
A98: 64_NA4 | C98: Not in CalSim
A99: 64_PA1 | B99: 64_PA1
A100: 64_PA2 | B100: 64_PA2
A101: 64_PA3 | B101: 64_PA3
A102: 64_XA | B102: 64_XA
A103: 71_NA1 | B103: 71_NA1
A104: 71_NA2 | B104: 71_NA2
A105: 71_NA3 | C105: Not in CalSim
A106: 71_PA1_3 | B106: 71_PA1
A107: 71_PA2 | B107: 71_PA2
A108: 71_PA4 | B108: 71_PA4
A109: 71_PA5 | B109: 71_PA5
A110: 71_PA6 | B110: 71_PA6
A111: 71_PA7 | B111: 71_PA7
A112: 71_PA8 | B112: 71_PA8
A113: 72_NA1 | B113: 72_NA1
A114: 72_NA2 | B114: 72_NA2
A115: 72_PA | B115: 72_PA
A116: 72_XA1 | B116: 72_XA1
A117: 72_XA2 | B117: 72_XA2
... A176: 26_PU5 | B176: 26S_PU2
A177: 50_NU2
A178: 50_PU | B178: 50_PU
A179: 60N_NU1 | B179: 60N_NU1
A180: 60S_NU1 | B180: 60S_NU1
A181: 60S_NU2 | B181: 60S_NU2
A182: 61N_NU1 | B182: 61_NU2
A183: 61N_NU2 | B183: 61_NU3
A184: 61N_NU3
A185: 61N_NU4
A186: 61N_NU5
A187: 61S_NU1
A188: 61S_NU2
A189: 61S_NU3
A190: 61S_NU4
A191: 61S_NU5
A192: 73_NU | B192: 73_NU
A193: 17_PR2 | B193: 17S_PR
A194: 62_NU | B194: 62_NU | C194: Calculated in script
A195: 63_NU | B195: 63_NU | C195: Calculated in script
A196: 64_NU | B196: 64_NU | C196: Calculated in script
A197: 71_NU | B197: 71_NU | C197: Calculated in script
A198: 72_NU | B198: 72_NU | C198: Calculated in script
A199: 61_NA1 | B199: 61_NA1 | C199: Calculated in script
A200: 61_NA4 | B200: 61_NA4 | C200: Calculated in script
A201: 61_PA3 | B201: 61_PA3 | C201: Calculated in script

Sheet Duplicates
A1: CalSim Variable | B1: CalSim Kind | C1: ObjID | D1: WEAP Variable | E1: WEAP Model | F1: WEAP Favorite
A2: {=_xlfn.LET( _xlpm.vars,Mapping!A2:A4999, _xlpm.kind,_xlfn.XLOOKUP(_xlpm.vars,Final!A:A,Final!B:B,""), _xlpm.firstrow,_xlfn.XMATCH(_xlpm.vars,_xlpm.vars), _xlpm.currentrow,_xlfn.SEQUENCE(ROWS(_xlpm.vars)), _xlfn._xlws.FILTER( _xlfn.HSTACK( _xlpm.vars, _xlpm.kind, Mapping!D2:D4999, Mapping!E2:E4999, Mapping!C2:C4999, Mapping!G2:G4999 ), (_xlpm.vars<>"")*(_xlpm.currentrow>_xlpm.firstrow)*(_xlpm.kind<>""), "" ) )} -> C_MFT011 | B2: CHANNEL | C2: 14306 | D2: Hell Hole Tunnel 0 \ Headflow | E2: SacWAM | F2: Streamflow (below node or reach listed)
A3: D_EDC021_EDP003 | B3: DIVERSION | C3: 12628 | D3: El Dorado Akin Powerhouse 0 \ Headflow | E3: SacWAM | F3: Streamflow (below node or reach listed)
A4: D_BSH003_CMN005 | B4: DIVERSION | C4: 13984 | D4: Brush Creek Tunnel 0 \ Headflow | E4: SacWAM | F4: Streamflow (below node or reach listed)
A5: C_CMN006 | B5: CHANNEL | C5: 13975 | D5: Camino Conduit 0 \ Headflow | E5: SacWAM | F5: Streamflow (below node or reach listed)
A6: D_GERLE_SFR006 | B6: DIVERSION | C6: 14042 | D6: Gerle Canal 0 \ Headflow | E6: SacWAM | F6: Streamflow (below node or reach listed)
A7: D_UNVLY_SLV017 | B7: DIVERSION | C7: 14300 | D7: Union Valley Powerhouse 0 \ Headflow | E7: SacWAM | F7: Streamflow (below node or reach listed)
A8: D_SFA040_WRT000 | B8: DIVERSION | C8: 13889 | D8: White Rock Tunnel 0 \ Headflow | E8: SacWAM | F8: Streamflow (below node or reach listed)
A9: D_NFA016_ABT002 | B9: DIVERSION | C9: 8471 | D9: Auburn Tunnel 0 \ Headflow | E9: SacWAM | F9: Streamflow (below node or reach listed)
A10: D_NTOMA_FSC003 | B10: DIVERSION | C10: 14623 | D10: Folsom South Canal 0 \ Headflow | E10: SacWAM | F10: Streamflow (below node or reach listed)
A11: D_LBR002_LBC001 | B11: DIVERSION | C11: 14635 | D11: Lower Boardman Canal 0 \ Headflow | E11: SacWAM | F11: Streamflow (below node or reach listed)
A12: D_BRR050_BEC000 | B12: DIVERSION | C12: 6539 | D12: Bear River Canal 0 \ Headflow | E12: SacWAM | F12: Streamflow (below node or reach listed)
A13: D_LBR002_LBC001 | B13: DIVERSION | C13: 14635 | D13: Lower Boardman Canal 0 \ Headflow | E13: SacWAM | F13: Streamflow (below node or reach listed)
A14: D_SFF011_MNRRH | B14: DIVERSION | C14: 6898 | D14: Miners Ranch Canal 0 \ Headflow | E14: SacWAM | F14: Streamflow (below node or reach listed)
... A50: C_DER001 | B50: CHANNEL | C50: 5911 | D50: Deer Creek Yuba 21 \ I_DER001 Inflow | E50: SacWAM | F50: Streamflow (below node or reach listed)
A51: S_SLUIS | B51: STORAGE | E51: SacWAM | F51: Reservoir Storage Volume
A52: I_TRNTY | B52: INFLOW | C52: 6356 | D52: Trinity River 7 \ I_TRNTY Inflow | E52: SacWAM | F52: Streamflow (below node or reach listed)
A53: I_SHSTA | B53: INFLOW | C53: 5648 | D53: Sacramento River 13 \ I_SHSTA Inflow | E53: SacWAM | F53: Streamflow (below node or reach listed)
A54: I_NHGAN | B54: INFLOW | C54: 5612 | D54: Calaveras River 5 \ I_NHGAN Inflow | E54: SacWAM | F54: Streamflow (below node or reach listed)
A55: D_BKR004_NBA009 | B55: DIVERSION | E55: SacWAM
A56: D_SHSTA_WTPJMS | B56: DIVERSION | C56: 7476 | D56: Transmission Link from Shasta Lake to U_03_PU | E56: SacWAM | F56: Transmission Link Flow
A57: D_SAC296_WTPFTH | B57: DIVERSION | C57: 8459 | D57: Foothill WTP 0 \ Headflow | E57: SacWAM | F57: Streamflow (below node or reach listed)
A58: D_SAC065_WTPBTB | B58: DIVERSION | C58: 7647 | D58: Transmission Link from Sacramento River RM 065 to U_21_PU | E58: SacWAM | F58: Transmission Link Flow
A59: D_SAC050_FPT013 | B59: DIVERSION | C59: 13077 | D59: Freeport Pumping Plant 0 \ Headflow | E59: SacWAM | F59: Streamflow (below node or reach listed)
A60: D_THRMF_11_NU1 | B60: DIVERSION | C60: 7538 | D60: Transmission Link from Power Canal SWP water to U_11_NU1 | E60: SacWAM | F60: Transmission Link Flow
A61: D_THRMF_12_NU1 | B61: DIVERSION | C61: 7550 | D61: Transmission Link from Power Canal SWP water to U_12_13_NU1 | E61: SacWAM | F61: Transmission Link Flow
A62: D_FTR031_WTPCYC | B62: DIVERSION | C62: 7595 | D62: Transmission Link from Feather River RM 031 to U_16_PU | E62: SacWAM | F62: Transmission Link Flow
A63: D_AMR007_WTPFBN | B63: DIVERSION | C63: 7717 | D63: Fairbairn WTP 0 \ Headflow | E63: SacWAM | F63: Streamflow (below node or reach listed)
A64: D_AMR017_WTPBJM | B64: DIVERSION | C64: 7737 | D64: Bajamont WTP 0 \ Headflow | E64: SacWAM | F64: Streamflow (below node or reach listed)
A65: D_FOLSM_WTPEDH | B65: DIVERSION | C65: 14621 | D65: El Dorado Hills WTP 0 \ Headflow | E65: SacWAM | F65: Streamflow (below node or reach listed)
A66: D_FOLSM_WTPFOL | B66: DIVERSION | C66: 7817 | D66: Folsom WTP 0 \ Headflow | E66: SacWAM | F66: Streamflow (below node or reach listed)
A67: D_FOLSM_WTPRSV | B67: DIVERSION | C67: 7795 | D67: Roseville WTP 0 \ Headflow | E67: SacWAM | F67: Streamflow (below node or reach listed)
... A95: C_EBP042 | B95: CHANNEL | C95: 15237 | D95: Eastside Bypass 41 \ Deadman Creek Inflow | E95: SJWAM | F95: Streamflow (below node or reach listed)
A96: C_FCS006 | B96: CHANNEL | E96: SJWAM
A97: C_EBP033 | B97: CHANNEL | E97: SJWAM
A98: D_SJR214_EBP001 | B98: DIVERSION | E98: SJWAM
A99: D_SJR166_EBP032 | B99: DIVERSION | E99: SJWAM
A100: C_CAA003 | B100: CHANNEL | C100: 21633 | D100: California Aqueduct 3 \ Withdrawal Node 44 | E100: SJWAM | F100: Streamflow (below node or reach listed)
A101: C_EBP050 | B101: CHANNEL | E101: SJWAM
A102: C_DMC003 | B102: CHANNEL | C102: 16811 | D102: Delta Mendota Canal 1 \ CVP Boundary Condition | E102: SJWAM | F102: Streamflow (below node or reach listed)
A103: D_DMC007_CAA009 | B103: DIVERSION | E103: SJWAM
A104: D_CAA069_DMC070 | B104: DIVERSION | E104: SJWAM
A105: D_DMC070_CAA069 | B105: DIVERSION | E105: SJWAM
A106: C_SLUIS_CVP | B106: CHANNEL | E106: SJWAM
A107: D_NFS033_SDT000 | B107: DIVERSION | C107: 15434 | D107: North Fork Stanislaus Diversion Tunnel 0 \ Headflow | E107: SJWAM | F107: Streamflow (below node or reach listed)
A108: D_BVC007_BVT000 | B108: DIVERSION | C108: 15455 | D108: Beaver Creek Diversion 0 \ Headflow | E108: SJWAM | F108: Streamflow (below node or reach listed)
A109: C_CVT009 | B109: CHANNEL | C109: 19423 | D109: Collierville Tunnel 3 \ OPS Collierville Tunnel | E109: SJWAM | F109: Streamflow (below node or reach listed)
A110: D_DMC070_VLW008 | B110: DIVERSION | E110: SJWAM
A111: D_CLV037_CACWD | B111: DIVERSION | E111: SJWAM
A112: D_CLV026_60S_PA1 | B112: DIVERSION | E112: SJWAM
A113: D_MCD055_62_NA6 | B113: DIVERSION | E113: SJWAM
A114: D_MCD052_MID021 | B114: DIVERSION | E114: SJWAM
A115: D_MDOTA_64_XA | B115: DIVERSION | E115: SJWAM
A116: D_SJR081_61_NA5 | B116: DIVERSION | E116: SJWAM
A117: D_SJR114_62_NA5 | B117: DIVERSION | E117: SJWAM
A118: D_CLV026_WTPWDH | B118: DIVERSION | E118: SJWAM
A119: D_CLV043_WTPJYL | B119: DIVERSION | E119: SJWAM
A120: D_LJC022_WTPWDH | B120: DIVERSION | E120: SJWAM
A121: D_SJR028_WTPDWS | B121: DIVERSION | E121: SJWAM
... A124: R_WSWWTP_SJR028 | B124: RETURN-FLOW | E124: SJWAM
A125: S_SLUIS | B125: STORAGE | E125: SJWAM | F125: Reservoir Storage Volume
A126: S_SLUIS_CVP | B126: STORAGE | C126: 9779 | D126: CVP San Luis Reservoir | E126: SJWAM | F126: Reservoir Storage Volume
A127: S_SLUIS_SWP | B127: STORAGE | C127: 13211 | D127: SWP San Luis Reservoir | E127: SJWAM | F127: Reservoir Storage Volume
A128: S_NHGAN | B128: STORAGE | C128: 351 | D128: New Hogan Reservoir | E128: SJWAM | F128: Reservoir Storage Volume
